Workbook

Sheet Start Here
B2: Bella's Car Search
B3: Live CARFAX inventory - 2022+ Toyota / Honda / Subaru SUVs within 75 miles of Elkhart, IN
B4: Data pulled | C4: September 14, 2026 from CARFAX used-car listings
B5: Search area | C5: Elkhart, IN 46514 - 75 mile radius (South Bend, Mishawaka, Goshen, Warsaw, Fort Wayne, Kalamazoo, Niles)
B7: The Funnel
B8: Filter applied | C8: Cars remaining
B9: All 2022+ RAV4 / 4Runner / CR-V / HR-V / Outback under $40k in radius | C9: 262
B10: ...that are AWD or 4WD | C10: 234
B11: ...with no accidents reported | C11: 173
B12: ...with service history on file | C12: 168
B13: ...under your mileage cap (Toyota 100k / Honda 70k / Subaru 50k) | C13: 144
B14: ...rated GOOD or GREAT value by CARFAX | C14: 53
B15: ...with heated seats | C15: 36
B16: ...with Apple CarPlay (standard on all of these - no cars lost) | C16: 36
B17: ...that are also Certified Pre-Owned | C17: 6
B18: Certified Pre-Owned is scored as a strong bonus rather than a hard filter, so the Shortlist holds 36 cars and the 6 certified ones float near the top. To see only CPO, set "Require Certified Pre-Owned" to TRUE on the Search Criteria tab.
B20: The Tabs
B21: Shortlist | C21: The 36 cars that meet every one of your criteria, ranked best first. Start here.
B22: Top 10 Compare | C22: The ten best side by side - price, miles, history, features, dealer - for a quick head-to-head.
B23: All Cars | C23: All 262 listings with every data point. Use the filter arrows to explore or loosen a requirement.
B24: Search Criteria | C24: The yellow cells that drive the YES/no "Meets All" column. Change a cap and the whole sheet re-flags.
B25: Scoring Weights | C25: The yellow cells that drive the Score. Change a weight and every car instantly re-ranks.
B26: Model Benchmarks | C26: What each model-year actually sells for here, so you can tell a real deal from a normal price.
B28: How the Score Works
B29: Every car gets six sub-scores from 0 to 100, blended using the weights you set. The weighting follows the priority you gave: reliability first, then price, then mileage, then features.
B30: Component | C30: What it measures | D30: Weight
B31: Reliability & History | C31: CARFAX's model reliability rating, projected repair cost and risk (60%), blended with this specific car's history - accident-free, one owner, personal use, how many service records (40%). | D31: ='Scoring Weights'!B5/100 -> 0.26
B32: Price / Value | C32: The CARFAX Great/Good/Fair value badge (55%), blended with how far below the going rate it is priced (45%). The going rate is fitted from the 262 real listings in this sheet, adjusting for year and mileage. | D32: ='Scoring Weights'!B6/100 -> 0.22
B33: Mileage | C33: Miles against your cap for that make (70%), plus miles-per-year against a 12,000/yr normal (30%). | D33: ='Scoring Weights'!B7/100 -> 0.18
B34: Certified Pre-Owned | C34: 100 if factory certified, 0 if not. | D34: ='Scoring Weights'!B8/100 -> 0.15
B35: Features | C35: Heated steering, sunroof, blind spot, power liftgate, leather, remote start, navigation, wireless charging, parking sensors, power seat, premium audio. | D35: ='Scoring Weights'!B9/100 -> 0.14
B36: Distance | C36: 100 at your doorstep, 0 at 75 miles. Tiebreaker only. | D36: ='Scoring Weights'!B10/100 -> 0.05
B39: Live Counts
B40: Cars meeting every criterion | C40: =COUNTIF('All Cars'!$C$5:$C$266,"YES") -> 36
B41: Of those, Certified Pre-Owned | C41: =COUNTIFS('All Cars'!$C$5:$C$266,"YES",'All Cars'!$K$5:$K$266,"Yes") -> 6
B42: Total listings tracked | C42: =COUNTA('All Cars'!$BC$5:$BC$266) -> 262
B43: These recalculate from the Search Criteria tab, so you can see instantly how many cars survive a change before you go looking.
B45: Before You Buy - Read This
B46: Verify CPO with the dealer | C46: CARFAX flags certification from the dealer feed. Confirm it is manufacturer certified (Toyota TCUV, Honda HondaTrue, Subaru Certified) and not a dealer in-house warranty - the warranty difference is significant.
B47: Features come from the trim, not the VIN | C47: Heated seats, sunroof and the rest are read from the factory equipment list for that trim. It is accurate for standard equipment but can miss optional packages. Confirm on the window sticker.
B48: "Est. Market" is our estimate, not CARFAX | C48: It is a fit across the 262 listings here, adjusting for year and mileage within each model. Treat it as a sanity check on the asking price, not an appraisal.
B49: Prices move | C49: Listings change daily and the good ones go fast. The "Days Listed" and "Price Drop" columns tell you which have been sitting - those have the most negotiating room.
B50: Get a pre-purchase inspection | C50: Even on a certified car with clean history, an independent inspection is the best $150 you will spend.
B51: Mileage caps are yours, not the market | C51: Your Subaru cap of 50k is tight and cuts a lot of Outbacks. If you like the Outback, loosening that cap on the Search Criteria tab opens up more.

Sheet Search Criteria
A1: Search Criteria
A2: Edit the yellow cells. Every YES/NO in the "Meets All" column recalculates from these.
A4: Filter | B4: Value | C4: Notes
A5: Max Price ($) | B5: 40000 | C5: Listing price, before tax/title/doc fee.
A6: Min Year | B6: 2022 | C6: Model year.
A7: Max Distance (mi) | B7: 75 | C7: Straight-line distance from Elkhart, IN 46514.
A8: Require AWD / 4WD | B8: =TRUE() -> TRUE | C8: TRUE or FALSE.
A9: Require No Accidents | B9: =TRUE() -> TRUE | C9: No accident or damage reported to CARFAX.
A10: Require Service History | B10: =TRUE() -> TRUE | C10: At least one service record on file.
A11: Require Heated Seats | B11: =TRUE() -> TRUE | C11: From the trim equipment list.
A12: Require Good/Great Value | B12: =TRUE() -> TRUE | C12: CARFAX's own value badge must be GOOD or GREAT.
A13: Require Certified Pre-Owned | B13: =FALSE() -> FALSE | C13: Set TRUE to see only CPO cars (that leaves 6).
A16: Mileage Cap by Make
A17: Make | B17: Max Miles | C17: Notes
A18: Toyota | B18: 100000 | C18: Your stated cap.
A19: Honda | B19: 70000 | C19: Your stated cap.
A20: Subaru | B20: 50000 | C20: Your stated cap.
A23: Models searched: Toyota 4Runner, Toyota RAV4, Honda HR-V, Honda CR-V, Subaru Outback.
A24: Apple CarPlay is standard on every 2022+ car in all five of these model lines, so it never eliminates anyone. It is shown as a column for confirmation.

Sheet Scoring Weights
A1: Scoring Weights
A2: Edit the yellow cells to re-rank every car instantly. They should add to 100.
A4: Component | B4: Weight | C4: What it measures
A5: Reliability & History | B5: 26 | C5: CARFAX model reliability rating, projected repair cost and risk (60%) blended with this car's own history - accident-free, one owner, personal use, number of service records (40%). Your #1 priority.
A6: Price / Value | B6: 22 | C6: CARFAX Great/Good/Fair value badge (55%) blended with how far the asking price sits below what a same-model car of that year and mileage typically lists for (45%). Your #2 priority.
A7: Mileage | B7: 18 | C7: Miles against your cap for that make (70%) blended with miles-per-year against a 12,000/yr normal (30%). Your #3 priority.
A8: Certified Pre-Owned | B8: 15 | C8: 100 if factory certified, 0 if not. Weighted heavily so CPO cars rise, without excluding good non-CPO cars.
A9: Features | B9: 14 | C9: Heated steering, sunroof, blind spot, power liftgate, leather, remote start, nav, wireless charging, parking sensors, power seat, premium audio. Your #4 priority.
A10: Distance | B10: 5 | C10: 100 at your doorstep down to 0 at 75 miles. Tiebreaker only.
A11: TOTAL | B11: =SUM(B5:B10) -> 100 | C11: =IF(B11=100,"OK - weights add to 100","ADJUST - weights must add to 100, currently "&B11) -> OK - weights add to 100

Sheet Shortlist
A1: Shortlist - 36 Cars That Meet Every Criterion
A2: AWD/4WD, no accidents, service history on file, under your mileage cap for the make, GOOD or GREAT value, heated seats, Apple CarPlay. Ranked best-value first. Certified cars are marked and scored higher.
A4: Rank | B4: Score | C4: Still Meets | D4: Year | E4: Make | F4: Model | G4: Trim | H4: Price | I4: Mileage | J4: Miles/Yr | K4: CPO | L4: Value Badge | M4: vs Market | N4: Reliability | O4: Owners | P4: Service Recs | Q4: Sunroof/Moonroof | R4: Leather | S4: Power Liftgate | T4: Blind Spot | U4: Fuel | V4: MPG | W4: Dealer | X4: City | Y4: Miles Away | Z4: Est. Monthly | AA4: CarFax Link | AB4: Listing URL
A5: =RANK(B5,$B$5:$B$40) -> 1 | B5: ='All Cars'!B5 -> 84 | C5: ='All Cars'!C5 -> YES | D5: ='All Cars'!D5 -> 2026 | E5: ='All Cars'!E5 -> Honda | F5: ='All Cars'!F5 -> CR-V | G5: ='All Cars'!G5 -> EXL | H5: ='All Cars'!H5 -> 35415 | I5: ='All Cars'!I5 -> 12036 | ... K5: ='All Cars'!K5 -> Yes | L5: ='All Cars'!O5 -> GREAT | M5: ='All Cars'!Q5 -> 0.026 | N5: ='All Cars'!R5 -> GREAT | O5: ='All Cars'!U5 -> 1 | P5: ='All Cars'!W5 -> 6 | Q5: ='All Cars'!AA5 -> Yes | R5: ='All Cars'!AD5 -> Yes | S5: ='All Cars'!AC5 -> Yes | T5: ='All Cars'!AB5 -> Yes | U5: ='All Cars'!M5 -> Gasoline | V5: ='All Cars'!N5 -> 29 | W5: ='All Cars'!AN5 -> Gurley Leep Honda | X5: ='All Cars'!AO5 -> Elkhart | Y5: ='All Cars'!AQ5 -> 0.4 | Z5: ='All Cars'!AU5 -> 632.64 | AA5: 2026 Honda CR-V EXL | AB5: https://www.carfax.com/vehicle/2HKRS4H73TH412625
A6: =RANK(B6,$B$5:$B$40) -> 2 | B6: ='All Cars'!B6 -> 72.4 | C6: ='All Cars'!C6 -> YES | D6: ='All Cars'!D6 -> 2025 | E6: ='All Cars'!E6 -> Honda | F6: ='All Cars'!F6 -> CR-V | G6: ='All Cars'!G6 -> EX | H6: ='All Cars'!H6 -> 32809 | I6: ='All Cars'!I6 -> 15682 | ... K6: ='All Cars'!K6 -> Yes | L6: ='All Cars'!O6 -> GREAT | M6: ='All Cars'!Q6 -> 0.062 | N6: ='All Cars'!R6 -> GREAT | O6: ='All Cars'!U6 -> 1 | P6: ='All Cars'!W6 -> 4 | Q6: ='All Cars'!AA6 -> Yes | R6: ='All Cars'!AD6 -> No | S6: ='All Cars'!AC6 -> No | T6: ='All Cars'!AB6 -> Yes | U6: ='All Cars'!M6 -> Gasoline | V6: ='All Cars'!N6 -> 28 | W6: ='All Cars'!AN6 -> Crown Motors Cadillac Buick Honda Mazda | X6: ='All Cars'!AO6 -> Holland | Y6: ='All Cars'!AQ6 -> 71 | Z6: ='All Cars'!AU6 -> 586.09 | AA6: 2025 Honda CR-V EX | AB6: https://www.carfax.com/vehicle/5J6RS4H46SL018336
A7: =RANK(B7,$B$5:$B$40) -> 3 | B7: ='All Cars'!B9 -> 70 | C7: ='All Cars'!C9 -> YES | D7: ='All Cars'!D9 -> 2025 | E7: ='All Cars'!E9 -> Subaru | F7: ='All Cars'!F9 -> Outback | G7: ='All Cars'!G9 -> Limited | H7: ='All Cars'!H9 -> 32609 | I7: ='All Cars'!I9 -> 31763 | ... K7: ='All Cars'!K9 -> Yes | L7: ='All Cars'!O9 -> GOOD | M7: ='All Cars'!Q9 -> -0.051 | N7: ='All Cars'!R9 -> GREAT | O7: ='All Cars'!U9 -> 1 | P7: ='All Cars'!W9 -> 6 | Q7: ='All Cars'!AA9 -> Yes | R7: ='All Cars'!AD9 -> Yes | S7: ='All Cars'!AC9 -> Yes | T7: ='All Cars'!AB9 -> Yes | U7: ='All Cars'!M9 -> Gasoline | V7: ='All Cars'!N9 -> 28 | W7: ='All Cars'!AN9 -> Fox Maple Hill | X7: ='All Cars'!AO9 -> Kalamazoo | Y7: ='All Cars'!AQ9 -> 42.8 | Z7: ='All Cars'!AU9 -> 582.51 | AA7: 2025 Subaru Outback Limited | AB7: https://www.carfax.com/vehicle/4S4BTANC7S3132470
A8: =RANK(B8,$B$5:$B$40) -> 4 | B8: ='All Cars'!B12 -> 69 | C8: ='All Cars'!C12 -> YES | D8: ='All Cars'!D12 -> 2024 | E8: ='All Cars'!E12 -> Honda | F8: ='All Cars'!F12 -> CR-V | G8: ='All Cars'!G12 -> Sport | H8: ='All Cars'!H12 -> 33809 | I8: ='All Cars'!I12 -> 25381 | ... K8: ='All Cars'!K12 -> Yes | L8: ='All Cars'!O12 -> GOOD | M8: ='All Cars'!Q12 -> -0.02 | N8: ='All Cars'!R12 -> GREAT | O8: ='All Cars'!U12 -> 1 | P8: ='All Cars'!W12 -> 6 | Q8: ='All Cars'!AA12 -> Yes | R8: ='All Cars'!AD12 -> Yes | S8: ='All Cars'!AC12 -> No | T8: ='All Cars'!AB12 -> Yes | U8: ='All Cars'!M12 -> Hybrid | V8: ='All Cars'!N12 -> 37 | W8: ='All Cars'!AN12 -> Crown Motors Cadillac Buick Honda Mazda | X8: ='All Cars'!AO12 -> Holland | Y8: ='All Cars'!AQ12 -> 71 | Z8: ='All Cars'!AU12 -> 603.95 | AA8: 2024 Honda CR-V Sport | AB8: https://www.carfax.com/vehicle/7FARS6H5XRE073206
A9: =RANK(B9,$B$5:$B$40) -> 5 | B9: ='All Cars'!B13 -> 68.1 | C9: ='All Cars'!C13 -> YES | D9: ='All Cars'!D13 -> 2026 | E9: ='All Cars'!E13 -> Honda | F9: ='All Cars'!F13 -> CR-V | G9: ='All Cars'!G13 -> TrailSport | H9: ='All Cars'!H13 -> 35913 | I9: ='All Cars'!I13 -> 9420 | ... K9: ='All Cars'!K13 -> No | L9: ='All Cars'!O13 -> GREAT | M9: ='All Cars'!Q13 -> 0.017 | N9: ='All Cars'!R13 -> n/a | O9: ='All Cars'!U13 -> 1 | P9: ='All Cars'!W13 -> 3 | Q9: ='All Cars'!AA13 -> Yes | R9: ='All Cars'!AD13 -> Yes | S9: ='All Cars'!AC13 -> Yes | T9: ='All Cars'!AB13 -> Yes | U9: ='All Cars'!M13 -> Hybrid | V9: ='All Cars'!N13 -> 35 | W9: ='All Cars'!AN13 -> Gurley Leep Kia | X9: ='All Cars'!AO13 -> Mishawaka | Y9: ='All Cars'!AQ13 -> 11 | Z9: ='All Cars'!AU13 -> 641.53 | AA9: 2026 Honda CR-V TrailSport | AB9: https://www.carfax.com/vehicle/7FARS6H69TE031075
A10: =RANK(B10,$B$5:$B$40) -> 6 | B10: ='All Cars'!B17 -> 66.6 | C10: ='All Cars'!C17 -> YES | D10: ='All Cars'!D17 -> 2023 | E10: ='All Cars'!E17 -> Honda | F10: ='All Cars'!F17 -> CR-V | G10: ='All Cars'!G17 -> Sport Touring | H10: ='All Cars'!H17 -> 32864 | I10: ='All Cars'!I17 -> 34991 | ... K10: ='All Cars'!K17 -> No | L10: ='All Cars'!O17 -> GREAT | M10: ='All Cars'!Q17 -> -0.048 | N10: ='All Cars'!R17 -> n/a | O10: ='All Cars'!U17 -> 2 | P10: ='All Cars'!W17 -> 10 | Q10: ='All Cars'!AA17 -> Yes | R10: ='All Cars'!AD17 -> Yes | S10: ='All Cars'!AC17 -> Yes | T10: ='All Cars'!AB17 -> Yes | U10: ='All Cars'!M17 -> Hybrid | V10: ='All Cars'!N17 -> 37 | W10: ='All Cars'!AN17 -> Gurley Leep Hyundai Subaru | X10: ='All Cars'!AO17 -> Mishawaka | Y10: ='All Cars'!AQ17 -> 10.8 | Z10: ='All Cars'!AU17 -> 587.07 | AA10: 2023 Honda CR-V Sport Touring | AB10: https://www.carfax.com/vehicle/5J6RS6H93PL004196
A11: =RANK(B11,$B$5:$B$40) -> 7 | B11: ='All Cars'!B18 -> 66.5 | C11: ='All Cars'!C18 -> YES | D11: ='All Cars'!D18 -> 2025 | E11: ='All Cars'!E18 -> Honda | F11: ='All Cars'!F18 -> CR-V | G11: ='All Cars'!G18 -> EX | H11: ='All Cars'!H18 -> 32809 | I11: ='All Cars'!I18 -> 23351 | ... K11: ='All Cars'!K18 -> Yes | L11: ='All Cars'!O18 -> GOOD | M11: ='All Cars'!Q18 -> 0.047 | N11: ='All Cars'!R18 -> GREAT | O11: ='All Cars'!U18 -> 1 | P11: ='All Cars'!W18 -> 3 | Q11: ='All Cars'!AA18 -> Yes | R11: ='All Cars'!AD18 -> No | S11: ='All Cars'!AC18 -> No | T11: ='All Cars'!AB18 -> Yes | U11: ='All Cars'!M18 -> Gasoline | V11: ='All Cars'!N18 -> 28 | W11: ='All Cars'!AN18 -> Crown Motors Cadillac Buick Honda Mazda | X11: ='All Cars'!AO18 -> Holland | Y11: ='All Cars'!AQ18 -> 71 | Z11: ='All Cars'!AU18 -> 586.09 | AA11: 2025 Honda CR-V EX | AB11: https://www.carfax.com/vehicle/7FARS4H4XSE002962
A12: =RANK(B12,$B$5:$B$40) -> 8 | B12: ='All Cars'!B19 -> 66.1 | C12: ='All Cars'!C19 -> YES | D12: ='All Cars'!D19 -> 2025 | E12: ='All Cars'!E19 -> Honda | F12: ='All Cars'!F19 -> CR-V | G12: ='All Cars'!G19 -> Sport-L | H12: ='All Cars'!H19 -> 34798 | I12: ='All Cars'!I19 -> 20222 | ... K12: ='All Cars'!K19 -> No | L12: ='All Cars'!O19 -> GREAT | M12: ='All Cars'!Q19 -> -0.004 | N12: ='All Cars'!R19 -> n/a | O12: ='All Cars'!U19 -> 1 | P12: ='All Cars'!W19 -> 7 | Q12: ='All Cars'!AA19 -> Yes | R12: ='All Cars'!AD19 -> Yes | S12: ='All Cars'!AC19 -> Yes | T12: ='All Cars'!AB19 -> Yes | U12: ='All Cars'!M19 -> Hybrid | V12: ='All Cars'!N19 -> 37 | W12: ='All Cars'!AN19 -> Jordan Lexus of Mishawaka | X12: ='All Cars'!AO19 -> Mishawaka | Y12: ='All Cars'!AQ19 -> 11.1 | Z12: ='All Cars'!AU19 -> 621.62 | AA12: 2025 Honda CR-V Sport-L | AB12: https://www.carfax.com/vehicle/7FARS6H82SE006423
A13: =RANK(B13,$B$5:$B$40) -> 9 | B13: ='All Cars'!B22 -> 64.6 | C13: ='All Cars'!C22 -> YES | D13: ='All Cars'!D22 -> 2024 | E13: ='All Cars'!E22 -> Toyota | F13: ='All Cars'!F22 -> RAV4 | G13: ='All Cars'!G22 -> Limited Edition | H13: ='All Cars'!H22 -> 39338 | I13: ='All Cars'!I22 -> 17459 | ... K13: ='All Cars'!K22 -> No | L13: ='All Cars'!O22 -> GOOD | M13: ='All Cars'!Q22 -> -0.137 | N13: ='All Cars'!R22 -> n/a | O13: ='All Cars'!U22 -> 1 | P13: ='All Cars'!W22 -> 5 | Q13: ='All Cars'!AA22 -> Yes | R13: ='All Cars'!AD22 -> Yes | S13: ='All Cars'!AC22 -> Yes | T13: ='All Cars'!AB22 -> Yes | U13: ='All Cars'!M22 -> Gasoline | V13: ='All Cars'!N22 -> 28 | W13: ='All Cars'!AN22 -> Gurley Leep Buick GMC Cadillac | X13: ='All Cars'!AO22 -> Mishawaka | Y13: ='All Cars'!AQ22 -> 10.7 | Z13: ='All Cars'!AU22 -> 702.72 | AA13: 2024 Toyota RAV4 Limited Edition | AB13: https://www.carfax.com/vehicle/2T3N1RFV3RW451961
A14: =RANK(B14,$B$5:$B$40) -> 10 | B14: ='All Cars'!B23 -> 64.5 | C14: ='All Cars'!C23 -> YES | D14: ='All Cars'!D23 -> 2024 | E14: ='All Cars'!E23 -> Honda | F14: ='All Cars'!F23 -> CR-V | G14: ='All Cars'!G23 -> Sport-L | H14: ='All Cars'!H23 -> 35190 | I14: ='All Cars'!I23 -> 23100 | ... K14: ='All Cars'!K23 -> No | L14: ='All Cars'!O23 -> GREAT | M14: ='All Cars'!Q23 -> -0.056 | N14: ='All Cars'!R23 -> n/a | O14: ='All Cars'!U23 -> 2 | P14: ='All Cars'!W23 -> 10 | Q14: ='All Cars'!AA23 -> Yes | R14: ='All Cars'!AD23 -> Yes | S14: ='All Cars'!AC23 -> Yes | T14: ='All Cars'!AB23 -> Yes | U14: ='All Cars'!M23 -> Hybrid | V14: ='All Cars'!N23 -> 37 | W14: ='All Cars'!AN23 -> Zeigler Ford Lincoln Elkhart | X14: ='All Cars'!AO23 -> Elkhart | Y14: ='All Cars'!AQ23 -> 3.1 | Z14: ='All Cars'!AU23 -> 628.62 | AA14: 2024 Honda CR-V Sport-L | AB14: https://www.carfax.com/vehicle/7FARS6H8XRE020161
A15: =RANK(B15,$B$5:$B$40) -> 11 | B15: ='All Cars'!B24 -> 63.9 | C15: ='All Cars'!C24 -> YES | D15: ='All Cars'!D24 -> 2023 | E15: ='All Cars'!E24 -> Honda | F15: ='All Cars'!F24 -> CR-V | G15: ='All Cars'!G24 -> EXL | H15: ='All Cars'!H24 -> 32149 | I15: ='All Cars'!I24 -> 29404 | ... K15: ='All Cars'!K24 -> No | L15: ='All Cars'!O24 -> GOOD | M15: ='All Cars'!Q24 -> -0.013 | N15: ='All Cars'!R24 -> GREAT | O15: ='All Cars'!U24 -> 2 | P15: ='All Cars'!W24 -> 13 | Q15: ='All Cars'!AA24 -> Yes | R15: ='All Cars'!AD24 -> Yes | S15: ='All Cars'!AC24 -> Yes | T15: ='All Cars'!AB24 -> Yes | U15: ='All Cars'!M24 -> Gasoline | V15: ='All Cars'!N24 -> 29 | W15: ='All Cars'!AN24 -> Jordan Ford | X15: ='All Cars'!AO24 -> Mishawaka | Y15: ='All Cars'!AQ24 -> 10.7 | Z15: ='All Cars'!AU24 -> 574.3 | AA15: 2023 Honda CR-V EXL | AB15: https://www.carfax.com/vehicle/5J6RS4H76PL000890
A16: =RANK(B16,$B$5:$B$40) -> 12 | B16: ='All Cars'!B27 -> 63.7 | C16: ='All Cars'!C27 -> YES | D16: ='All Cars'!D27 -> 2024 | E16: ='All Cars'!E27 -> Honda | F16: ='All Cars'!F27 -> CR-V | G16: ='All Cars'!G27 -> Sport Touring | H16: ='All Cars'!H27 -> 35270 | I16: ='All Cars'!I27 -> 34486 | ... K16: ='All Cars'!K27 -> No | L16: ='All Cars'!O27 -> GREAT | M16: ='All Cars'!Q27 -> -0.084 | N16: ='All Cars'!R27 -> n/a | O16: ='All Cars'!U27 -> 1 | P16: ='All Cars'!W27 -> 10 | Q16: ='All Cars'!AA27 -> Yes | R16: ='All Cars'!AD27 -> Yes | S16: ='All Cars'!AC27 -> Yes | T16: ='All Cars'!AB27 -> Yes | U16: ='All Cars'!M27 -> Hybrid | V16: ='All Cars'!N27 -> 37 | W16: ='All Cars'!AN27 -> Signature Toyota Hyundai | X16: ='All Cars'!AO27 -> Benton Harbor | Y16: ='All Cars'!AQ27 -> 34.7 | Z16: ='All Cars'!AU27 -> 630.05 | AA16: 2024 Honda CR-V Sport Touring | AB16: https://www.carfax.com/vehicle/7FARS6H92RE014122
A17: =RANK(B17,$B$5:$B$40) -> 13 | B17: ='All Cars'!B29 -> 63.2 | C17: ='All Cars'!C29 -> YES | D17: ='All Cars'!D29 -> 2024 | E17: ='All Cars'!E29 -> Honda | F17: ='All Cars'!F29 -> CR-V | G17: ='All Cars'!G29 -> Sport-L | H17: ='All Cars'!H29 -> 34185 | I17: ='All Cars'!I29 -> 34150 | ... K17: ='All Cars'!K29 -> No | L17: ='All Cars'!O29 -> GREAT | M17: ='All Cars'!Q29 -> -0.05 | N17: ='All Cars'!R29 -> n/a | O17: ='All Cars'!U29 -> 1 | P17: ='All Cars'!W29 -> 7 | Q17: ='All Cars'!AA29 -> Yes | R17: ='All Cars'!AD29 -> Yes | S17: ='All Cars'!AC29 -> Yes | T17: ='All Cars'!AB29 -> Yes | U17: ='All Cars'!M29 -> Hybrid | V17: ='All Cars'!N29 -> 37 | W17: ='All Cars'!AN29 -> Gurley Leep Honda | X17: ='All Cars'!AO29 -> Elkhart | Y17: ='All Cars'!AQ29 -> 0.4 | Z17: ='All Cars'!AU29 -> 610.67 | AA17: 2024 Honda CR-V Sport-L | AB17: https://www.carfax.com/vehicle/7FARS6H84RE043984
A18: =RANK(B18,$B$5:$B$40) -> 14 | B18: ='All Cars'!B32 -> 62.9 | C18: ='All Cars'!C32 -> YES | D18: ='All Cars'!D32 -> 2025 | E18: ='All Cars'!E32 -> Toyota | F18: ='All Cars'!F32 -> RAV4 | G18: ='All Cars'!G32 -> XLE | H18: ='All Cars'!H32 -> 36252 | I18: ='All Cars'!I32 -> 14982 | ... K18: ='All Cars'!K32 -> No | L18: ='All Cars'!O32 -> GREAT | M18: ='All Cars'!Q32 -> -0.008 | N18: ='All Cars'!R32 -> GREAT | O18: ='All Cars'!U32 -> 1 | P18: ='All Cars'!W32 -> 4 | Q18: ='All Cars'!AA32 -> Yes | R18: ='All Cars'!AD32 -> No | S18: ='All Cars'!AC32 -> No | T18: ='All Cars'!AB32 -> Yes | U18: ='All Cars'!M32 -> Hybrid | V18: ='All Cars'!N32 -> 39 | W18: ='All Cars'!AN32 -> Michiana Chrysler Dodge Jeep Ram Fiat | X18: ='All Cars'!AO32 -> Mishawaka | Y18: ='All Cars'!AQ32 -> 11 | Z18: ='All Cars'!AU32 -> 647.59 | AA18: 2025 Toyota RAV4 XLE | AB18: https://www.carfax.com/vehicle/4T3RWRFV4SU211732
A19: =RANK(B19,$B$5:$B$40) -> 15 | B19: ='All Cars'!B33 -> 62.7 | C19: ='All Cars'!C33 -> YES | D19: ='All Cars'!D33 -> 2025 | E19: ='All Cars'!E33 -> Toyota | F19: ='All Cars'!F33 -> RAV4 | G19: ='All Cars'!G33 -> XLE | H19: ='All Cars'!H33 -> 35719 | I19: ='All Cars'!I33 -> 54139 | ... K19: ='All Cars'!K33 -> Yes | L19: ='All Cars'!O33 -> GOOD | M19: ='All Cars'!Q33 -> -0.087 | N19: ='All Cars'!R33 -> GREAT | O19: ='All Cars'!U33 -> 1 | P19: ='All Cars'!W33 -> 6 | Q19: ='All Cars'!AA33 -> Yes | R19: ='All Cars'!AD33 -> No | S19: ='All Cars'!AC33 -> No | T19: ='All Cars'!AB33 -> Yes | U19: ='All Cars'!M33 -> Hybrid | V19: ='All Cars'!N33 -> 39 | W19: ='All Cars'!AN33 -> Crown Toyota Volkswagen | X19: ='All Cars'!AO33 -> Holland | Y19: ='All Cars'!AQ33 -> 74.7 | Z19: ='All Cars'!AU33 -> 638.07 | AA19: 2025 Toyota RAV4 XLE | AB19: https://www.carfax.com/vehicle/JTMRWRFV5SD591595
A20: =RANK(B20,$B$5:$B$40) -> 16 | B20: ='All Cars'!B35 -> 62.1 | C20: ='All Cars'!C35 -> YES | D20: ='All Cars'!D35 -> 2025 | E20: ='All Cars'!E35 -> Subaru | F20: ='All Cars'!F35 -> Outback | G20: ='All Cars'!G35 -> Onyx Edition | H20: ='All Cars'!H35 -> 31233 | I20: ='All Cars'!I35 -> 16159 | ... K20: ='All Cars'!K35 -> No | L20: ='All Cars'!O35 -> GREAT | M20: ='All Cars'!Q35 -> 0.045 | N20: ='All Cars'!R35 -> GOOD | O20: ='All Cars'!U35 -> 1 | P20: ='All Cars'!W35 -> 6 | Q20: ='All Cars'!AA35 -> Yes | R20: ='All Cars'!AD35 -> Yes | S20: ='All Cars'!AC35 -> Yes | T20: ='All Cars'!AB35 -> Yes | U20: ='All Cars'!M35 -> Gasoline | V20: ='All Cars'!N35 -> 28 | W20: ='All Cars'!AN35 -> Toyota of Warsaw | X20: ='All Cars'!AO35 -> Warsaw | Y20: ='All Cars'!AQ35 -> 31.9 | Z20: ='All Cars'!AU35 -> 557.93 | AA20: 2025 Subaru Outback Onyx Edition | AB20: https://www.carfax.com/vehicle/4S4BTALC4S3182780
A21: =RANK(B21,$B$5:$B$40) -> 17 | B21: ='All Cars'!B41 -> 61.1 | C21: ='All Cars'!C41 -> YES | D21: ='All Cars'!D41 -> 2025 | E21: ='All Cars'!E41 -> Honda | F21: ='All Cars'!F41 -> CR-V | G21: ='All Cars'!G41 -> Sport-L | H21: ='All Cars'!H41 -> 35094 | I21: ='All Cars'!I41 -> 29734 | ... K21: ='All Cars'!K41 -> No | L21: ='All Cars'!O41 -> GREAT | M21: ='All Cars'!Q41 -> -0.032 | N21: ='All Cars'!R41 -> n/a | O21: ='All Cars'!U41 -> 2 | P21: ='All Cars'!W41 -> 9 | Q21: ='All Cars'!AA41 -> Yes | R21: ='All Cars'!AD41 -> Yes | S21: ='All Cars'!AC41 -> Yes | T21: ='All Cars'!AB41 -> Yes | U21: ='All Cars'!M41 -> Hybrid | V21: ='All Cars'!N41 -> 37 | W21: ='All Cars'!AN41 -> Gurley Leep Honda | X21: ='All Cars'!AO41 -> Elkhart | Y21: ='All Cars'!AQ41 -> 0.4 | Z21: ='All Cars'!AU41 -> 626.9 | AA21: 2025 Honda CR-V Sport-L | AB21: https://www.carfax.com/vehicle/7FARS6H88SE008967
A22: =RANK(B22,$B$5:$B$40) -> 18 | B22: ='All Cars'!B45 -> 59.4 | C22: ='All Cars'!C45 -> YES | D22: ='All Cars'!D45 -> 2025 | E22: ='All Cars'!E45 -> Subaru | F22: ='All Cars'!F45 -> Outback | G22: ='All Cars'!G45 -> Onyx Edition | H22: ='All Cars'!H45 -> 28149 | I22: ='All Cars'!I45 -> 33731 | ... K22: ='All Cars'!K45 -> No | L22: ='All Cars'!O45 -> GOOD | M22: ='All Cars'!Q45 -> 0.087 | N22: ='All Cars'!R45 -> GREAT | O22: ='All Cars'!U45 -> 1 | P22: ='All Cars'!W45 -> 4 | Q22: ='All Cars'!AA45 -> Yes | R22: ='All Cars'!AD45 -> Yes | S22: ='All Cars'!AC45 -> Yes | T22: ='All Cars'!AB45 -> Yes | U22: ='All Cars'!M45 -> Gasoline | V22: ='All Cars'!N45 -> 28 | W22: ='All Cars'!AN45 -> Gurley Leep Honda | X22: ='All Cars'!AO45 -> Elkhart | Y22: ='All Cars'!AQ45 -> 0.4 | Z22: ='All Cars'!AU45 -> 502.84 | AA22: 2025 Subaru Outback Onyx Edition | AB22: https://www.carfax.com/vehicle/4S4BTALC3S3187209
A23: =RANK(B23,$B$5:$B$40) -> 19 | B23: ='All Cars'!B46 -> 59.2 | C23: ='All Cars'!C46 -> YES | D23: ='All Cars'!D46 -> 2025 | E23: ='All Cars'!E46 -> Toyota | F23: ='All Cars'!F46 -> RAV4 | G23: ='All Cars'!G46 -> XLE Premium | H23: ='All Cars'!H46 -> 39185 | I23: ='All Cars'!I46 -> 15206 | ... K23: ='All Cars'!K46 -> No | L23: ='All Cars'!O46 -> GOOD | M23: ='All Cars'!Q46 -> -0.09 | N23: ='All Cars'!R46 -> GREAT | O23: ='All Cars'!U46 -> 1 | P23: ='All Cars'!W46 -> 5 | Q23: ='All Cars'!AA46 -> Yes | R23: ='All Cars'!AD46 -> Yes | S23: ='All Cars'!AC46 -> Yes | T23: ='All Cars'!AB46 -> Yes | U23: ='All Cars'!M46 -> Gasoline | V23: ='All Cars'!N46 -> 28 | W23: ='All Cars'!AN46 -> Bob Thomas Ford West | X23: ='All Cars'!AO46 -> Fort Wayne | Y23: ='All Cars'!AQ46 -> 59.9 | Z23: ='All Cars'!AU46 -> 699.98 | AA23: 2025 Toyota RAV4 XLE Premium | AB23: https://www.carfax.com/vehicle/2T3A1RFV1SW502278
A24: =RANK(B24,$B$5:$B$40) -> 20 | B24: ='All Cars'!B48 -> 59 | C24: ='All Cars'!C48 -> YES | D24: ='All Cars'!D48 -> 2024 | E24: ='All Cars'!E48 -> Honda | F24: ='All Cars'!F48 -> CR-V | G24: ='All Cars'!G48 -> Sport | H24: ='All Cars'!H48 -> 33249 | I24: ='All Cars'!I48 -> 31775 | ... K24: ='All Cars'!K48 -> No | L24: ='All Cars'!O48 -> GREAT | M24: ='All Cars'!Q48 -> -0.016 | N24: ='All Cars'!R48 -> n/a | O24: ='All Cars'!U48 -> 2 | P24: ='All Cars'!W48 -> 8 | Q24: ='All Cars'!AA48 -> Yes | R24: ='All Cars'!AD48 -> Yes | S24: ='All Cars'!AC48 -> No | T24: ='All Cars'!AB48 -> Yes | U24: ='All Cars'!M48 -> Hybrid | V24: ='All Cars'!N48 -> 37 | W24: ='All Cars'!AN48 -> Jordan Ford | X24: ='All Cars'!AO48 -> Mishawaka | Y24: ='All Cars'!AQ48 -> 10.7 | Z24: ='All Cars'!AU48 -> 593.95 | AA24: 2024 Honda CR-V Sport | AB24: https://www.carfax.com/vehicle/7FARS6H56RE044785
A25: =RANK(B25,$B$5:$B$40) -> 21 | B25: ='All Cars'!B50 -> 58.6 | C25: ='All Cars'!C50 -> YES | D25: ='All Cars'!D50 -> 2025 | E25: ='All Cars'!E50 -> Honda | F25: ='All Cars'!F50 -> CR-V | G25: ='All Cars'!G50 -> Sport-L | H25: ='All Cars'!H50 -> 36597 | I25: ='All Cars'!I50 -> 16535 | ... K25: ='All Cars'!K50 -> No | L25: ='All Cars'!O50 -> GOOD | M25: ='All Cars'!Q50 -> -0.049 | N25: ='All Cars'!R50 -> GREAT | O25: ='All Cars'!U50 -> 2 | P25: ='All Cars'!W50 -> 5 | Q25: ='All Cars'!AA50 -> Yes | R25: ='All Cars'!AD50 -> Yes | S25: ='All Cars'!AC50 -> Yes | T25: ='All Cars'!AB50 -> Yes | U25: ='All Cars'!M50 -> Hybrid | V25: ='All Cars'!N50 -> 37 | W25: ='All Cars'!AN50 -> Gurley Leep Honda | X25: ='All Cars'!AO50 -> Elkhart | Y25: ='All Cars'!AQ50 -> 0.4 | Z25: ='All Cars'!AU50 -> 653.75 | AA25: 2025 Honda CR-V Sport-L | AB25: https://www.carfax.com/vehicle/7FARS6H89SE024319
A26: =RANK(B26,$B$5:$B$40) -> 22 | B26: ='All Cars'!B53 -> 57.9 | C26: ='All Cars'!C53 -> YES | D26: ='All Cars'!D53 -> 2024 | E26: ='All Cars'!E53 -> Subaru | F26: ='All Cars'!F53 -> Outback | G26: ='All Cars'!G53 -> Limited XT | H26: ='All Cars'!H53 -> 30238 | I26: ='All Cars'!I53 -> 25726 | ... K26: ='All Cars'!K53 -> No | L26: ='All Cars'!O53 -> GOOD | M26: ='All Cars'!Q53 -> -0.008 | N26: ='All Cars'!R53 -> GOOD | O26: ='All Cars'!U53 -> 1 | P26: ='All Cars'!W53 -> 9 | Q26: ='All Cars'!AA53 -> Yes | R26: ='All Cars'!AD53 -> Yes | S26: ='All Cars'!AC53 -> Yes | T26: ='All Cars'!AB53 -> Yes | U26: ='All Cars'!M53 -> Gasoline | V26: ='All Cars'!N53 -> 25 | W26: ='All Cars'!AN53 -> Victory Honda Michigan City | X26: ='All Cars'!AO53 -> MICHIGAN CITY | Y26: ='All Cars'!AQ53 -> 46.9 | Z26: ='All Cars'!AU53 -> 540.16 | AA26: 2024 Subaru Outback Limited XT | AB26: https://www.carfax.com/vehicle/4S4BTGND3R3143827
A27: =RANK(B27,$B$5:$B$40) -> 23 | B27: ='All Cars'!B55 -> 57.7 | C27: ='All Cars'!C55 -> YES | D27: ='All Cars'!D55 -> 2022 | E27: ='All Cars'!E55 -> Honda | F27: ='All Cars'!F55 -> CR-V | G27: ='All Cars'!G55 -> EXL | H27: ='All Cars'!H55 -> 27793 | I27: ='All Cars'!I55 -> 49644 | ... K27: ='All Cars'!K55 -> No | L27: ='All Cars'!O55 -> GREAT | M27: ='All Cars'!Q55 -> 0.048 | N27: ='All Cars'!R55 -> GREAT | O27: ='All Cars'!U55 -> 3 | P27: ='All Cars'!W55 -> 12 | Q27: ='All Cars'!AA55 -> Yes | R27: ='All Cars'!AD55 -> Yes | S27: ='All Cars'!AC55 -> Yes | T27: ='All Cars'!AB55 -> Yes | U27: ='All Cars'!M55 -> Gasoline | V27: ='All Cars'!N55 -> 29 | W27: ='All Cars'!AN55 -> Jim Stykemain Ford | X27: ='All Cars'!AO55 -> Garrett | Y27: ='All Cars'!AQ55 -> 50.6 | Z27: ='All Cars'!AU55 -> 496.48 | AA27: 2022 Honda CR-V EXL | AB27: https://www.carfax.com/vehicle/5J6RW2H87NA000701
A28: =RANK(B28,$B$5:$B$40) -> 24 | B28: ='All Cars'!B57 -> 57.4 | C28: ='All Cars'!C57 -> YES | D28: ='All Cars'!D57 -> 2025 | E28: ='All Cars'!E57 -> Honda | F28: ='All Cars'!F57 -> CR-V | G28: ='All Cars'!G57 -> Sport-L | H28: ='All Cars'!H57 -> 35897 | I28: ='All Cars'!I57 -> 27590 | ... K28: ='All Cars'!K57 -> No | L28: ='All Cars'!O57 -> GOOD | M28: ='All Cars'!Q57 -> -0.052 | N28: ='All Cars'!R57 -> GREAT | O28: ='All Cars'!U57 -> 2 | P28: ='All Cars'!W57 -> 12 | Q28: ='All Cars'!AA57 -> Yes | R28: ='All Cars'!AD57 -> Yes | S28: ='All Cars'!AC57 -> Yes | T28: ='All Cars'!AB57 -> Yes | U28: ='All Cars'!M57 -> Hybrid | V28: ='All Cars'!N57 -> 37 | W28: ='All Cars'!AN57 -> Gurley Leep Honda | X28: ='All Cars'!AO57 -> Elkhart | Y28: ='All Cars'!AQ57 -> 0.4 | Z28: ='All Cars'!AU57 -> 641.25 | AA28: 2025 Honda CR-V Sport-L | AB28: https://www.carfax.com/vehicle/7FARS6H86SE022138
A29: =RANK(B29,$B$5:$B$40) -> 25 | B29: ='All Cars'!B58 -> 57.3 | C29: ='All Cars'!C58 -> YES | D29: ='All Cars'!D58 -> 2025 | E29: ='All Cars'!E58 -> Honda | F29: ='All Cars'!F58 -> HR-V | G29: ='All Cars'!G58 -> Sport | H29: ='All Cars'!H58 -> 27095 | I29: ='All Cars'!I58 -> 21310 | ... K29: ='All Cars'!K58 -> No | L29: ='All Cars'!O58 -> GOOD | M29: ='All Cars'!Q58 -> 0.001 | N29: ='All Cars'!R58 -> GREAT | O29: ='All Cars'!U58 -> 1 | P29: ='All Cars'!W58 -> 5 | Q29: ='All Cars'!AA58 -> No | R29: ='All Cars'!AD58 -> Yes | S29: ='All Cars'!AC58 -> No | T29: ='All Cars'!AB58 -> Yes | U29: ='All Cars'!M58 -> Gasoline | V29: ='All Cars'!N58 -> 27 | W29: ='All Cars'!AN58 -> Gurley Leep Honda | X29: ='All Cars'!AO58 -> Elkhart | Y29: ='All Cars'!AQ58 -> 0.4 | Z29: ='All Cars'!AU58 -> 484.01 | AA29: 2025 Honda HR-V Sport | AB29: https://www.carfax.com/vehicle/3CZRZ2H51SM757265
A30: =RANK(B30,$B$5:$B$40) -> 26 | B30: ='All Cars'!B62 -> 56.8 | C30: ='All Cars'!C62 -> YES | D30: ='All Cars'!D62 -> 2025 | E30: ='All Cars'!E62 -> Toyota | F30: ='All Cars'!F62 -> RAV4 | G30: ='All Cars'!G62 -> XLE | H30: ='All Cars'!H62 -> 36395 | I30: ='All Cars'!I62 -> 11639 | ... K30: ='All Cars'!K62 -> No | L30: ='All Cars'!O62 -> GOOD | M30: ='All Cars'!Q62 -> -0.004 | N30: ='All Cars'!R62 -> GREAT | O30: ='All Cars'!U62 -> 2 | P30: ='All Cars'!W62 -> 3 | Q30: ='All Cars'!AA62 -> Yes | R30: ='All Cars'!AD62 -> No | S30: ='All Cars'!AC62 -> Yes | T30: ='All Cars'!AB62 -> Yes | U30: ='All Cars'!M62 -> Gasoline | V30: ='All Cars'!N62 -> 28 | W30: ='All Cars'!AN62 -> Sunshine Toyota | X30: ='All Cars'!AO62 -> Springfield | Y30: ='All Cars'!AQ62 -> 56.8 | Z30: ='All Cars'!AU62 -> 650.14 | AA30: 2025 Toyota RAV4 XLE | AB30: https://www.carfax.com/vehicle/2T3P1RFV7SC536558
A31: =RANK(B31,$B$5:$B$40) -> 27 | B31: ='All Cars'!B64 -> 56.6 | C31: ='All Cars'!C64 -> YES | D31: ='All Cars'!D64 -> 2023 | E31: ='All Cars'!E64 -> Honda | F31: ='All Cars'!F64 -> CR-V | G31: ='All Cars'!G64 -> EX | H31: ='All Cars'!H64 -> 29982 | I31: ='All Cars'!I64 -> 34721 | ... K31: ='All Cars'!K64 -> No | L31: ='All Cars'!O64 -> GOOD | M31: ='All Cars'!Q64 -> 0.044 | N31: ='All Cars'!R64 -> GREAT | O31: ='All Cars'!U64 -> 2 | P31: ='All Cars'!W64 -> 9 | Q31: ='All Cars'!AA64 -> Yes | R31: ='All Cars'!AD64 -> No | S31: ='All Cars'!AC64 -> No | T31: ='All Cars'!AB64 -> Yes | U31: ='All Cars'!M64 -> Gasoline | V31: ='All Cars'!N64 -> 29 | W31: ='All Cars'!AN64 -> Gates Chevrolet South Bend | X31: ='All Cars'!AO64 -> South Bend | Y31: ='All Cars'!AQ64 -> 15.4 | Z31: ='All Cars'!AU64 -> 535.59 | AA31: 2023 Honda CR-V EX | AB31: https://www.carfax.com/vehicle/7FARS4H46PE011892
A32: =RANK(B32,$B$5:$B$40) -> 28 | B32: ='All Cars'!B69 -> 55.8 | C32: ='All Cars'!C69 -> YES | D32: ='All Cars'!D69 -> 2025 | E32: ='All Cars'!E69 -> Honda | F32: ='All Cars'!F69 -> CR-V | G32: ='All Cars'!G69 -> EX | H32: ='All Cars'!H69 -> 30472 | I32: ='All Cars'!I69 -> 41083 | ... K32: ='All Cars'!K69 -> No | L32: ='All Cars'!O69 -> GREAT | M32: ='All Cars'!Q69 -> 0.082 | N32: ='All Cars'!R69 -> GREAT | O32: ='All Cars'!U69 -> 1 | P32: ='All Cars'!W69 -> 5 | Q32: ='All Cars'!AA69 -> Yes | R32: ='All Cars'!AD69 -> No | S32: ='All Cars'!AC69 -> No | T32: ='All Cars'!AB69 -> Yes | U32: ='All Cars'!M69 -> Gasoline | V32: ='All Cars'!N69 -> 28 | W32: ='All Cars'!AN69 -> Zeigler Chrysler Jeep Dodge Ram of Kalamazoo | X32: ='All Cars'!AO69 -> Kalamazoo | Y32: ='All Cars'!AQ69 -> 41.6 | Z32: ='All Cars'!AU69 -> 544.34 | AA32: 2025 Honda CR-V EX | AB32: https://www.carfax.com/vehicle/2HKRS4H49SH430180
A33: =RANK(B33,$B$5:$B$40) -> 29 | B33: ='All Cars'!B77 -> 55.1 | C33: ='All Cars'!C77 -> YES | D33: ='All Cars'!D77 -> 2022 | E33: ='All Cars'!E77 -> Toyota | F33: ='All Cars'!F77 -> 4Runner | G33: ='All Cars'!G77 -> TRD Off Road Premium | H33: ='All Cars'!H77 -> 38104 | I33: ='All Cars'!I77 -> 78455 | ... K33: ='All Cars'!K77 -> No | L33: ='All Cars'!O77 -> GREAT | M33: ='All Cars'!Q77 -> 0 | N33: ='All Cars'!R77 -> GREAT | O33: ='All Cars'!U77 -> 1 | P33: ='All Cars'!W77 -> 17 | Q33: ='All Cars'!AA77 -> Yes | R33: ='All Cars'!AD77 -> No | S33: ='All Cars'!AC77 -> No | T33: ='All Cars'!AB77 -> Yes | U33: ='All Cars'!M77 -> Gasoline | V33: ='All Cars'!N77 -> 17 | W33: ='All Cars'!AN77 -> Gurley Leep Kia | X33: ='All Cars'!AO77 -> Mishawaka | Y33: ='All Cars'!AQ77 -> 11 | Z33: ='All Cars'!AU77 -> 680.67 | AA33: 2022 Toyota 4Runner TRD Off Road Premium | AB33: https://www.carfax.com/vehicle/JTERU5JR4N6047375
A34: =RANK(B34,$B$5:$B$40) -> 30 | B34: ='All Cars'!B78 -> 54.5 | C34: ='All Cars'!C78 -> YES | D34: ='All Cars'!D78 -> 2025 | E34: ='All Cars'!E78 -> Honda | F34: ='All Cars'!F78 -> CR-V | G34: ='All Cars'!G78 -> EX | H34: ='All Cars'!H78 -> 30814 | I34: ='All Cars'!I78 -> 38801 | ... K34: ='All Cars'!K78 -> No | L34: ='All Cars'!O78 -> GREAT | M34: ='All Cars'!Q78 -> 0.076 | N34: ='All Cars'!R78 -> GREAT | O34: ='All Cars'!U78 -> 1 | P34: ='All Cars'!W78 -> 7 | Q34: ='All Cars'!AA78 -> Yes | R34: ='All Cars'!AD78 -> No | S34: ='All Cars'!AC78 -> No | T34: ='All Cars'!AB78 -> Yes | U34: ='All Cars'!M78 -> Gasoline | V34: ='All Cars'!N78 -> 28 | W34: ='All Cars'!AN78 -> Zeigler GMC of Holland | X34: ='All Cars'!AO78 -> Holland | Y34: ='All Cars'!AQ78 -> 74.5 | Z34: ='All Cars'!AU78 -> 550.45 | AA34: 2025 Honda CR-V EX | AB34: https://www.carfax.com/vehicle/2HKRS4H44SH448795
A35: =RANK(B35,$B$5:$B$40) -> 31 | B35: ='All Cars'!B83 -> 54.3 | C35: ='All Cars'!C83 -> YES | D35: ='All Cars'!D83 -> 2022 | E35: ='All Cars'!E83 -> Honda | F35: ='All Cars'!F83 -> CR-V | G35: ='All Cars'!G83 -> EXL | H35: ='All Cars'!H83 -> 28212 | I35: ='All Cars'!I83 -> 54671 | ... K35: ='All Cars'!K83 -> No | L35: ='All Cars'!O83 -> GOOD | M35: ='All Cars'!Q83 -> 0.022 | N35: ='All Cars'!R83 -> GOOD | O35: ='All Cars'!U83 -> 2 | P35: ='All Cars'!W83 -> 17 | Q35: ='All Cars'!AA83 -> Yes | R35: ='All Cars'!AD83 -> Yes | S35: ='All Cars'!AC83 -> Yes | T35: ='All Cars'!AB83 -> Yes | U35: ='All Cars'!M83 -> Hybrid | V35: ='All Cars'!N83 -> 38 | W35: ='All Cars'!AN83 -> Gurley Leep Kia | X35: ='All Cars'!AO83 -> Mishawaka | Y35: ='All Cars'!AQ83 -> 11 | Z35: ='All Cars'!AU83 -> 503.97 | AA35: 2022 Honda CR-V EXL | AB35: https://www.carfax.com/vehicle/5J6RT6H88NL023795
A36: =RANK(B36,$B$5:$B$40) -> 32 | B36: ='All Cars'!B87 -> 53.9 | C36: ='All Cars'!C87 -> YES | D36: ='All Cars'!D87 -> 2024 | E36: ='All Cars'!E87 -> Subaru | F36: ='All Cars'!F87 -> Outback | G36: ='All Cars'!G87 -> Premium | H36: ='All Cars'!H87 -> 25059 | I36: ='All Cars'!I87 -> 33775 | ... K36: ='All Cars'!K87 -> No | L36: ='All Cars'!O87 -> GREAT | M36: ='All Cars'!Q87 -> 0.141 | N36: ='All Cars'!R87 -> GOOD | O36: ='All Cars'!U87 -> 1 | P36: ='All Cars'!W87 -> 4 | Q36: ='All Cars'!AA87 -> Yes | R36: ='All Cars'!AD87 -> Yes | S36: ='All Cars'!AC87 -> No | T36: ='All Cars'!AB87 -> Yes | U36: ='All Cars'!M87 -> Gasoline | V36: ='All Cars'!N87 -> 28 | W36: ='All Cars'!AN87 -> Chevrolet of Merrillville | X36: ='All Cars'!AO87 -> Merrillville | Y36: ='All Cars'!AQ87 -> 71.2 | Z36: ='All Cars'!AU87 -> 447.64 | AA36: 2024 Subaru Outback Premium | AB36: https://www.carfax.com/vehicle/4S4BTAFC6R3136342
A37: =RANK(B37,$B$5:$B$40) -> 33 | B37: ='All Cars'!B93 -> 53.1 | C37: ='All Cars'!C93 -> YES | D37: ='All Cars'!D93 -> 2024 | E37: ='All Cars'!E93 -> Subaru | F37: ='All Cars'!F93 -> Outback | G37: ='All Cars'!G93 -> Onyx Edition | H37: ='All Cars'!H93 -> 29314 | I37: ='All Cars'!I93 -> 37948 | ... K37: ='All Cars'!K93 -> No | L37: ='All Cars'!O93 -> GOOD | M37: ='All Cars'!Q93 -> -0.021 | N37: ='All Cars'!R93 -> GREAT | O37: ='All Cars'!U93 -> 1 | P37: ='All Cars'!W93 -> 11 | Q37: ='All Cars'!AA93 -> Yes | R37: ='All Cars'!AD93 -> Yes | S37: ='All Cars'!AC93 -> Yes | T37: ='All Cars'!AB93 -> Yes | U37: ='All Cars'!M93 -> Gasoline | V37: ='All Cars'!N93 -> 28 | W37: ='All Cars'!AN93 -> Zeigler GMC of Holland | X37: ='All Cars'!AO93 -> Holland | Y37: ='All Cars'!AQ93 -> 74.5 | Z37: ='All Cars'!AU93 -> 523.65 | AA37: 2024 Subaru Outback Onyx Edition | AB37: https://www.carfax.com/vehicle/4S4BTALC5R3189893
A38: =RANK(B38,$B$5:$B$40) -> 34 | B38: ='All Cars'!B100 -> 52.6 | C38: ='All Cars'!C100 -> YES | D38: ='All Cars'!D100 -> 2024 | E38: ='All Cars'!E100 -> Honda | F38: ='All Cars'!F100 -> CR-V | G38: ='All Cars'!G100 -> Sport-L | H38: ='All Cars'!H100 -> 34238 | I38: ='All Cars'!I100 -> 39309 | ... K38: ='All Cars'!K100 -> No | L38: ='All Cars'!O100 -> GOOD | M38: ='All Cars'!Q100 -> -0.064 | N38: ='All Cars'!R100 -> GREAT | O38: ='All Cars'!U100 -> 1 | P38: ='All Cars'!W100 -> 5 | Q38: ='All Cars'!AA100 -> Yes | R38: ='All Cars'!AD100 -> Yes | S38: ='All Cars'!AC100 -> Yes | T38: ='All Cars'!AB100 -> Yes | U38: ='All Cars'!M100 -> Hybrid | V38: ='All Cars'!N100 -> 37 | W38: ='All Cars'!AN100 -> Victory Honda Michigan City | X38: ='All Cars'!AO100 -> MICHIGAN CITY | Y38: ='All Cars'!AQ100 -> 46.9 | Z38: ='All Cars'!AU100 -> 611.61 | AA38: 2024 Honda CR-V Sport-L | AB38: https://www.carfax.com/vehicle/5J6RS6H84RL038433
A39: =RANK(B39,$B$5:$B$40) -> 35 | B39: ='All Cars'!B144 -> 48.7 | C39: ='All Cars'!C144 -> YES | D39: ='All Cars'!D144 -> 2023 | E39: ='All Cars'!E144 -> Subaru | F39: ='All Cars'!F144 -> Outback | G39: ='All Cars'!G144 -> Premium | H39: ='All Cars'!H144 -> 25814 | I39: ='All Cars'!I144 -> 36225 | ... K39: ='All Cars'!K144 -> No | L39: ='All Cars'!O144 -> GOOD | M39: ='All Cars'!Q144 -> 0.052 | N39: ='All Cars'!R144 -> GOOD | O39: ='All Cars'!U144 -> 1 | P39: ='All Cars'!W144 -> 11 | Q39: ='All Cars'!AA144 -> No | R39: ='All Cars'!AD144 -> Yes | S39: ='All Cars'!AC144 -> Yes | T39: ='All Cars'!AB144 -> Yes | U39: ='All Cars'!M144 -> Gasoline | V39: ='All Cars'!N144 -> 28 | W39: ='All Cars'!AN144 -> Zeigler GMC of Holland | X39: ='All Cars'!AO144 -> Holland | Y39: ='All Cars'!AQ144 -> 74.5 | Z39: ='All Cars'!AU144 -> 461.13 | AA39: 2023 Subaru Outback Premium | AB39: https://www.carfax.com/vehicle/4S4BTADC9P3197765
A40: =RANK(B40,$B$5:$B$40) -> 36 | B40: ='All Cars'!B158 -> 47.1 | C40: ='All Cars'!C158 -> YES | D40: ='All Cars'!D158 -> 2024 | E40: ='All Cars'!E158 -> Subaru | F40: ='All Cars'!F158 -> Outback | G40: ='All Cars'!G158 -> Premium | H40: ='All Cars'!H158 -> 26314 | I40: ='All Cars'!I158 -> 39922 | ... K40: ='All Cars'!K158 -> No | L40: ='All Cars'!O158 -> GOOD | M40: ='All Cars'!Q158 -> 0.077 | N40: ='All Cars'!R158 -> GOOD | O40: ='All Cars'!U158 -> 3 | P40: ='All Cars'!W158 -> 11 | Q40: ='All Cars'!AA158 -> Yes | R40: ='All Cars'!AD158 -> Yes | S40: ='All Cars'!AC158 -> Yes | T40: ='All Cars'!AB158 -> Yes | U40: ='All Cars'!M158 -> Gasoline | V40: ='All Cars'!N158 -> 28 | W40: ='All Cars'!AN158 -> Zeigler GMC of Holland | X40: ='All Cars'!AO158 -> Holland | Y40: ='All Cars'!AQ158 -> 74.5 | Z40: ='All Cars'!AU158 -> 470.06 | AA40: 2024 Subaru Outback Premium | AB40: https://www.carfax.com/vehicle/4S4BTAFC1R3240916
A42: "Still Meets" recalculates from the Search Criteria tab. If you tighten a filter, rows that no longer qualify turn red here rather than disappearing - check the All Cars tab for anything new that qualifies.

Sheet Top 10 Compare
A1: Top 10 Head-to-Head
A2: The ten highest-scoring cars from the Shortlist, side by side. Everything here is live-linked to All Cars.
A4: Attribute | B4: #1 2026 Honda CR-V EXL | C4: #2 2025 Honda CR-V EX | D4: #3 2025 Subaru Outback Limited | E4: #4 2024 Honda CR-V Sport | F4: #5 2026 Honda CR-V TrailSport | G4: #6 2023 Honda CR-V Sport Touring | H4: #7 2025 Honda CR-V EX | I4: #8 2025 Honda CR-V Sport-L | J4: #9 2024 Toyota RAV4 Limited Edition | K4: #10 2024 Honda CR-V Sport-L
A5: Score | B5: ='All Cars'!B5 -> 84 | C5: ='All Cars'!B6 -> 72.4 | D5: ='All Cars'!B9 -> 70 | E5: ='All Cars'!B12 -> 69 | F5: ='All Cars'!B13 -> 68.1 | G5: ='All Cars'!B17 -> 66.6 | H5: ='All Cars'!B18 -> 66.5 | I5: ='All Cars'!B19 -> 66.1 | J5: ='All Cars'!B22 -> 64.6 | K5: ='All Cars'!B23 -> 64.5
A6: Year | B6: ='All Cars'!D5 -> 2026 | C6: ='All Cars'!D6 -> 2025 | D6: ='All Cars'!D9 -> 2025 | E6: ='All Cars'!D12 -> 2024 | F6: ='All Cars'!D13 -> 2026 | G6: ='All Cars'!D17 -> 2023 | H6: ='All Cars'!D18 -> 2025 | I6: ='All Cars'!D19 -> 2025 | J6: ='All Cars'!D22 -> 2024 | K6: ='All Cars'!D23 -> 2024
A7: Make | B7: ='All Cars'!E5 -> Honda | C7: ='All Cars'!E6 -> Honda | D7: ='All Cars'!E9 -> Subaru | E7: ='All Cars'!E12 -> Honda | F7: ='All Cars'!E13 -> Honda | G7: ='All Cars'!E17 -> Honda | H7: ='All Cars'!E18 -> Honda | I7: ='All Cars'!E19 -> Honda | J7: ='All Cars'!E22 -> Toyota | K7: ='All Cars'!E23 -> Honda
A8: Model | B8: ='All Cars'!F5 -> CR-V | C8: ='All Cars'!F6 -> CR-V | D8: ='All Cars'!F9 -> Outback | E8: ='All Cars'!F12 -> CR-V | F8: ='All Cars'!F13 -> CR-V | G8: ='All Cars'!F17 -> CR-V | H8: ='All Cars'!F18 -> CR-V | I8: ='All Cars'!F19 -> CR-V | J8: ='All Cars'!F22 -> RAV4 | K8: ='All Cars'!F23 -> CR-V
A9: Trim | B9: ='All Cars'!G5 -> EXL | C9: ='All Cars'!G6 -> EX | D9: ='All Cars'!G9 -> Limited | E9: ='All Cars'!G12 -> Sport | F9: ='All Cars'!G13 -> TrailSport | G9: ='All Cars'!G17 -> Sport Touring | H9: ='All Cars'!G18 -> EX | I9: ='All Cars'!G19 -> Sport-L | J9: ='All Cars'!G22 -> Limited Edition | K9: ='All Cars'!G23 -> Sport-L
A10: Price | B10: ='All Cars'!H5 -> 35415 | C10: ='All Cars'!H6 -> 32809 | D10: ='All Cars'!H9 -> 32609 | E10: ='All Cars'!H12 -> 33809 | F10: ='All Cars'!H13 -> 35913 | G10: ='All Cars'!H17 -> 32864 | H10: ='All Cars'!H18 -> 32809 | I10: ='All Cars'!H19 -> 34798 | J10: ='All Cars'!H22 -> 39338 | K10: ='All Cars'!H23 -> 35190
A11: Mileage | B11: ='All Cars'!I5 -> 12036 | C11: ='All Cars'!I6 -> 15682 | D11: ='All Cars'!I9 -> 31763 | E11: ='All Cars'!I12 -> 25381 | F11: ='All Cars'!I13 -> 9420 | G11: ='All Cars'!I17 -> 34991 | H11: ='All Cars'!I18 -> 23351 | I11: ='All Cars'!I19 -> 20222 | J11: ='All Cars'!I22 -> 17459 | K11: ='All Cars'!I23 -> 23100
A12: Miles/Yr | B12: ='All Cars'!J5 -> 24072 | C12: ='All Cars'!J6 -> 15682 | D12: ='All Cars'!J9 -> 31763 | E12: ='All Cars'!J12 -> 12691 | F12: ='All Cars'!J13 -> 18840 | G12: ='All Cars'!J17 -> 11664 | H12: ='All Cars'!J18 -> 23351 | I12: ='All Cars'!J19 -> 20222 | J12: ='All Cars'!J22 -> 8730 | K12: ='All Cars'!J23 -> 11550
A13: Est. Monthly | B13: ='All Cars'!AU5 -> 632.64 | C13: ='All Cars'!AU6 -> 586.09 | D13: ='All Cars'!AU9 -> 582.51 | E13: ='All Cars'!AU12 -> 603.95 | F13: ='All Cars'!AU13 -> 641.53 | G13: ='All Cars'!AU17 -> 587.07 | H13: ='All Cars'!AU18 -> 586.09 | I13: ='All Cars'!AU19 -> 621.62 | J13: ='All Cars'!AU22 -> 702.72 | K13: ='All Cars'!AU23 -> 628.62
A14: CPO | B14: ='All Cars'!K5 -> Yes | C14: ='All Cars'!K6 -> Yes | D14: ='All Cars'!K9 -> Yes | E14: ='All Cars'!K12 -> Yes | F14: ='All Cars'!K13 -> No | G14: ='All Cars'!K17 -> No | H14: ='All Cars'!K18 -> Yes | I14: ='All Cars'!K19 -> No | J14: ='All Cars'!K22 -> No | K14: ='All Cars'!K23 -> No
A15: Value Badge | B15: ='All Cars'!O5 -> GREAT | C15: ='All Cars'!O6 -> GREAT | D15: ='All Cars'!O9 -> GOOD | E15: ='All Cars'!O12 -> GOOD | F15: ='All Cars'!O13 -> GREAT | G15: ='All Cars'!O17 -> GREAT | H15: ='All Cars'!O18 -> GOOD | I15: ='All Cars'!O19 -> GREAT | J15: ='All Cars'!O22 -> GOOD | K15: ='All Cars'!O23 -> GREAT
A16: Est. Market | B16: ='All Cars'!P5 -> 36351 | C16: ='All Cars'!P6 -> 34961 | D16: ='All Cars'!P9 -> 31035 | E16: ='All Cars'!P12 -> 33153 | F16: ='All Cars'!P13 -> 36532 | G16: ='All Cars'!P17 -> 31351 | H16: ='All Cars'!P18 -> 34432 | I16: ='All Cars'!P19 -> 34648 | J16: ='All Cars'!P22 -> 34583 | K16: ='All Cars'!P23 -> 33311
A17: vs Market | B17: ='All Cars'!Q5 -> 0.026 | C17: ='All Cars'!Q6 -> 0.062 | D17: ='All Cars'!Q9 -> -0.051 | E17: ='All Cars'!Q12 -> -0.02 | F17: ='All Cars'!Q13 -> 0.017 | G17: ='All Cars'!Q17 -> -0.048 | H17: ='All Cars'!Q18 -> 0.047 | I17: ='All Cars'!Q19 -> -0.004 | J17: ='All Cars'!Q22 -> -0.137 | K17: ='All Cars'!Q23 -> -0.056
A18: Reliability | B18: ='All Cars'!R5 -> GREAT | C18: ='All Cars'!R6 -> GREAT | D18: ='All Cars'!R9 -> GREAT | E18: ='All Cars'!R12 -> GREAT | F18: ='All Cars'!R13 -> n/a | G18: ='All Cars'!R17 -> n/a | H18: ='All Cars'!R18 -> GREAT | I18: ='All Cars'!R19 -> n/a | J18: ='All Cars'!R22 -> n/a | K18: ='All Cars'!R23 -> n/a
A19: Repair $/yr | B19: ='All Cars'!S5 -> 190 | C19: ='All Cars'!S6 -> 560 | D19: ='All Cars'!S9 -> 120 | E19: ='All Cars'!S12 -> 600 | F19: ='All Cars'!S13 -> 0 | G19: ='All Cars'!S17 -> 0 | H19: ='All Cars'!S18 -> 840 | I19: ='All Cars'!S19 -> 0 | J19: ='All Cars'!S22 -> 0 | K19: ='All Cars'!S23 -> 0
A20: No Accidents | B20: ='All Cars'!T5 -> Yes | C20: ='All Cars'!T6 -> Yes | D20: ='All Cars'!T9 -> Yes | E20: ='All Cars'!T12 -> Yes | F20: ='All Cars'!T13 -> Yes | G20: ='All Cars'!T17 -> Yes | H20: ='All Cars'!T18 -> Yes | I20: ='All Cars'!T19 -> Yes | J20: ='All Cars'!T22 -> Yes | K20: ='All Cars'!T23 -> Yes
A21: Owners | B21: ='All Cars'!U5 -> 1 | C21: ='All Cars'!U6 -> 1 | D21: ='All Cars'!U9 -> 1 | E21: ='All Cars'!U12 -> 1 | F21: ='All Cars'!U13 -> 1 | G21: ='All Cars'!U17 -> 2 | H21: ='All Cars'!U18 -> 1 | I21: ='All Cars'!U19 -> 1 | J21: ='All Cars'!U22 -> 1 | K21: ='All Cars'!U23 -> 2
A22: Personal Use | B22: ='All Cars'!V5 -> Yes | C22: ='All Cars'!V6 -> Yes | D22: ='All Cars'!V9 -> Yes | E22: ='All Cars'!V12 -> Yes | F22: ='All Cars'!V13 -> Yes | G22: ='All Cars'!V17 -> Yes | H22: ='All Cars'!V18 -> Yes | I22: ='All Cars'!V19 -> Yes | J22: ='All Cars'!V22 -> Yes | K22: ='All Cars'!V23 -> Yes
A23: Service Recs | B23: ='All Cars'!W5 -> 6 | C23: ='All Cars'!W6 -> 4 | D23: ='All Cars'!W9 -> 6 | E23: ='All Cars'!W12 -> 6 | F23: ='All Cars'!W13 -> 3 | G23: ='All Cars'!W17 -> 10 | H23: ='All Cars'!W18 -> 3 | I23: ='All Cars'!W19 -> 7 | J23: ='All Cars'!W22 -> 5 | K23: ='All Cars'!W23 -> 10
A24: Drivetrain | B24: ='All Cars'!L5 -> AWD | C24: ='All Cars'!L6 -> AWD | D24: ='All Cars'!L9 -> AWD | E24: ='All Cars'!L12 -> AWD | F24: ='All Cars'!L13 -> AWD | G24: ='All Cars'!L17 -> AWD | H24: ='All Cars'!L18 -> AWD | I24: ='All Cars'!L19 -> AWD | J24: ='All Cars'!L22 -> AWD | K24: ='All Cars'!L23 -> AWD
A25: Fuel | B25: ='All Cars'!M5 -> Gasoline | C25: ='All Cars'!M6 -> Gasoline | D25: ='All Cars'!M9 -> Gasoline | E25: ='All Cars'!M12 -> Hybrid | F25: ='All Cars'!M13 -> Hybrid | G25: ='All Cars'!M17 -> Hybrid | H25: ='All Cars'!M18 -> Gasoline | I25: ='All Cars'!M19 -> Hybrid | J25: ='All Cars'!M22 -> Gasoline | K25: ='All Cars'!M23 -> Hybrid
A26: MPG | B26: ='All Cars'!N5 -> 29 | C26: ='All Cars'!N6 -> 28 | D26: ='All Cars'!N9 -> 28 | E26: ='All Cars'!N12 -> 37 | F26: ='All Cars'!N13 -> 35 | G26: ='All Cars'!N17 -> 37 | H26: ='All Cars'!N18 -> 28 | I26: ='All Cars'!N19 -> 37 | J26: ='All Cars'!N22 -> 28 | K26: ='All Cars'!N23 -> 37
A27: Heated Seats | B27: ='All Cars'!X5 -> Yes | C27: ='All Cars'!X6 -> Yes | D27: ='All Cars'!X9 -> Yes | E27: ='All Cars'!X12 -> Yes | F27: ='All Cars'!X13 -> Yes | G27: ='All Cars'!X17 -> Yes | H27: ='All Cars'!X18 -> Yes | I27: ='All Cars'!X19 -> Yes | J27: ='All Cars'!X22 -> Yes | K27: ='All Cars'!X23 -> Yes
A28: Heated Steering | B28: ='All Cars'!Z5 -> No | C28: ='All Cars'!Z6 -> No | D28: ='All Cars'!Z9 -> Yes | E28: ='All Cars'!Z12 -> No | F28: ='All Cars'!Z13 -> Yes | G28: ='All Cars'!Z17 -> Yes | H28: ='All Cars'!Z18 -> No | I28: ='All Cars'!Z19 -> No | J28: ='All Cars'!Z22 -> Yes | K28: ='All Cars'!Z23 -> No
A29: Sunroof/Moonroof | B29: ='All Cars'!AA5 -> Yes | C29: ='All Cars'!AA6 -> Yes | D29: ='All Cars'!AA9 -> Yes | E29: ='All Cars'!AA12 -> Yes | F29: ='All Cars'!AA13 -> Yes | G29: ='All Cars'!AA17 -> Yes | H29: ='All Cars'!AA18 -> Yes | I29: ='All Cars'!AA19 -> Yes | J29: ='All Cars'!AA22 -> Yes | K29: ='All Cars'!AA23 -> Yes
A30: Leather | B30: ='All Cars'!AD5 -> Yes | C30: ='All Cars'!AD6 -> No | D30: ='All Cars'!AD9 -> Yes | E30: ='All Cars'!AD12 -> Yes | F30: ='All Cars'!AD13 -> Yes | G30: ='All Cars'!AD17 -> Yes | H30: ='All Cars'!AD18 -> No | I30: ='All Cars'!AD19 -> Yes | J30: ='All Cars'!AD22 -> Yes | K30: ='All Cars'!AD23 -> Yes
A31: Power Liftgate | B31: ='All Cars'!AC5 -> Yes | C31: ='All Cars'!AC6 -> No | D31: ='All Cars'!AC9 -> Yes | E31: ='All Cars'!AC12 -> No | F31: ='All Cars'!AC13 -> Yes | G31: ='All Cars'!AC17 -> Yes | H31: ='All Cars'!AC18 -> No | I31: ='All Cars'!AC19 -> Yes | J31: ='All Cars'!AC22 -> Yes | K31: ='All Cars'!AC23 -> Yes
A32: Blind Spot | B32: ='All Cars'!AB5 -> Yes | C32: ='All Cars'!AB6 -> Yes | D32: ='All Cars'!AB9 -> Yes | E32: ='All Cars'!AB12 -> Yes | F32: ='All Cars'!AB13 -> Yes | G32: ='All Cars'!AB17 -> Yes | H32: ='All Cars'!AB18 -> Yes | I32: ='All Cars'!AB19 -> Yes | J32: ='All Cars'!AB22 -> Yes | K32: ='All Cars'!AB23 -> Yes
A33: Remote Start | B33: ='All Cars'!AE5 -> Yes | C33: ='All Cars'!AE6 -> No | D33: ='All Cars'!AE9 -> No | E33: ='All Cars'!AE12 -> No | F33: ='All Cars'!AE13 -> Yes | G33: ='All Cars'!AE17 -> Yes | H33: ='All Cars'!AE18 -> No | I33: ='All Cars'!AE19 -> Yes | J33: ='All Cars'!AE22 -> No | K33: ='All Cars'!AE23 -> No
A34: Navigation | B34: ='All Cars'!AF5 -> No | C34: ='All Cars'!AF6 -> No | D34: ='All Cars'!AF9 -> Yes | E34: ='All Cars'!AF12 -> No | F34: ='All Cars'!AF13 -> No | G34: ='All Cars'!AF17 -> Yes | H34: ='All Cars'!AF18 -> No | I34: ='All Cars'!AF19 -> No | J34: ='All Cars'!AF22 -> Yes | K34: ='All Cars'!AF23 -> No
A35: Wireless Charging | B35: ='All Cars'!AG5 -> Yes | C35: ='All Cars'!AG6 -> No | D35: ='All Cars'!AG9 -> No | E35: ='All Cars'!AG12 -> No | F35: ='All Cars'!AG13 -> Yes | G35: ='All Cars'!AG17 -> Yes | H35: ='All Cars'!AG18 -> No | I35: ='All Cars'!AG19 -> Yes | J35: ='All Cars'!AG22 -> No | K35: ='All Cars'!AG23 -> Yes
A36: Ext Color | B36: ='All Cars'!AK5 -> Gray | C36: ='All Cars'!AK6 -> Silver | D36: ='All Cars'!AK9 -> Black | E36: ='All Cars'!AK12 -> Blue | F36: ='All Cars'!AK13 -> Gray | G36: ='All Cars'!AK17 -> Blue | H36: ='All Cars'!AK18 -> Silver | I36: ='All Cars'!AK19 -> Silver | J36: ='All Cars'!AK22 -> White | K36: ='All Cars'!AK23 -> Gray
A37: Int Color | B37: ='All Cars'!AL5 -> Black | C37: ='All Cars'!AL6 -> Gray | D37: ='All Cars'!AL9 -> White | E37: ='All Cars'!AL12 -> Black | F37: ='All Cars'!AL13 -> Black | G37: ='All Cars'!AL17 -> Black | H37: ='All Cars'!AL18 -> Gray | I37: ='All Cars'!AL19 -> Black | J37: ='All Cars'!AL22 -> Tan | K37: ='All Cars'!AL23 -> Black
A38: Dealer | B38: ='All Cars'!AN5 -> Gurley Leep Honda | C38: ='All Cars'!AN6 -> Crown Motors Cadillac Buick Honda Mazda | D38: ='All Cars'!AN9 -> Fox Maple Hill | E38: ='All Cars'!AN12 -> Crown Motors Cadillac Buick Honda Mazda | F38: ='All Cars'!AN13 -> Gurley Leep Kia | G38: ='All Cars'!AN17 -> Gurley Leep Hyundai Subaru | H38: ='All Cars'!AN18 -> Crown Motors Cadillac Buick Honda Mazda | I38: ='All Cars'!AN19 -> Jordan Lexus of Mishawaka | J38: ='All Cars'!AN22 -> Gurley Leep Buick GMC Cadillac | K38: ='All Cars'!AN23 -> Zeigler Ford Lincoln Elkhart
A39: City | B39: ='All Cars'!AO5 -> Elkhart | C39: ='All Cars'!AO6 -> Holland | D39: ='All Cars'!AO9 -> Kalamazoo | E39: ='All Cars'!AO12 -> Holland | F39: ='All Cars'!AO13 -> Mishawaka | G39: ='All Cars'!AO17 -> Mishawaka | H39: ='All Cars'!AO18 -> Holland | I39: ='All Cars'!AO19 -> Mishawaka | J39: ='All Cars'!AO22 -> Mishawaka | K39: ='All Cars'!AO23 -> Elkhart
A40: Miles Away | B40: ='All Cars'!AQ5 -> 0.4 | C40: ='All Cars'!AQ6 -> 71 | D40: ='All Cars'!AQ9 -> 42.8 | E40: ='All Cars'!AQ12 -> 71 | F40: ='All Cars'!AQ13 -> 11 | G40: ='All Cars'!AQ17 -> 10.8 | H40: ='All Cars'!AQ18 -> 71 | I40: ='All Cars'!AQ19 -> 11.1 | J40: ='All Cars'!AQ22 -> 10.7 | K40: ='All Cars'!AQ23 -> 3.1
A41: Dealer Rating | B41: ='All Cars'!AR5 -> 4.6 | C41: ='All Cars'!AR6 -> 4.7 | D41: ='All Cars'!AR9 -> 0 | E41: ='All Cars'!AR12 -> 4.7 | F41: ='All Cars'!AR13 -> 4.2 | G41: ='All Cars'!AR17 -> 4.5 | H41: ='All Cars'!AR18 -> 4.7 | I41: ='All Cars'!AR19 -> 4.7 | J41: ='All Cars'!AR22 -> 4.5 | K41: ='All Cars'!AR23 -> 4.6
A42: Days Listed | B42: ='All Cars'!AS5 -> 53 | C42: ='All Cars'!AS6 -> 32 | D42: ='All Cars'!AS9 -> 17 | E42: ='All Cars'!AS12 -> 44 | F42: ='All Cars'!AS13 -> 89 | G42: ='All Cars'!AS17 -> 25 | H42: ='All Cars'!AS18 -> 32 | I42: ='All Cars'!AS19 -> 19 | J42: ='All Cars'!AS22 -> 3 | K42: ='All Cars'!AS23 -> 46
A43: Price Drop | B43: ='All Cars'!AT5 -> 3169 | C43: ='All Cars'!AT6 -> 0 | D43: ='All Cars'!AT9 -> 895 | E43: ='All Cars'!AT12 -> 0 | F43: ='All Cars'!AT13 -> 0 | G43: ='All Cars'!AT17 -> 0 | H43: ='All Cars'!AT18 -> 0 | I43: ='All Cars'!AT19 -> -49 | J43: ='All Cars'!AT22 -> 0 | K43: ='All Cars'!AT23 -> 0
A44: CarFax | B44: Open CARFAX listing | C44: Open CARFAX listing | D44: Open CARFAX listing | E44: Open CARFAX listing | F44: Open CARFAX listing | G44: Open CARFAX listing | H44: Open CARFAX listing | I44: Open CARFAX listing | J44: Open CARFAX listing | K44: Open CARFAX listing
A45: Listing URL | B45: https://www.carfax.com/vehicle/2HKRS4H73TH412625 | C45: https://www.carfax.com/vehicle/5J6RS4H46SL018336 | D45: https://www.carfax.com/vehicle/4S4BTANC7S3132470 | E45: https://www.carfax.com/vehicle/7FARS6H5XRE073206 | F45: https://www.carfax.com/vehicle/7FARS6H69TE031075 | G45: https://www.carfax.com/vehicle/5J6RS6H93PL004196 | H45: https://www.carfax.com/vehicle/7FARS4H4XSE002962 | I45: https://www.carfax.com/vehicle/7FARS6H82SE006423 | J45: https://www.carfax.com/vehicle/2T3N1RFV3RW451961 | K45: https://www.carfax.com/vehicle/7FARS6H8XRE020161

Sheet Model Benchmarks
A1: Model Benchmarks
A2: What each model and year actually goes for in this market. Everything is a live formula over the All Cars tab - it updates if you edit that data.
A4: Make | B4: Model | C4: Year | D4: Cars Listed | E4: Avg Price | F4: Min Price | G4: Max Price | H4: Avg Mileage | I4: Avg Score | J4: CPO Count | K4: Meets-All Count
A5: Honda | B5: CR-V | C5: 2022 | D5: =COUNTIFS('All Cars'!$E$5:$E$266,$A5,'All Cars'!$F$5:$F$266,$B5,'All Cars'!$D$5:$D$266,$C5) -> 5 | E5: =IFERROR(AVERAGEIFS('All Cars'!$H$5:$H$266,'All Cars'!$E$5:$E$266,$A5,'All Cars'!$F$5:$F$266,$B5,'All Cars'!$D$5:$D$266,$C5),"") -> 27888.4 | F5: =IFERROR(_xlfn.MINIFS('All Cars'!$H$5:$H$266,'All Cars'!$E$5:$E$266,$A5,'All Cars'!$F$5:$F$266,$B5,'All Cars'!$D$5:$D$266,$C5),"") -> 26548 | G5: =IFERROR(_xlfn.MAXIFS('All Cars'!$H$5:$H$266,'All Cars'!$E$5:$E$266,$A5,'All Cars'!$F$5:$F$266,$B5,'All Cars'!$D$5:$D$266,$C5),"") -> 28670 | H5: =IFERROR(AVERAGEIFS('All Cars'!$I$5:$I$266,'All Cars'!$E$5:$E$266,$A5,'All Cars'!$F$5:$F$266,$B5,'All Cars'!$D$5:$D$266,$C5),"") -> 54387.2 | I5: =IFERROR(AVERAGEIFS('All Cars'!$B$5:$B$266,'All Cars'!$E$5:$E$266,$A5,'All Cars'!$F$5:$F$266,$B5,'All Cars'!$D$5:$D$266,$C5),"") -> 51.84 | J5: =COUNTIFS('All Cars'!$E$5:$E$266,$A5,'All Cars'!$F$5:$F$266,$B5,'All Cars'!$D$5:$D$266,$C5,'All Cars'!$K$5:$K$266,"Yes") -> 0 | K5: =COUNTIFS('All Cars'!$E$5:$E$266,$A5,'All Cars'!$F$5:$F$266,$B5,'All Cars'!$D$5:$D$266,$C5,'All Cars'!$C$5:$C$266,"YES") -> 2
A6: Honda | B6: CR-V | C6: 2023 | D6: =COUNTIFS('All Cars'!$E$5:$E$266,$A6,'All Cars'!$F$5:$F$266,$B6,'All Cars'!$D$5:$D$266,$C6) -> 15 | E6: =IFERROR(AVERAGEIFS('All Cars'!$H$5:$H$266,'All Cars'!$E$5:$E$266,$A6,'All Cars'!$F$5:$F$266,$B6,'All Cars'!$D$5:$D$266,$C6),"") -> 30764.067 | F6: =IFERROR(_xlfn.MINIFS('All Cars'!$H$5:$H$266,'All Cars'!$E$5:$E$266,$A6,'All Cars'!$F$5:$F$266,$B6,'All Cars'!$D$5:$D$266,$C6),"") -> 26561 | G6: =IFERROR(_xlfn.MAXIFS('All Cars'!$H$5:$H$266,'All Cars'!$E$5:$E$266,$A6,'All Cars'!$F$5:$F$266,$B6,'All Cars'!$D$5:$D$266,$C6),"") -> 33741 | H6: =IFERROR(AVERAGEIFS('All Cars'!$I$5:$I$266,'All Cars'!$E$5:$E$266,$A6,'All Cars'!$F$5:$F$266,$B6,'All Cars'!$D$5:$D$266,$C6),"") -> 50979.133 | I6: =IFERROR(AVERAGEIFS('All Cars'!$B$5:$B$266,'All Cars'!$E$5:$E$266,$A6,'All Cars'!$F$5:$F$266,$B6,'All Cars'!$D$5:$D$266,$C6),"") -> 53.286667 | J6: =COUNTIFS('All Cars'!$E$5:$E$266,$A6,'All Cars'!$F$5:$F$266,$B6,'All Cars'!$D$5:$D$266,$C6,'All Cars'!$K$5:$K$266,"Yes") -> 0 | K6: =COUNTIFS('All Cars'!$E$5:$E$266,$A6,'All Cars'!$F$5:$F$266,$B6,'All Cars'!$D$5:$D$266,$C6,'All Cars'!$C$5:$C$266,"YES") -> 3
A7: Honda | B7: CR-V | C7: 2024 | D7: =COUNTIFS('All Cars'!$E$5:$E$266,$A7,'All Cars'!$F$5:$F$266,$B7,'All Cars'!$D$5:$D$266,$C7) -> 26 | E7: =IFERROR(AVERAGEIFS('All Cars'!$H$5:$H$266,'All Cars'!$E$5:$E$266,$A7,'All Cars'!$F$5:$F$266,$B7,'All Cars'!$D$5:$D$266,$C7),"") -> 32123 | F7: =IFERROR(_xlfn.MINIFS('All Cars'!$H$5:$H$266,'All Cars'!$E$5:$E$266,$A7,'All Cars'!$F$5:$F$266,$B7,'All Cars'!$D$5:$D$266,$C7),"") -> 25990 | G7: =IFERROR(_xlfn.MAXIFS('All Cars'!$H$5:$H$266,'All Cars'!$E$5:$E$266,$A7,'All Cars'!$F$5:$F$266,$B7,'All Cars'!$D$5:$D$266,$C7),"") -> 37990 | H7: =IFERROR(AVERAGEIFS('All Cars'!$I$5:$I$266,'All Cars'!$E$5:$E$266,$A7,'All Cars'!$F$5:$F$266,$B7,'All Cars'!$D$5:$D$266,$C7),"") -> 39449.269 | I7: =IFERROR(AVERAGEIFS('All Cars'!$B$5:$B$266,'All Cars'!$E$5:$E$266,$A7,'All Cars'!$F$5:$F$266,$B7,'All Cars'!$D$5:$D$266,$C7),"") -> 55.761538 | J7: =COUNTIFS('All Cars'!$E$5:$E$266,$A7,'All Cars'!$F$5:$F$266,$B7,'All Cars'!$D$5:$D$266,$C7,'All Cars'!$K$5:$K$266,"Yes") -> 3 | K7: =COUNTIFS('All Cars'!$E$5:$E$266,$A7,'All Cars'!$F$5:$F$266,$B7,'All Cars'!$D$5:$D$266,$C7,'All Cars'!$C$5:$C$266,"YES") -> 6
A8: Honda | B8: CR-V | C8: 2025 | D8: =COUNTIFS('All Cars'!$E$5:$E$266,$A8,'All Cars'!$F$5:$F$266,$B8,'All Cars'!$D$5:$D$266,$C8) -> 18 | E8: =IFERROR(AVERAGEIFS('All Cars'!$H$5:$H$266,'All Cars'!$E$5:$E$266,$A8,'All Cars'!$F$5:$F$266,$B8,'All Cars'!$D$5:$D$266,$C8),"") -> 33886.889 | F8: =IFERROR(_xlfn.MINIFS('All Cars'!$H$5:$H$266,'All Cars'!$E$5:$E$266,$A8,'All Cars'!$F$5:$F$266,$B8,'All Cars'!$D$5:$D$266,$C8),"") -> 29024 | G8: =IFERROR(_xlfn.MAXIFS('All Cars'!$H$5:$H$266,'All Cars'!$E$5:$E$266,$A8,'All Cars'!$F$5:$F$266,$B8,'All Cars'!$D$5:$D$266,$C8),"") -> 38238 | H8: =IFERROR(AVERAGEIFS('All Cars'!$I$5:$I$266,'All Cars'!$E$5:$E$266,$A8,'All Cars'!$F$5:$F$266,$B8,'All Cars'!$D$5:$D$266,$C8),"") -> 30774.333 | I8: =IFERROR(AVERAGEIFS('All Cars'!$B$5:$B$266,'All Cars'!$E$5:$E$266,$A8,'All Cars'!$F$5:$F$266,$B8,'All Cars'!$D$5:$D$266,$C8),"") -> 56.705556 | J8: =COUNTIFS('All Cars'!$E$5:$E$266,$A8,'All Cars'!$F$5:$F$266,$B8,'All Cars'!$D$5:$D$266,$C8,'All Cars'!$K$5:$K$266,"Yes") -> 2 | K8: =COUNTIFS('All Cars'!$E$5:$E$266,$A8,'All Cars'!$F$5:$F$266,$B8,'All Cars'!$D$5:$D$266,$C8,'All Cars'!$C$5:$C$266,"YES") -> 8
A9: Honda | B9: CR-V | C9: 2026 | D9: =COUNTIFS('All Cars'!$E$5:$E$266,$A9,'All Cars'!$F$5:$F$266,$B9,'All Cars'!$D$5:$D$266,$C9) -> 4 | E9: =IFERROR(AVERAGEIFS('All Cars'!$H$5:$H$266,'All Cars'!$E$5:$E$266,$A9,'All Cars'!$F$5:$F$266,$B9,'All Cars'!$D$5:$D$266,$C9),"") -> 35994.75 | F9: =IFERROR(_xlfn.MINIFS('All Cars'!$H$5:$H$266,'All Cars'!$E$5:$E$266,$A9,'All Cars'!$F$5:$F$266,$B9,'All Cars'!$D$5:$D$266,$C9),"") -> 34661 | G9: =IFERROR(_xlfn.MAXIFS('All Cars'!$H$5:$H$266,'All Cars'!$E$5:$E$266,$A9,'All Cars'!$F$5:$F$266,$B9,'All Cars'!$D$5:$D$266,$C9),"") -> 37990 | H9: =IFERROR(AVERAGEIFS('All Cars'!$I$5:$I$266,'All Cars'!$E$5:$E$266,$A9,'All Cars'!$F$5:$F$266,$B9,'All Cars'!$D$5:$D$266,$C9),"") -> 14458.5 | I9: =IFERROR(AVERAGEIFS('All Cars'!$B$5:$B$266,'All Cars'!$E$5:$E$266,$A9,'All Cars'!$F$5:$F$266,$B9,'All Cars'!$D$5:$D$266,$C9),"") -> 65.375 | J9: =COUNTIFS('All Cars'!$E$5:$E$266,$A9,'All Cars'!$F$5:$F$266,$B9,'All Cars'!$D$5:$D$266,$C9,'All Cars'!$K$5:$K$266,"Yes") -> 1 | K9: =COUNTIFS('All Cars'!$E$5:$E$266,$A9,'All Cars'!$F$5:$F$266,$B9,'All Cars'!$D$5:$D$266,$C9,'All Cars'!$C$5:$C$266,"YES") -> 2
A10: Honda | B10: HR-V | C10: 2023 | D10: =COUNTIFS('All Cars'!$E$5:$E$266,$A10,'All Cars'!$F$5:$F$266,$B10,'All Cars'!$D$5:$D$266,$C10) -> 3 | E10: =IFERROR(AVERAGEIFS('All Cars'!$H$5:$H$266,'All Cars'!$E$5:$E$266,$A10,'All Cars'!$F$5:$F$266,$B10,'All Cars'!$D$5:$D$266,$C10),"") -> 24575.333 | F10: =IFERROR(_xlfn.MINIFS('All Cars'!$H$5:$H$266,'All Cars'!$E$5:$E$266,$A10,'All Cars'!$F$5:$F$266,$B10,'All Cars'!$D$5:$D$266,$C10),"") -> 22144 | G10: =IFERROR(_xlfn.MAXIFS('All Cars'!$H$5:$H$266,'All Cars'!$E$5:$E$266,$A10,'All Cars'!$F$5:$F$266,$B10,'All Cars'!$D$5:$D$266,$C10),"") -> 28814 | H10: =IFERROR(AVERAGEIFS('All Cars'!$I$5:$I$266,'All Cars'!$E$5:$E$266,$A10,'All Cars'!$F$5:$F$266,$B10,'All Cars'!$D$5:$D$266,$C10),"") -> 51929.667 | I10: =IFERROR(AVERAGEIFS('All Cars'!$B$5:$B$266,'All Cars'!$E$5:$E$266,$A10,'All Cars'!$F$5:$F$266,$B10,'All Cars'!$D$5:$D$266,$C10),"") -> 52.9 | J10: =COUNTIFS('All Cars'!$E$5:$E$266,$A10,'All Cars'!$F$5:$F$266,$B10,'All Cars'!$D$5:$D$266,$C10,'All Cars'!$K$5:$K$266,"Yes") -> 1 | K10: =COUNTIFS('All Cars'!$E$5:$E$266,$A10,'All Cars'!$F$5:$F$266,$B10,'All Cars'!$D$5:$D$266,$C10,'All Cars'!$C$5:$C$266,"YES") -> 0
A11: Honda | B11: HR-V | C11: 2024 | D11: =COUNTIFS('All Cars'!$E$5:$E$266,$A11,'All Cars'!$F$5:$F$266,$B11,'All Cars'!$D$5:$D$266,$C11) -> 10 | E11: =IFERROR(AVERAGEIFS('All Cars'!$H$5:$H$266,'All Cars'!$E$5:$E$266,$A11,'All Cars'!$F$5:$F$266,$B11,'All Cars'!$D$5:$D$266,$C11),"") -> 26245.9 | F11: =IFERROR(_xlfn.MINIFS('All Cars'!$H$5:$H$266,'All Cars'!$E$5:$E$266,$A11,'All Cars'!$F$5:$F$266,$B11,'All Cars'!$D$5:$D$266,$C11),"") -> 24809 | G11: =IFERROR(_xlfn.MAXIFS('All Cars'!$H$5:$H$266,'All Cars'!$E$5:$E$266,$A11,'All Cars'!$F$5:$F$266,$B11,'All Cars'!$D$5:$D$266,$C11),"") -> 29950 | H11: =IFERROR(AVERAGEIFS('All Cars'!$I$5:$I$266,'All Cars'!$E$5:$E$266,$A11,'All Cars'!$F$5:$F$266,$B11,'All Cars'!$D$5:$D$266,$C11),"") -> 38131.5 | I11: =IFERROR(AVERAGEIFS('All Cars'!$B$5:$B$266,'All Cars'!$E$5:$E$266,$A11,'All Cars'!$F$5:$F$266,$B11,'All Cars'!$D$5:$D$266,$C11),"") -> 50.65 | J11: =COUNTIFS('All Cars'!$E$5:$E$266,$A11,'All Cars'!$F$5:$F$266,$B11,'All Cars'!$D$5:$D$266,$C11,'All Cars'!$K$5:$K$266,"Yes") -> 2 | K11: =COUNTIFS('All Cars'!$E$5:$E$266,$A11,'All Cars'!$F$5:$F$266,$B11,'All Cars'!$D$5:$D$266,$C11,'All Cars'!$C$5:$C$266,"YES") -> 0
A12: Honda | B12: HR-V | C12: 2025 | D12: =COUNTIFS('All Cars'!$E$5:$E$266,$A12,'All Cars'!$F$5:$F$266,$B12,'All Cars'!$D$5:$D$266,$C12) -> 5 | E12: =IFERROR(AVERAGEIFS('All Cars'!$H$5:$H$266,'All Cars'!$E$5:$E$266,$A12,'All Cars'!$F$5:$F$266,$B12,'All Cars'!$D$5:$D$266,$C12),"") -> 26149.2 | F12: =IFERROR(_xlfn.MINIFS('All Cars'!$H$5:$H$266,'All Cars'!$E$5:$E$266,$A12,'All Cars'!$F$5:$F$266,$B12,'All Cars'!$D$5:$D$266,$C12),"") -> 23869 | G12: =IFERROR(_xlfn.MAXIFS('All Cars'!$H$5:$H$266,'All Cars'!$E$5:$E$266,$A12,'All Cars'!$F$5:$F$266,$B12,'All Cars'!$D$5:$D$266,$C12),"") -> 27738 | H12: =IFERROR(AVERAGEIFS('All Cars'!$I$5:$I$266,'All Cars'!$E$5:$E$266,$A12,'All Cars'!$F$5:$F$266,$B12,'All Cars'!$D$5:$D$266,$C12),"") -> 32718 | I12: =IFERROR(AVERAGEIFS('All Cars'!$B$5:$B$266,'All Cars'!$E$5:$E$266,$A12,'All Cars'!$F$5:$F$266,$B12,'All Cars'!$D$5:$D$266,$C12),"") -> 49.84 | J12: =COUNTIFS('All Cars'!$E$5:$E$266,$A12,'All Cars'!$F$5:$F$266,$B12,'All Cars'!$D$5:$D$266,$C12,'All Cars'!$K$5:$K$266,"Yes") -> 1 | K12: =COUNTIFS('All Cars'!$E$5:$E$266,$A12,'All Cars'!$F$5:$F$266,$B12,'All Cars'!$D$5:$D$266,$C12,'All Cars'!$C$5:$C$266,"YES") -> 1
A13: Subaru | B13: Outback | C13: 2022 | D13: =COUNTIFS('All Cars'!$E$5:$E$266,$A13,'All Cars'!$F$5:$F$266,$B13,'All Cars'!$D$5:$D$266,$C13) -> 3 | E13: =IFERROR(AVERAGEIFS('All Cars'!$H$5:$H$266,'All Cars'!$E$5:$E$266,$A13,'All Cars'!$F$5:$F$266,$B13,'All Cars'!$D$5:$D$266,$C13),"") -> 22204.333 | F13: =IFERROR(_xlfn.MINIFS('All Cars'!$H$5:$H$266,'All Cars'!$E$5:$E$266,$A13,'All Cars'!$F$5:$F$266,$B13,'All Cars'!$D$5:$D$266,$C13),"") -> 20309 | G13: =IFERROR(_xlfn.MAXIFS('All Cars'!$H$5:$H$266,'All Cars'!$E$5:$E$266,$A13,'All Cars'!$F$5:$F$266,$B13,'All Cars'!$D$5:$D$266,$C13),"") -> 23995 | H13: =IFERROR(AVERAGEIFS('All Cars'!$I$5:$I$266,'All Cars'!$E$5:$E$266,$A13,'All Cars'!$F$5:$F$266,$B13,'All Cars'!$D$5:$D$266,$C13),"") -> 64580.667 | I13: =IFERROR(AVERAGEIFS('All Cars'!$B$5:$B$266,'All Cars'!$E$5:$E$266,$A13,'All Cars'!$F$5:$F$266,$B13,'All Cars'!$D$5:$D$266,$C13),"") -> 42.2 | J13: =COUNTIFS('All Cars'!$E$5:$E$266,$A13,'All Cars'!$F$5:$F$266,$B13,'All Cars'!$D$5:$D$266,$C13,'All Cars'!$K$5:$K$266,"Yes") -> 0 | K13: =COUNTIFS('All Cars'!$E$5:$E$266,$A13,'All Cars'!$F$5:$F$266,$B13,'All Cars'!$D$5:$D$266,$C13,'All Cars'!$C$5:$C$266,"YES") -> 0
A14: Subaru | B14: Outback | C14: 2023 | D14: =COUNTIFS('All Cars'!$E$5:$E$266,$A14,'All Cars'!$F$5:$F$266,$B14,'All Cars'!$D$5:$D$266,$C14) -> 12 | E14: =IFERROR(AVERAGEIFS('All Cars'!$H$5:$H$266,'All Cars'!$E$5:$E$266,$A14,'All Cars'!$F$5:$F$266,$B14,'All Cars'!$D$5:$D$266,$C14),"") -> 23907.833 | F14: =IFERROR(_xlfn.MINIFS('All Cars'!$H$5:$H$266,'All Cars'!$E$5:$E$266,$A14,'All Cars'!$F$5:$F$266,$B14,'All Cars'!$D$5:$D$266,$C14),"") -> 19645 | G14: =IFERROR(_xlfn.MAXIFS('All Cars'!$H$5:$H$266,'All Cars'!$E$5:$E$266,$A14,'All Cars'!$F$5:$F$266,$B14,'All Cars'!$D$5:$D$266,$C14),"") -> 27814 | H14: =IFERROR(AVERAGEIFS('All Cars'!$I$5:$I$266,'All Cars'!$E$5:$E$266,$A14,'All Cars'!$F$5:$F$266,$B14,'All Cars'!$D$5:$D$266,$C14),"") -> 68709.333 | I14: =IFERROR(AVERAGEIFS('All Cars'!$B$5:$B$266,'All Cars'!$E$5:$E$266,$A14,'All Cars'!$F$5:$F$266,$B14,'All Cars'!$D$5:$D$266,$C14),"") -> 42.675 | J14: =COUNTIFS('All Cars'!$E$5:$E$266,$A14,'All Cars'!$F$5:$F$266,$B14,'All Cars'!$D$5:$D$266,$C14,'All Cars'!$K$5:$K$266,"Yes") -> 0 | K14: =COUNTIFS('All Cars'!$E$5:$E$266,$A14,'All Cars'!$F$5:$F$266,$B14,'All Cars'!$D$5:$D$266,$C14,'All Cars'!$C$5:$C$266,"YES") -> 1
A15: Subaru | B15: Outback | C15: 2024 | D15: =COUNTIFS('All Cars'!$E$5:$E$266,$A15,'All Cars'!$F$5:$F$266,$B15,'All Cars'!$D$5:$D$266,$C15) -> 23 | E15: =IFERROR(AVERAGEIFS('All Cars'!$H$5:$H$266,'All Cars'!$E$5:$E$266,$A15,'All Cars'!$F$5:$F$266,$B15,'All Cars'!$D$5:$D$266,$C15),"") -> 27278.783 | F15: =IFERROR(_xlfn.MINIFS('All Cars'!$H$5:$H$266,'All Cars'!$E$5:$E$266,$A15,'All Cars'!$F$5:$F$266,$B15,'All Cars'!$D$5:$D$266,$C15),"") -> 20091 | G15: =IFERROR(_xlfn.MAXIFS('All Cars'!$H$5:$H$266,'All Cars'!$E$5:$E$266,$A15,'All Cars'!$F$5:$F$266,$B15,'All Cars'!$D$5:$D$266,$C15),"") -> 33314 | H15: =IFERROR(AVERAGEIFS('All Cars'!$I$5:$I$266,'All Cars'!$E$5:$E$266,$A15,'All Cars'!$F$5:$F$266,$B15,'All Cars'!$D$5:$D$266,$C15),"") -> 51299 | I15: =IFERROR(AVERAGEIFS('All Cars'!$B$5:$B$266,'All Cars'!$E$5:$E$266,$A15,'All Cars'!$F$5:$F$266,$B15,'All Cars'!$D$5:$D$266,$C15),"") -> 46.252174 | J15: =COUNTIFS('All Cars'!$E$5:$E$266,$A15,'All Cars'!$F$5:$F$266,$B15,'All Cars'!$D$5:$D$266,$C15,'All Cars'!$K$5:$K$266,"Yes") -> 0 | K15: =COUNTIFS('All Cars'!$E$5:$E$266,$A15,'All Cars'!$F$5:$F$266,$B15,'All Cars'!$D$5:$D$266,$C15,'All Cars'!$C$5:$C$266,"YES") -> 4
A16: Subaru | B16: Outback | C16: 2025 | D16: =COUNTIFS('All Cars'!$E$5:$E$266,$A16,'All Cars'!$F$5:$F$266,$B16,'All Cars'!$D$5:$D$266,$C16) -> 12 | E16: =IFERROR(AVERAGEIFS('All Cars'!$H$5:$H$266,'All Cars'!$E$5:$E$266,$A16,'All Cars'!$F$5:$F$266,$B16,'All Cars'!$D$5:$D$266,$C16),"") -> 31632 | F16: =IFERROR(_xlfn.MINIFS('All Cars'!$H$5:$H$266,'All Cars'!$E$5:$E$266,$A16,'All Cars'!$F$5:$F$266,$B16,'All Cars'!$D$5:$D$266,$C16),"") -> 27755 | G16: =IFERROR(_xlfn.MAXIFS('All Cars'!$H$5:$H$266,'All Cars'!$E$5:$E$266,$A16,'All Cars'!$F$5:$F$266,$B16,'All Cars'!$D$5:$D$266,$C16),"") -> 36004 | H16: =IFERROR(AVERAGEIFS('All Cars'!$I$5:$I$266,'All Cars'!$E$5:$E$266,$A16,'All Cars'!$F$5:$F$266,$B16,'All Cars'!$D$5:$D$266,$C16),"") -> 26496.083 | I16: =IFERROR(AVERAGEIFS('All Cars'!$B$5:$B$266,'All Cars'!$E$5:$E$266,$A16,'All Cars'!$F$5:$F$266,$B16,'All Cars'!$D$5:$D$266,$C16),"") -> 56.408333 | J16: =COUNTIFS('All Cars'!$E$5:$E$266,$A16,'All Cars'!$F$5:$F$266,$B16,'All Cars'!$D$5:$D$266,$C16,'All Cars'!$K$5:$K$266,"Yes") -> 4 | K16: =COUNTIFS('All Cars'!$E$5:$E$266,$A16,'All Cars'!$F$5:$F$266,$B16,'All Cars'!$D$5:$D$266,$C16,'All Cars'!$C$5:$C$266,"YES") -> 3
... A23: Toyota | B23: RAV4 | C23: 2025 | D23: =COUNTIFS('All Cars'!$E$5:$E$266,$A23,'All Cars'!$F$5:$F$266,$B23,'All Cars'!$D$5:$D$266,$C23) -> 60 | E23: =IFERROR(AVERAGEIFS('All Cars'!$H$5:$H$266,'All Cars'!$E$5:$E$266,$A23,'All Cars'!$F$5:$F$266,$B23,'All Cars'!$D$5:$D$266,$C23),"") -> 34114.717 | F23: =IFERROR(_xlfn.MINIFS('All Cars'!$H$5:$H$266,'All Cars'!$E$5:$E$266,$A23,'All Cars'!$F$5:$F$266,$B23,'All Cars'!$D$5:$D$266,$C23),"") -> 27233 | G23: =IFERROR(_xlfn.MAXIFS('All Cars'!$H$5:$H$266,'All Cars'!$E$5:$E$266,$A23,'All Cars'!$F$5:$F$266,$B23,'All Cars'!$D$5:$D$266,$C23),"") -> 39309 | H23: =IFERROR(AVERAGEIFS('All Cars'!$I$5:$I$266,'All Cars'!$E$5:$E$266,$A23,'All Cars'!$F$5:$F$266,$B23,'All Cars'!$D$5:$D$266,$C23),"") -> 35845.4 | I23: =IFERROR(AVERAGEIFS('All Cars'!$B$5:$B$266,'All Cars'!$E$5:$E$266,$A23,'All Cars'!$F$5:$F$266,$B23,'All Cars'!$D$5:$D$266,$C23),"") -> 49.903333 | J23: =COUNTIFS('All Cars'!$E$5:$E$266,$A23,'All Cars'!$F$5:$F$266,$B23,'All Cars'!$D$5:$D$266,$C23,'All Cars'!$K$5:$K$266,"Yes") -> 11 | K23: =COUNTIFS('All Cars'!$E$5:$E$266,$A23,'All Cars'!$F$5:$F$266,$B23,'All Cars'!$D$5:$D$266,$C23,'All Cars'!$C$5:$C$266,"YES") -> 4

Sheet All Cars
A1: All Cars - Full Inventory
A2: Every 2022+ 4Runner / RAV4 / HR-V / CR-V / Outback under $40,000 within 75 miles of Elkhart. Click the filter arrows to narrow. Data pulled from CARFAX 2026-09-14.
A4: Rank | B4: Score | C4: Meets All | D4: Year | E4: Make | F4: Model | G4: Trim | H4: Price | I4: Mileage | J4: Miles/Yr | K4: CPO | L4: Drivetrain | M4: Fuel | N4: MPG | O4: Value Badge | P4: Est. Market | Q4: vs Market | R4: Reliability | S4: Repair $/yr | T4: No Accidents | U4: Owners | V4: Personal Use | W4: Service Recs | X4: Heated Seats | Y4: Apple CarPlay | Z4: Heated Steering | AA4: Sunroof/Moonroof | AB4: Blind Spot | AC4: Power Liftgate | AD4: Leather | AE4: Remote Start | AF4: Navigation | AG4: Wireless Charging | AH4: Parking Sensors | AI4: Power Driver Seat | AJ4: Premium Audio | AK4: Ext Color | AL4: Int Color | AM4: Engine | AN4: Dealer | AO4: City | AP4: ST | AQ4: Miles Away | AR4: Dealer Rating | AS4: Days Listed | AT4: Price Drop | AU4: Est. Monthly | AV4: Doc Fee | AW4: Sub: Reliability | AX4: Sub: Value | AY4: Sub: Mileage | AZ4: Sub: Features | BA4: Sub: CPO | BB4: Sub: Distance | BC4: VIN | BD4: CarFax Link | BE4: Listing URL
A5: =RANK(B5,$B$5:$B$266) -> 1 | B5: =ROUND((AW5*'Scoring Weights'!$B$5+AX5*'Scoring Weights'!$B$6+AY5*'Scoring Weights'!$B$7+BA5*'Scoring Weights'!$B$8+AZ5*'Scoring Weights'!$B$9+BB5*'Scoring Weights'!$B$10)/MAX('Scoring Weights'!$B$11,1),1) -> 84 | C5: =IF(AND(H5<='Search Criteria'!$B$5,D5>='Search Criteria'!$B$6,AQ5<='Search Criteria'!$B$7,I5<=INDEX('Search Criteria'!$B$18:$B$20,MATCH(E5,'Search Criteria'!$A$18:$A$20,0)),OR(NOT('Search Criteria'!$B$8),L5<>"FWD"),OR(NOT('Search Criteria'!$B$9),T5="Yes"),OR(NOT('Search Criteria'!$B$10),W5>0),OR(NOT('Search Criteria'!$B$11),X5="Yes"),OR(NOT('Search Criteria'!$B$12),O5="GREAT",O5="GOOD"),OR(NOT('Search Criteria'!$B$13),K5="Yes")),"YES","no") -> YES | D5: 2026 | E5: Honda | F5: CR-V | G5: EXL | H5: 35415 | I5: 12036 | J5: =IFERROR(ROUND(I5/MAX(2026-D5,0.5),0),"") -> 24072 | K5: Yes | L5: AWD | M5: Gasoline | N5: 29 | O5: GREAT | P5: 36351 | Q5: 0.026 | R5: GREAT | S5: 190 | T5: Yes | U5: 1 | V5: Yes | W5: 6 | X5: Yes | Y5: Yes | Z5: No | AA5: Yes | AB5: Yes | AC5: Yes | AD5: Yes | AE5: Yes | AF5: No | AG5: Yes | AH5: Yes | AI5: Yes | AJ5: No | AK5: Gray | AL5: Black | AM5: 1.5 L 4 Cyl | AN5: Gurley Leep Honda | AO5: Elkhart | AP5: IN | AQ5: 0.4 | AR5: 4.6 | AS5: 53 | AT5: 3169 | AU5: 632.64 | AV5: 261 | AW5: 95.2 | AX5: 81.4 | AY5: 58 | AZ5: 78 | BA5: 100 | BB5: 99.4 | BC5: 2HKRS4H73TH412625 | BD5: 2026 Honda CR-V | BE5: https://www.carfax.com/vehicle/2HKRS4H73TH412625
A6: =RANK(B6,$B$5:$B$266) -> 2 | B6: =ROUND((AW6*'Scoring Weights'!$B$5+AX6*'Scoring Weights'!$B$6+AY6*'Scoring Weights'!$B$7+BA6*'Scoring Weights'!$B$8+AZ6*'Scoring Weights'!$B$9+BB6*'Scoring Weights'!$B$10)/MAX('Scoring Weights'!$B$11,1),1) -> 72.4 | C6: =IF(AND(H6<='Search Criteria'!$B$5,D6>='Search Criteria'!$B$6,AQ6<='Search Criteria'!$B$7,I6<=INDEX('Search Criteria'!$B$18:$B$20,MATCH(E6,'Search Criteria'!$A$18:$A$20,0)),OR(NOT('Search Criteria'!$B$8),L6<>"FWD"),OR(NOT('Search Criteria'!$B$9),T6="Yes"),OR(NOT('Search Criteria'!$B$10),W6>0),OR(NOT('Search Criteria'!$B$11),X6="Yes"),OR(NOT('Search Criteria'!$B$12),O6="GREAT",O6="GOOD"),OR(NOT('Search Criteria'!$B$13),K6="Yes")),"YES","no") -> YES | D6: 2025 | E6: Honda | F6: CR-V | G6: EX | H6: 32809 | I6: 15682 | J6: =IFERROR(ROUND(I6/MAX(2026-D6,0.5),0),"") -> 15682 | K6: Yes | L6: AWD | M6: Gasoline | N6: 28 | O6: GREAT | P6: 34961 | Q6: 0.062 | R6: GREAT | S6: 560 | T6: Yes | U6: 1 | V6: Yes | W6: 4 | X6: Yes | Y6: Yes | Z6: No | AA6: Yes | AB6: Yes | AC6: No | AD6: No | AE6: No | AF6: No | AG6: No | AH6: No | AI6: Yes | AJ6: No | AK6: Silver | AL6: Gray | AM6: 1.5 L 4 Cyl | AN6: Crown Motors Cadillac Buick Honda Mazda | AO6: Holland | AP6: MI | AQ6: 71 | AR6: 4.7 | AS6: 32 | AU6: 586.09 | AV6: 314 | AW6: 88.6 | AX6: 86.7 | AY6: 60.1 | AZ6: 30 | BA6: 100 | BB6: 5.4 | BC6: 5J6RS4H46SL018336 | BD6: 2025 Honda CR-V | BE6: https://www.carfax.com/vehicle/5J6RS4H46SL018336
A7: =RANK(B7,$B$5:$B$266) -> 3 | B7: =ROUND((AW7*'Scoring Weights'!$B$5+AX7*'Scoring Weights'!$B$6+AY7*'Scoring Weights'!$B$7+BA7*'Scoring Weights'!$B$8+AZ7*'Scoring Weights'!$B$9+BB7*'Scoring Weights'!$B$10)/MAX('Scoring Weights'!$B$11,1),1) -> 71.8 | C7: =IF(AND(H7<='Search Criteria'!$B$5,D7>='Search Criteria'!$B$6,AQ7<='Search Criteria'!$B$7,I7<=INDEX('Search Criteria'!$B$18:$B$20,MATCH(E7,'Search Criteria'!$A$18:$A$20,0)),OR(NOT('Search Criteria'!$B$8),L7<>"FWD"),OR(NOT('Search Criteria'!$B$9),T7="Yes"),OR(NOT('Search Criteria'!$B$10),W7>0),OR(NOT('Search Criteria'!$B$11),X7="Yes"),OR(NOT('Search Criteria'!$B$12),O7="GREAT",O7="GOOD"),OR(NOT('Search Criteria'!$B$13),K7="Yes")),"YES","no") -> no | D7: 2025 | E7: Subaru | F7: Outback | G7: Limited | H7: 36004 | I7: 10034 | J7: =IFERROR(ROUND(I7/MAX(2026-D7,0.5),0),"") -> 10034 | K7: Yes | L7: AWD | M7: Gasoline | N7: 28 | O7: None | P7: 33342 | Q7: -0.08 | R7: n/a | T7: Yes | V7: No | W7: 7 | X7: Yes | Y7: Yes | Z7: Yes | AA7: Yes | AB7: Yes | AC7: Yes | AD7: Yes | AE7: No | AF7: Yes | AG7: No | AH7: Yes | AI7: Yes | AJ7: Yes | AK7: Black | AL7: Black | AM7: 2.5 L 4 Cyl | AN7: Gurley Leep Hyundai Subaru | AO7: Mishawaka | AP7: IN | AQ7: 10.8 | AR7: 4.5 | AS7: 138 | AT7: 3413 | AU7: 643.16 | AV7: 261 | AW7: 67.7 | AX7: 44.6 | AY7: 75.9 | AZ7: 82 | BA7: 100 | BB7: 85.6 | BC7: 4S4BTANC9S3315353 | BD7: 2025 Subaru Outback | BE7: https://www.carfax.com/vehicle/4S4BTANC9S3315353
A8: =RANK(B8,$B$5:$B$266) -> 4 | B8: =ROUND((AW8*'Scoring Weights'!$B$5+AX8*'Scoring Weights'!$B$6+AY8*'Scoring Weights'!$B$7+BA8*'Scoring Weights'!$B$8+AZ8*'Scoring Weights'!$B$9+BB8*'Scoring Weights'!$B$10)/MAX('Scoring Weights'!$B$11,1),1) -> 70.4 | C8: =IF(AND(H8<='Search Criteria'!$B$5,D8>='Search Criteria'!$B$6,AQ8<='Search Criteria'!$B$7,I8<=INDEX('Search Criteria'!$B$18:$B$20,MATCH(E8,'Search Criteria'!$A$18:$A$20,0)),OR(NOT('Search Criteria'!$B$8),L8<>"FWD"),OR(NOT('Search Criteria'!$B$9),T8="Yes"),OR(NOT('Search Criteria'!$B$10),W8>0),OR(NOT('Search Criteria'!$B$11),X8="Yes"),OR(NOT('Search Criteria'!$B$12),O8="GREAT",O8="GOOD"),OR(NOT('Search Criteria'!$B$13),K8="Yes")),"YES","no") -> no | D8: 2025 | E8: Toyota | F8: RAV4 | G8: XLE Premium | H8: 38902 | I8: 15101 | J8: =IFERROR(ROUND(I8/MAX(2026-D8,0.5),0),"") -> 15101 | K8: Yes | L8: FWD | M8: Gasoline | N8: 30 | O8: GOOD | P8: 35966 | Q8: -0.082 | R8: GREAT | S8: 310 | T8: Yes | U8: 1 | V8: Yes | W8: 4 | X8: No | Y8: Yes | Z8: No | AA8: Yes | AB8: Yes | AC8: Yes | AD8: Yes | AE8: No | AF8: No | AG8: No | AH8: No | AI8: Yes | AJ8: No | AK8: Black | AL8: Tan | AM8: 2.5 L 4 Cyl | AN8: Crown Toyota Volkswagen | AO8: Holland | AP8: MI | AQ8: 74.7 | AR8: 4.7 | AS8: 46 | AT8: -903 | AU8: 694.93 | AV8: 314 | AW8: 92.8 | AX8: 53.2 | AY8: 66.7 | AZ8: 54 | BA8: 100 | BB8: 0.4 | BC8: 2T3C1RFV9SW407573 | BD8: 2025 Toyota RAV4 | BE8: https://www.carfax.com/vehicle/2T3C1RFV9SW407573
A9: =RANK(B9,$B$5:$B$266) -> 5 | B9: =ROUND((AW9*'Scoring Weights'!$B$5+AX9*'Scoring Weights'!$B$6+AY9*'Scoring Weights'!$B$7+BA9*'Scoring Weights'!$B$8+AZ9*'Scoring Weights'!$B$9+BB9*'Scoring Weights'!$B$10)/MAX('Scoring Weights'!$B$11,1),1) -> 70 | C9: =IF(AND(H9<='Search Criteria'!$B$5,D9>='Search Criteria'!$B$6,AQ9<='Search Criteria'!$B$7,I9<=INDEX('Search Criteria'!$B$18:$B$20,MATCH(E9,'Search Criteria'!$A$18:$A$20,0)),OR(NOT('Search Criteria'!$B$8),L9<>"FWD"),OR(NOT('Search Criteria'!$B$9),T9="Yes"),OR(NOT('Search Criteria'!$B$10),W9>0),OR(NOT('Search Criteria'!$B$11),X9="Yes"),OR(NOT('Search Criteria'!$B$12),O9="GREAT",O9="GOOD"),OR(NOT('Search Criteria'!$B$13),K9="Yes")),"YES","no") -> YES | D9: 2025 | E9: Subaru | F9: Outback | G9: Limited | H9: 32609 | I9: 31763 | J9: =IFERROR(ROUND(I9/MAX(2026-D9,0.5),0),"") -> 31763 | K9: Yes | L9: AWD | M9: Gasoline | N9: 28 | O9: GOOD | P9: 31035 | Q9: -0.051 | R9: GREAT | S9: 120 | T9: Yes | U9: 1 | V9: Yes | W9: 6 | X9: Yes | Y9: Yes | Z9: Yes | AA9: Yes | AB9: Yes | AC9: Yes | AD9: Yes | AE9: No | AF9: Yes | AG9: No | AH9: Yes | AI9: Yes | AJ9: Yes | AK9: Black | AL9: White | AM9: 2.5 L 4 Cyl | AN9: Fox Maple Hill | AO9: Kalamazoo | AP9: MI | AQ9: 42.8 | AS9: 17 | AT9: 895 | AU9: 582.51 | AW9: 92.7 | AX9: 57.8 | AY9: 25.5 | AZ9: 82 | BA9: 100 | BB9: 42.9 | BC9: 4S4BTANC7S3132470 | BD9: 2025 Subaru Outback | BE9: https://www.carfax.com/vehicle/4S4BTANC7S3132470
A10: =RANK(B10,$B$5:$B$266) -> 6 | B10: =ROUND((AW10*'Scoring Weights'!$B$5+AX10*'Scoring Weights'!$B$6+AY10*'Scoring Weights'!$B$7+BA10*'Scoring Weights'!$B$8+AZ10*'Scoring Weights'!$B$9+BB10*'Scoring Weights'!$B$10)/MAX('Scoring Weights'!$B$11,1),1) -> 69.1 | C10: =IF(AND(H10<='Search Criteria'!$B$5,D10>='Search Criteria'!$B$6,AQ10<='Search Criteria'!$B$7,I10<=INDEX('Search Criteria'!$B$18:$B$20,MATCH(E10,'Search Criteria'!$A$18:$A$20,0)),OR(NOT('Search Criteria'!$B$8),L10<>"FWD"),OR(NOT('Search Criteria'!$B$9),T10="Yes"),OR(NOT('Search Criteria'!$B$10),W10>0),OR(NOT('Search Criteria'!$B$11),X10="Yes"),OR(NOT('Search Criteria'!$B$12),O10="GREAT",O10="GOOD"),OR(NOT('Search Criteria'!$B$13),K10="Yes")),"YES","no") -> no | D10: 2025 | E10: Toyota | F10: RAV4 | G10: XLE | H10: 38180 | I10: 17889 | J10: =IFERROR(ROUND(I10/MAX(2026-D10,0.5),0),"") -> 17889 | K10: Yes | L10: AWD | M10: Gasoline | N10: 28 | O10: FAIR | P10: 35743 | Q10: -0.068 | R10: GREAT | S10: 280 | T10: Yes | U10: 1 | V10: Yes | W10: 6 | X10: Yes | Y10: Yes | Z10: Yes | AA10: Yes | AB10: Yes | AC10: Yes | AD10: No | AE10: No | AF10: No | AG10: No | AH10: No | AI10: Yes | AJ10: No | AK10: Gray | AL10: Black | AM10: 2.5 L 4 Cyl | AN10: Metro Toyota / DeNooyer Jaguar | AO10: Kalamazoo | AP10: MI | AQ10: 40.8 | AR10: 4.7 | AS10: 9 | AU10: 682.03 | AV10: 280 | AW10: 95.2 | AX10: 42.5 | AY10: 57.8 | AZ10: 52 | BA10: 100 | BB10: 45.5 | BC10: 2T3P1RFV9SW625840 | BD10: 2025 Toyota RAV4 | BE10: https://www.carfax.com/vehicle/2T3P1RFV9SW625840
A11: =RANK(B11,$B$5:$B$266) -> 7 | B11: =ROUND((AW11*'Scoring Weights'!$B$5+AX11*'Scoring Weights'!$B$6+AY11*'Scoring Weights'!$B$7+BA11*'Scoring Weights'!$B$8+AZ11*'Scoring Weights'!$B$9+BB11*'Scoring Weights'!$B$10)/MAX('Scoring Weights'!$B$11,1),1) -> 69 | C11: =IF(AND(H11<='Search Criteria'!$B$5,D11>='Search Criteria'!$B$6,AQ11<='Search Criteria'!$B$7,I11<=INDEX('Search Criteria'!$B$18:$B$20,MATCH(E11,'Search Criteria'!$A$18:$A$20,0)),OR(NOT('Search Criteria'!$B$8),L11<>"FWD"),OR(NOT('Search Criteria'!$B$9),T11="Yes"),OR(NOT('Search Criteria'!$B$10),W11>0),OR(NOT('Search Criteria'!$B$11),X11="Yes"),OR(NOT('Search Criteria'!$B$12),O11="GREAT",O11="GOOD"),OR(NOT('Search Criteria'!$B$13),K11="Yes")),"YES","no") -> no | D11: 2024 | E11: Honda | F11: CR-V | G11: Sport | H11: 34495 | I11: 22771 | J11: =IFERROR(ROUND(I11/MAX(2026-D11,0.5),0),"") -> 11386 | K11: Yes | L11: AWD | M11: Hybrid | N11: 37 | O11: None | P11: 33334 | Q11: -0.035 | R11: GREAT | S11: 790 | T11: Yes | U11: 1 | V11: Yes | W11: 11 | X11: Yes | Y11: Yes | Z11: No | AA11: Yes | AB11: Yes | AC11: No | AD11: Yes | AE11: No | AF11: No | AG11: No | AH11: No | AI11: Yes | AJ11: No | AK11: White | AL11: Black | AM11: 2.0 L 4 Cyl | AN11: Graff Toyota of Chesterton | AO11: Chesterton | AP11: IN | AQ11: 59.4 | AR11: 4.4 | AS11: 3 | AU11: 616.2 | AW11: 93.3 | AX11: 51.4 | AY11: 63.8 | AZ11: 42 | BA11: 100 | BB11: 20.8 | BC11: 5J6RS6H52RL023287 | BD11: 2024 Honda CR-V | BE11: https://www.carfax.com/vehicle/5J6RS6H52RL023287
A12: =RANK(B12,$B$5:$B$266) -> 7 | B12: =ROUND((AW12*'Scoring Weights'!$B$5+AX12*'Scoring Weights'!$B$6+AY12*'Scoring Weights'!$B$7+BA12*'Scoring Weights'!$B$8+AZ12*'Scoring Weights'!$B$9+BB12*'Scoring Weights'!$B$10)/MAX('Scoring Weights'!$B$11,1),1) -> 69 | C12: =IF(AND(H12<='Search Criteria'!$B$5,D12>='Search Criteria'!$B$6,AQ12<='Search Criteria'!$B$7,I12<=INDEX('Search Criteria'!$B$18:$B$20,MATCH(E12,'Search Criteria'!$A$18:$A$20,0)),OR(NOT('Search Criteria'!$B$8),L12<>"FWD"),OR(NOT('Search Criteria'!$B$9),T12="Yes"),OR(NOT('Search Criteria'!$B$10),W12>0),OR(NOT('Search Criteria'!$B$11),X12="Yes"),OR(NOT('Search Criteria'!$B$12),O12="GREAT",O12="GOOD"),OR(NOT('Search Criteria'!$B$13),K12="Yes")),"YES","no") -> YES | D12: 2024 | E12: Honda | F12: CR-V | G12: Sport | H12: 33809 | I12: 25381 | J12: =IFERROR(ROUND(I12/MAX(2026-D12,0.5),0),"") -> 12691 | K12: Yes | L12: AWD | M12: Hybrid | N12: 37 | O12: GOOD | P12: 33153 | Q12: -0.02 | R12: GREAT | S12: 600 | T12: Yes | U12: 1 | V12: Yes | W12: 6 | X12: Yes | Y12: Yes | Z12: No | AA12: Yes | AB12: Yes | AC12: No | AD12: Yes | AE12: No | AF12: No | AG12: No | AH12: No | AI12: Yes | AJ12: No | AK12: Blue | AL12: Black | AM12: 2.0 L 4 Cyl | AN12: Crown Motors Cadillac Buick Honda Mazda | AO12: Holland | AP12: MI | AQ12: 71 | AR12: 4.7 | AS12: 44 | AU12: 603.95 | AV12: 314 | AW12: 91 | AX12: 62.4 | AY12: 57.9 | AZ12: 42 | BA12: 100 | BB12: 5.4 | BC12: 7FARS6H5XRE073206 | BD12: 2024 Honda CR-V | BE12: https://www.carfax.com/vehicle/7FARS6H5XRE073206
A13: =RANK(B13,$B$5:$B$266) -> 9 | B13: =ROUND((AW13*'Scoring Weights'!$B$5+AX13*'Scoring Weights'!$B$6+AY13*'Scoring Weights'!$B$7+BA13*'Scoring Weights'!$B$8+AZ13*'Scoring Weights'!$B$9+BB13*'Scoring Weights'!$B$10)/MAX('Scoring Weights'!$B$11,1),1) -> 68.1 | C13: =IF(AND(H13<='Search Criteria'!$B$5,D13>='Search Criteria'!$B$6,AQ13<='Search Criteria'!$B$7,I13<=INDEX('Search Criteria'!$B$18:$B$20,MATCH(E13,'Search Criteria'!$A$18:$A$20,0)),OR(NOT('Search Criteria'!$B$8),L13<>"FWD"),OR(NOT('Search Criteria'!$B$9),T13="Yes"),OR(NOT('Search Criteria'!$B$10),W13>0),OR(NOT('Search Criteria'!$B$11),X13="Yes"),OR(NOT('Search Criteria'!$B$12),O13="GREAT",O13="GOOD"),OR(NOT('Search Criteria'!$B$13),K13="Yes")),"YES","no") -> YES | D13: 2026 | E13: Honda | F13: CR-V | G13: TrailSport | H13: 35913 | I13: 9420 | J13: =IFERROR(ROUND(I13/MAX(2026-D13,0.5),0),"") -> 18840 | K13: No | L13: AWD | M13: Hybrid | N13: 35 | O13: GREAT | P13: 36532 | Q13: 0.017 | R13: n/a | T13: Yes | U13: 1 | V13: Yes | W13: 3 | X13: Yes | Y13: Yes | Z13: Yes | AA13: Yes | AB13: Yes | AC13: Yes | AD13: Yes | AE13: Yes | AF13: No | AG13: Yes | AH13: No | AI13: Yes | AJ13: No | AK13: Gray | AL13: Black | AM13: 2.0 L 4 Cyl | AN13: Gurley Leep Kia | AO13: Mishawaka | AP13: IN | AQ13: 11 | AR13: 4.2 | AS13: 89 | AU13: 641.53 | AV13: 261 | AW13: 91.6 | AX13: 80 | AY13: 60.6 | AZ13: 82 | BA13: 0 | BB13: 85.3 | BC13: 7FARS6H69TE031075 | BD13: 2026 Honda CR-V | BE13: https://www.carfax.com/vehicle/7FARS6H69TE031075
A14: =RANK(B14,$B$5:$B$266) -> 10 | B14: =ROUND((AW14*'Scoring Weights'!$B$5+AX14*'Scoring Weights'!$B$6+AY14*'Scoring Weights'!$B$7+BA14*'Scoring Weights'!$B$8+AZ14*'Scoring Weights'!$B$9+BB14*'Scoring Weights'!$B$10)/MAX('Scoring Weights'!$B$11,1),1) -> 67.3 | C14: =IF(AND(H14<='Search Criteria'!$B$5,D14>='Search Criteria'!$B$6,AQ14<='Search Criteria'!$B$7,I14<=INDEX('Search Criteria'!$B$18:$B$20,MATCH(E14,'Search Criteria'!$A$18:$A$20,0)),OR(NOT('Search Criteria'!$B$8),L14<>"FWD"),OR(NOT('Search Criteria'!$B$9),T14="Yes"),OR(NOT('Search Criteria'!$B$10),W14>0),OR(NOT('Search Criteria'!$B$11),X14="Yes"),OR(NOT('Search Criteria'!$B$12),O14="GREAT",O14="GOOD"),OR(NOT('Search Criteria'!$B$13),K14="Yes")),"YES","no") -> no | D14: 2023 | E14: Honda | F14: HR-V | G14: EX-L | H14: 28814 | I14: 28383 | J14: =IFERROR(ROUND(I14/MAX(2026-D14,0.5),0),"") -> 9461 | K14: Yes | L14: AWD | M14: Gasoline | N14: 27 | O14: FAIR | P14: 26456 | Q14: -0.089 | R14: GREAT | S14: 220 | T14: Yes | U14: 2 | V14: No | W14: 12 | X14: Yes | Y14: Yes | Z14: No | AA14: Yes | AB14: Yes | AC14: No | AD14: Yes | AE14: No | AF14: No | AG14: Yes | AH14: Yes | AI14: Yes | AJ14: No | AK14: White | AL14: Black | AM14: 2.0 L 4 Cyl | AN14: Zeigler Chrysler Jeep Dodge Ram of Kalamazoo | AO14: Kalamazoo | AP14: MI | AQ14: 41.6 | AR14: 4.6 | AS14: 34 | AU14: 514.72 | AV14: 314 | AW14: 85.6 | AX14: 39.4 | AY14: 63 | AZ14: 56 | BA14: 100 | BB14: 44.5 | BC14: 3CZRZ2H72PM717026 | BD14: 2023 Honda HR-V | BE14: https://www.carfax.com/vehicle/3CZRZ2H72PM717026
A15: =RANK(B15,$B$5:$B$266) -> 11 | B15: =ROUND((AW15*'Scoring Weights'!$B$5+AX15*'Scoring Weights'!$B$6+AY15*'Scoring Weights'!$B$7+BA15*'Scoring Weights'!$B$8+AZ15*'Scoring Weights'!$B$9+BB15*'Scoring Weights'!$B$10)/MAX('Scoring Weights'!$B$11,1),1) -> 67 | C15: =IF(AND(H15<='Search Criteria'!$B$5,D15>='Search Criteria'!$B$6,AQ15<='Search Criteria'!$B$7,I15<=INDEX('Search Criteria'!$B$18:$B$20,MATCH(E15,'Search Criteria'!$A$18:$A$20,0)),OR(NOT('Search Criteria'!$B$8),L15<>"FWD"),OR(NOT('Search Criteria'!$B$9),T15="Yes"),OR(NOT('Search Criteria'!$B$10),W15>0),OR(NOT('Search Criteria'!$B$11),X15="Yes"),OR(NOT('Search Criteria'!$B$12),O15="GREAT",O15="GOOD"),OR(NOT('Search Criteria'!$B$13),K15="Yes")),"YES","no") -> no | D15: 2024 | E15: Honda | F15: HR-V | G15: LX | H15: 25990 | I15: 20818 | J15: =IFERROR(ROUND(I15/MAX(2026-D15,0.5),0),"") -> 10409 | K15: Yes | L15: AWD | M15: Gasoline | N15: 27 | O15: GOOD | P15: 27029 | Q15: 0.038 | R15: GREAT | S15: 220 | T15: Yes | U15: 1 | V15: Yes | W15: 0 | X15: No | Y15: Yes | Z15: No | AA15: No | AB15: No | AC15: No | AD15: No | AE15: No | AF15: No | AG15: No | AH15: No | AI15: No | AJ15: No | AK15: White | AL15: Black | AM15: 2.0 L 4 Cyl | AN15: Battle Creek Honda | AO15: Springfield | AP15: MI | AQ15: 56.8 | AR15: 4.5 | AS15: 2 | AU15: 464.27 | AV15: 314 | AW15: 88 | AX15: 71.2 | AY15: 68.2 | AZ15: 0 | BA15: 100 | BB15: 24.3 | BC15: 3CZRZ2H34RM718890 | BD15: 2024 Honda HR-V | BE15: https://www.carfax.com/vehicle/3CZRZ2H34RM718890
A16: =RANK(B16,$B$5:$B$266) -> 12 | B16: =ROUND((AW16*'Scoring Weights'!$B$5+AX16*'Scoring Weights'!$B$6+AY16*'Scoring Weights'!$B$7+BA16*'Scoring Weights'!$B$8+AZ16*'Scoring Weights'!$B$9+BB16*'Scoring Weights'!$B$10)/MAX('Scoring Weights'!$B$11,1),1) -> 66.8 | C16: =IF(AND(H16<='Search Criteria'!$B$5,D16>='Search Criteria'!$B$6,AQ16<='Search Criteria'!$B$7,I16<=INDEX('Search Criteria'!$B$18:$B$20,MATCH(E16,'Search Criteria'!$A$18:$A$20,0)),OR(NOT('Search Criteria'!$B$8),L16<>"FWD"),OR(NOT('Search Criteria'!$B$9),T16="Yes"),OR(NOT('Search Criteria'!$B$10),W16>0),OR(NOT('Search Criteria'!$B$11),X16="Yes"),OR(NOT('Search Criteria'!$B$12),O16="GREAT",O16="GOOD"),OR(NOT('Search Criteria'!$B$13),K16="Yes")),"YES","no") -> no | D16: 2025 | E16: Subaru | F16: Outback | G16: Onyx Edition | H16: 31360 | I16: 27136 | J16: =IFERROR(ROUND(I16/MAX(2026-D16,0.5),0),"") -> 27136 | K16: Yes | L16: AWD | M16: Gasoline | N16: 28 | O16: FAIR | P16: 31526 | Q16: 0.005 | R16: GREAT | S16: 290 | T16: Yes | U16: 1 | V16: No | W16: 1 | X16: Yes | Y16: Yes | Z16: Yes | AA16: Yes | AB16: Yes | AC16: Yes | AD16: Yes | AE16: No | AF16: No | AG16: No | AH16: Yes | AI16: Yes | AJ16: Yes | AK16: Gray | AL16: Gray | AM16: 2.5 L 4 Cyl | AN16: Fox Maple Hill | AO16: Kalamazoo | AP16: MI | AQ16: 42.8 | AS16: 17 | AT16: 1268 | AU16: 560.2 | AW16: 83.6 | AX16: 53.5 | AY16: 32 | AZ16: 74 | BA16: 100 | BB16: 42.9 | BC16: 4S4BTALC1S3218764 | BD16: 2025 Subaru Outback | BE16: https://www.carfax.com/vehicle/4S4BTALC1S3218764
A17: =RANK(B17,$B$5:$B$266) -> 13 | B17: =ROUND((AW17*'Scoring Weights'!$B$5+AX17*'Scoring Weights'!$B$6+AY17*'Scoring Weights'!$B$7+BA17*'Scoring Weights'!$B$8+AZ17*'Scoring Weights'!$B$9+BB17*'Scoring Weights'!$B$10)/MAX('Scoring Weights'!$B$11,1),1) -> 66.6 | C17: =IF(AND(H17<='Search Criteria'!$B$5,D17>='Search Criteria'!$B$6,AQ17<='Search Criteria'!$B$7,I17<=INDEX('Search Criteria'!$B$18:$B$20,MATCH(E17,'Search Criteria'!$A$18:$A$20,0)),OR(NOT('Search Criteria'!$B$8),L17<>"FWD"),OR(NOT('Search Criteria'!$B$9),T17="Yes"),OR(NOT('Search Criteria'!$B$10),W17>0),OR(NOT('Search Criteria'!$B$11),X17="Yes"),OR(NOT('Search Criteria'!$B$12),O17="GREAT",O17="GOOD"),OR(NOT('Search Criteria'!$B$13),K17="Yes")),"YES","no") -> YES | D17: 2023 | E17: Honda | F17: CR-V | G17: Sport Touring | H17: 32864 | I17: 34991 | J17: =IFERROR(ROUND(I17/MAX(2026-D17,0.5),0),"") -> 11664 | K17: No | L17: AWD | M17: Hybrid | N17: 37 | O17: GREAT | P17: 31351 | Q17: -0.048 | R17: n/a | T17: Yes | U17: 2 | V17: Yes | W17: 10 | X17: Yes | Y17: Yes | Z17: Yes | AA17: Yes | AB17: Yes | AC17: Yes | AD17: Yes | AE17: Yes | AF17: Yes | AG17: Yes | AH17: Yes | AI17: Yes | AJ17: Yes | AK17: Blue | AL17: Black | AM17: 2.0 L 4 Cyl | AN17: Gurley Leep Hyundai Subaru | AO17: Mishawaka | AP17: IN | AQ17: 10.8 | AR17: 4.5 | AS17: 25 | AU17: 587.07 | AV17: 261 | AW17: 91.2 | AX17: 70.3 | AY17: 50.8 | AZ17: 100 | BA17: 0 | BB17: 85.6 | BC17: 5J6RS6H93PL004196 | BD17: 2023 Honda CR-V | BE17: https://www.carfax.com/vehicle/5J6RS6H93PL004196
A18: =RANK(B18,$B$5:$B$266) -> 14 | B18: =ROUND((AW18*'Scoring Weights'!$B$5+AX18*'Scoring Weights'!$B$6+AY18*'Scoring Weights'!$B$7+BA18*'Scoring Weights'!$B$8+AZ18*'Scoring Weights'!$B$9+BB18*'Scoring Weights'!$B$10)/MAX('Scoring Weights'!$B$11,1),1) -> 66.5 | C18: =IF(AND(H18<='Search Criteria'!$B$5,D18>='Search Criteria'!$B$6,AQ18<='Search Criteria'!$B$7,I18<=INDEX('Search Criteria'!$B$18:$B$20,MATCH(E18,'Search Criteria'!$A$18:$A$20,0)),OR(NOT('Search Criteria'!$B$8),L18<>"FWD"),OR(NOT('Search Criteria'!$B$9),T18="Yes"),OR(NOT('Search Criteria'!$B$10),W18>0),OR(NOT('Search Criteria'!$B$11),X18="Yes"),OR(NOT('Search Criteria'!$B$12),O18="GREAT",O18="GOOD"),OR(NOT('Search Criteria'!$B$13),K18="Yes")),"YES","no") -> YES | D18: 2025 | E18: Honda | F18: CR-V | G18: EX | H18: 32809 | I18: 23351 | J18: =IFERROR(ROUND(I18/MAX(2026-D18,0.5),0),"") -> 23351 | K18: Yes | L18: AWD | M18: Gasoline | N18: 28 | O18: GOOD | P18: 34432 | Q18: 0.047 | R18: GREAT | S18: 840 | T18: Yes | U18: 1 | V18: Yes | W18: 3 | X18: Yes | Y18: Yes | Z18: No | AA18: Yes | AB18: Yes | AC18: No | AD18: No | AE18: No | AF18: No | AG18: No | AH18: No | AI18: Yes | AJ18: No | AK18: Silver | AL18: Gray | AM18: 1.5 L 4 Cyl | AN18: Crown Motors Cadillac Buick Honda Mazda | AO18: Holland | AP18: MI | AQ18: 71 | AR18: 4.7 | AS18: 32 | AU18: 586.09 | AV18: 314 | AW18: 87.4 | AX18: 72.5 | AY18: 46.6 | AZ18: 30 | BA18: 100 | BB18: 5.4 | BC18: 7FARS4H4XSE002962 | BD18: 2025 Honda CR-V | BE18: https://www.carfax.com/vehicle/7FARS4H4XSE002962
A19: =RANK(B19,$B$5:$B$266) -> 15 | B19: =ROUND((AW19*'Scoring Weights'!$B$5+AX19*'Scoring Weights'!$B$6+AY19*'Scoring Weights'!$B$7+BA19*'Scoring Weights'!$B$8+AZ19*'Scoring Weights'!$B$9+BB19*'Scoring Weights'!$B$10)/MAX('Scoring Weights'!$B$11,1),1) -> 66.1 | C19: =IF(AND(H19<='Search Criteria'!$B$5,D19>='Search Criteria'!$B$6,AQ19<='Search Criteria'!$B$7,I19<=INDEX('Search Criteria'!$B$18:$B$20,MATCH(E19,'Search Criteria'!$A$18:$A$20,0)),OR(NOT('Search Criteria'!$B$8),L19<>"FWD"),OR(NOT('Search Criteria'!$B$9),T19="Yes"),OR(NOT('Search Criteria'!$B$10),W19>0),OR(NOT('Search Criteria'!$B$11),X19="Yes"),OR(NOT('Search Criteria'!$B$12),O19="GREAT",O19="GOOD"),OR(NOT('Search Criteria'!$B$13),K19="Yes")),"YES","no") -> YES | D19: 2025 | E19: Honda | F19: CR-V | G19: Sport-L | H19: 34798 | I19: 20222 | J19: =IFERROR(ROUND(I19/MAX(2026-D19,0.5),0),"") -> 20222 | K19: No | L19: AWD | M19: Hybrid | N19: 37 | O19: GREAT | P19: 34648 | Q19: -0.004 | R19: n/a | T19: Yes | U19: 1 | V19: Yes | W19: 7 | X19: Yes | Y19: Yes | Z19: No | AA19: Yes | AB19: Yes | AC19: Yes | AD19: Yes | AE19: Yes | AF19: No | AG19: Yes | AH19: Yes | AI19: Yes | AJ19: No | AK19: Silver | AL19: Black | AM19: 2.0 L 4 Cyl | AN19: Jordan Lexus of Mishawaka | AO19: Mishawaka | AP19: IN | AQ19: 11.1 | AR19: 4.7 | AS19: 19 | AT19: -49 | AU19: 621.62 | AV19: 250 | AW19: 96.4 | AX19: 76.8 | AY19: 49.8 | AZ19: 78 | BA19: 0 | BB19: 85.2 | BC19: 7FARS6H82SE006423 | BD19: 2025 Honda CR-V | BE19: https://www.carfax.com/vehicle/7FARS6H82SE006423
A20: =RANK(B20,$B$5:$B$266) -> 16 | B20: =ROUND((AW20*'Scoring Weights'!$B$5+AX20*'Scoring Weights'!$B$6+AY20*'Scoring Weights'!$B$7+BA20*'Scoring Weights'!$B$8+AZ20*'Scoring Weights'!$B$9+BB20*'Scoring Weights'!$B$10)/MAX('Scoring Weights'!$B$11,1),1) -> 64.8 | C20: =IF(AND(H20<='Search Criteria'!$B$5,D20>='Search Criteria'!$B$6,AQ20<='Search Criteria'!$B$7,I20<=INDEX('Search Criteria'!$B$18:$B$20,MATCH(E20,'Search Criteria'!$A$18:$A$20,0)),OR(NOT('Search Criteria'!$B$8),L20<>"FWD"),OR(NOT('Search Criteria'!$B$9),T20="Yes"),OR(NOT('Search Criteria'!$B$10),W20>0),OR(NOT('Search Criteria'!$B$11),X20="Yes"),OR(NOT('Search Criteria'!$B$12),O20="GREAT",O20="GOOD"),OR(NOT('Search Criteria'!$B$13),K20="Yes")),"YES","no") -> no | D20: 2025 | E20: Toyota | F20: RAV4 | G20: XLE | H20: 32997 | I20: 27008 | J20: =IFERROR(ROUND(I20/MAX(2026-D20,0.5),0),"") -> 27008 | K20: Yes | L20: AWD | M20: Gasoline | N20: 28 | O20: GREAT | P20: 35015 | Q20: 0.058 | R20: GREAT | S20: 220 | T20: No | U20: 1 | V20: No | W20: 1 | X20: No | Y20: Yes | Z20: No | AA20: No | AB20: Yes | AC20: No | AD20: No | AE20: No | AF20: No | AG20: No | AH20: No | AI20: Yes | AJ20: No | AK20: Silver | AL20: Black | AM20: 2.5 L 4 Cyl | AN20: Sunshine Toyota | AO20: Springfield | AP20: MI | AQ20: 56.8 | AR20: 4.6 | AS20: 107 | AU20: 589.44 | AV20: 345 | AW20: 70 | AX20: 86.1 | AY20: 51.1 | AZ20: 16 | BA20: 100 | BB20: 24.2 | BC20: 2T3P1RFV7SW568876 | BD20: 2025 Toyota RAV4 | BE20: https://www.carfax.com/vehicle/2T3P1RFV7SW568876
A21: =RANK(B21,$B$5:$B$266) -> 16 | B21: =ROUND((AW21*'Scoring Weights'!$B$5+AX21*'Scoring Weights'!$B$6+AY21*'Scoring Weights'!$B$7+BA21*'Scoring Weights'!$B$8+AZ21*'Scoring Weights'!$B$9+BB21*'Scoring Weights'!$B$10)/MAX('Scoring Weights'!$B$11,1),1) -> 64.8 | C21: =IF(AND(H21<='Search Criteria'!$B$5,D21>='Search Criteria'!$B$6,AQ21<='Search Criteria'!$B$7,I21<=INDEX('Search Criteria'!$B$18:$B$20,MATCH(E21,'Search Criteria'!$A$18:$A$20,0)),OR(NOT('Search Criteria'!$B$8),L21<>"FWD"),OR(NOT('Search Criteria'!$B$9),T21="Yes"),OR(NOT('Search Criteria'!$B$10),W21>0),OR(NOT('Search Criteria'!$B$11),X21="Yes"),OR(NOT('Search Criteria'!$B$12),O21="GREAT",O21="GOOD"),OR(NOT('Search Criteria'!$B$13),K21="Yes")),"YES","no") -> no | D21: 2025 | E21: Toyota | F21: RAV4 | G21: LE | H21: 30250 | I21: 36011 | J21: =IFERROR(ROUND(I21/MAX(2026-D21,0.5),0),"") -> 36011 | K21: Yes | L21: FWD | M21: Gasoline | N21: 30 | O21: GREAT | P21: 34297 | Q21: 0.118 | R21: GREAT | S21: 290 | T21: Yes | U21: 2 | V21: No | W21: 2 | X21: No | Y21: Yes | Z21: No | AA21: No | AB21: No | AC21: No | AD21: No | AE21: No | AF21: No | AG21: No | AH21: No | AI21: No | AJ21: No | AK21: Black | AL21: Black | AM21: 2.5 L 4 Cyl | AN21: Evans Toyota | AO21: Fort Wayne | AP21: IN | AQ21: 59.9 | AR21: 4.5 | AS21: 80 | AU21: 540.37 | AV21: 262 | AW21: 76 | AX21: 95.2 | AY21: 44.8 | AZ21: 0 | BA21: 100 | BB21: 20.2 | BC21: 2T3H1RFV3SW373233 | BD21: 2025 Toyota RAV4 | BE21: https://www.carfax.com/vehicle/2T3H1RFV3SW373233
A22: =RANK(B22,$B$5:$B$266) -> 18 | B22: =ROUND((AW22*'Scoring Weights'!$B$5+AX22*'Scoring Weights'!$B$6+AY22*'Scoring Weights'!$B$7+BA22*'Scoring Weights'!$B$8+AZ22*'Scoring Weights'!$B$9+BB22*'Scoring Weights'!$B$10)/MAX('Scoring Weights'!$B$11,1),1) -> 64.6 | C22: =IF(AND(H22<='Search Criteria'!$B$5,D22>='Search Criteria'!$B$6,AQ22<='Search Criteria'!$B$7,I22<=INDEX('Search Criteria'!$B$18:$B$20,MATCH(E22,'Search Criteria'!$A$18:$A$20,0)),OR(NOT('Search Criteria'!$B$8),L22<>"FWD"),OR(NOT('Search Criteria'!$B$9),T22="Yes"),OR(NOT('Search Criteria'!$B$10),W22>0),OR(NOT('Search Criteria'!$B$11),X22="Yes"),OR(NOT('Search Criteria'!$B$12),O22="GREAT",O22="GOOD"),OR(NOT('Search Criteria'!$B$13),K22="Yes")),"YES","no") -> YES | D22: 2024 | E22: Toyota | F22: RAV4 | G22: Limited Edition | H22: 39338 | I22: 17459 | J22: =IFERROR(ROUND(I22/MAX(2026-D22,0.5),0),"") -> 8730 | K22: No | L22: AWD | M22: Gasoline | N22: 28 | O22: GOOD | P22: 34583 | Q22: -0.137 | R22: n/a | T22: Yes | U22: 1 | V22: Yes | W22: 5 | X22: Yes | Y22: Yes | Z22: Yes | AA22: Yes | AB22: Yes | AC22: Yes | AD22: Yes | AE22: No | AF22: Yes | AG22: No | AH22: Yes | AI22: Yes | AJ22: Yes | AK22: White | AL22: Tan | AM22: 2.5 L 4 Cyl | AN22: Gurley Leep Buick GMC Cadillac | AO22: Mishawaka | AP22: IN | AQ22: 10.7 | AR22: 4.5 | AS22: 3 | AU22: 702.72 | AV22: 261 | AW22: 94 | AX22: 44.8 | AY22: 81 | AZ22: 82 | BA22: 0 | BB22: 85.8 | BC22: 2T3N1RFV3RW451961 | BD22: 2024 Toyota RAV4 | BE22: https://www.carfax.com/vehicle/2T3N1RFV3RW451961
A23: =RANK(B23,$B$5:$B$266) -> 19 | B23: =ROUND((AW23*'Scoring Weights'!$B$5+AX23*'Scoring Weights'!$B$6+AY23*'Scoring Weights'!$B$7+BA23*'Scoring Weights'!$B$8+AZ23*'Scoring Weights'!$B$9+BB23*'Scoring Weights'!$B$10)/MAX('Scoring Weights'!$B$11,1),1) -> 64.5 | C23: =IF(AND(H23<='Search Criteria'!$B$5,D23>='Search Criteria'!$B$6,AQ23<='Search Criteria'!$B$7,I23<=INDEX('Search Criteria'!$B$18:$B$20,MATCH(E23,'Search Criteria'!$A$18:$A$20,0)),OR(NOT('Search Criteria'!$B$8),L23<>"FWD"),OR(NOT('Search Criteria'!$B$9),T23="Yes"),OR(NOT('Search Criteria'!$B$10),W23>0),OR(NOT('Search Criteria'!$B$11),X23="Yes"),OR(NOT('Search Criteria'!$B$12),O23="GREAT",O23="GOOD"),OR(NOT('Search Criteria'!$B$13),K23="Yes")),"YES","no") -> YES | D23: 2024 | E23: Honda | F23: CR-V | G23: Sport-L | H23: 35190 | I23: 23100 | J23: =IFERROR(ROUND(I23/MAX(2026-D23,0.5),0),"") -> 11550 | K23: No | L23: AWD | M23: Hybrid | N23: 37 | O23: GREAT | P23: 33311 | Q23: -0.056 | R23: n/a | T23: Yes | U23: 2 | V23: Yes | W23: 10 | X23: Yes | Y23: Yes | Z23: No | AA23: Yes | AB23: Yes | AC23: Yes | AD23: Yes | AE23: No | AF23: No | AG23: Yes | AH23: Yes | AI23: Yes | AJ23: No | AK23: Gray | AL23: Black | AM23: 2.0 L 4 Cyl | AN23: Zeigler Ford Lincoln Elkhart | AO23: Elkhart | AP23: IN | AQ23: 3.1 | AR23: 4.6 | AS23: 46 | AU23: 628.62 | AV23: 283 | AW23: 91.2 | AX23: 69 | AY23: 63 | AZ23: 68 | BA23: 0 | BB23: 95.9 | BC23: 7FARS6H8XRE020161 | BD23: 2024 Honda CR-V | BE23: https://www.carfax.com/vehicle/7FARS6H8XRE020161
A24: =RANK(B24,$B$5:$B$266) -> 20 | B24: =ROUND((AW24*'Scoring Weights'!$B$5+AX24*'Scoring Weights'!$B$6+AY24*'Scoring Weights'!$B$7+BA24*'Scoring Weights'!$B$8+AZ24*'Scoring Weights'!$B$9+BB24*'Scoring Weights'!$B$10)/MAX('Scoring Weights'!$B$11,1),1) -> 63.9 | C24: =IF(AND(H24<='Search Criteria'!$B$5,D24>='Search Criteria'!$B$6,AQ24<='Search Criteria'!$B$7,I24<=INDEX('Search Criteria'!$B$18:$B$20,MATCH(E24,'Search Criteria'!$A$18:$A$20,0)),OR(NOT('Search Criteria'!$B$8),L24<>"FWD"),OR(NOT('Search Criteria'!$B$9),T24="Yes"),OR(NOT('Search Criteria'!$B$10),W24>0),OR(NOT('Search Criteria'!$B$11),X24="Yes"),OR(NOT('Search Criteria'!$B$12),O24="GREAT",O24="GOOD"),OR(NOT('Search Criteria'!$B$13),K24="Yes")),"YES","no") -> YES | D24: 2023 | E24: Honda | F24: CR-V | G24: EXL | H24: 32149 | I24: 29404 | J24: =IFERROR(ROUND(I24/MAX(2026-D24,0.5),0),"") -> 9801 | K24: No | L24: AWD | M24: Gasoline | N24: 29 | O24: GOOD | P24: 31737 | Q24: -0.013 | R24: GREAT | S24: 320 | T24: Yes | U24: 2 | V24: Yes | W24: 13 | X24: Yes | Y24: Yes | Z24: No | AA24: Yes | AB24: Yes | AC24: Yes | AD24: Yes | AE24: Yes | AF24: No | AG24: Yes | AH24: Yes | AI24: Yes | AJ24: No | AK24: Blue | AL24: Black | AM24: 1.5 L 4 Cyl | AN24: Jordan Ford | AO24: Mishawaka | AP24: IN | AQ24: 10.7 | AR24: 4.6 | AS24: 17 | AU24: 574.3 | AV24: 250 | AW24: 91.2 | AX24: 63.5 | AY24: 61.1 | AZ24: 78 | BA24: 0 | BB24: 85.7 | BC24: 5J6RS4H76PL000890 | BD24: 2023 Honda CR-V | BE24: https://www.carfax.com/vehicle/5J6RS4H76PL000890
A25: =RANK(B25,$B$5:$B$266) -> 20 | B25: =ROUND((AW25*'Scoring Weights'!$B$5+AX25*'Scoring Weights'!$B$6+AY25*'Scoring Weights'!$B$7+BA25*'Scoring Weights'!$B$8+AZ25*'Scoring Weights'!$B$9+BB25*'Scoring Weights'!$B$10)/MAX('Scoring Weights'!$B$11,1),1) -> 63.9 | C25: =IF(AND(H25<='Search Criteria'!$B$5,D25>='Search Criteria'!$B$6,AQ25<='Search Criteria'!$B$7,I25<=INDEX('Search Criteria'!$B$18:$B$20,MATCH(E25,'Search Criteria'!$A$18:$A$20,0)),OR(NOT('Search Criteria'!$B$8),L25<>"FWD"),OR(NOT('Search Criteria'!$B$9),T25="Yes"),OR(NOT('Search Criteria'!$B$10),W25>0),OR(NOT('Search Criteria'!$B$11),X25="Yes"),OR(NOT('Search Criteria'!$B$12),O25="GREAT",O25="GOOD"),OR(NOT('Search Criteria'!$B$13),K25="Yes")),"YES","no") -> no | D25: 2024 | E25: Honda | F25: HR-V | G25: LX | H25: 24809 | I25: 37974 | J25: =IFERROR(ROUND(I25/MAX(2026-D25,0.5),0),"") -> 18987 | K25: Yes | L25: AWD | M25: Gasoline | N25: 27 | O25: GREAT | P25: 25986 | Q25: 0.045 | R25: GREAT | S25: 670 | T25: Yes | U25: 1 | V25: Yes | W25: 8 | X25: No | Y25: Yes | Z25: No | AA25: No | AB25: No | AC25: No | AD25: No | AE25: No | AF25: No | AG25: No | AH25: No | AI25: No | AJ25: No | AK25: White | AL25: Gray | AM25: 2.0 L 4 Cyl | AN25: Crown Motors Cadillac Buick Honda Mazda | AO25: Holland | AP25: MI | AQ25: 71 | AR25: 4.7 | AS25: 40 | AT25: 1186 | AU25: 443.18 | AV25: 314 | AW25: 93.4 | AX25: 84.3 | AY25: 32 | AZ25: 0 | BA25: 100 | BB25: 5.4 | BC25: 3CZRZ2H32RM708066 | BD25: 2024 Honda HR-V | BE25: https://www.carfax.com/vehicle/3CZRZ2H32RM708066
A26: =RANK(B26,$B$5:$B$266) -> 22 | B26: =ROUND((AW26*'Scoring Weights'!$B$5+AX26*'Scoring Weights'!$B$6+AY26*'Scoring Weights'!$B$7+BA26*'Scoring Weights'!$B$8+AZ26*'Scoring Weights'!$B$9+BB26*'Scoring Weights'!$B$10)/MAX('Scoring Weights'!$B$11,1),1) -> 63.7 | C26: =IF(AND(H26<='Search Criteria'!$B$5,D26>='Search Criteria'!$B$6,AQ26<='Search Criteria'!$B$7,I26<=INDEX('Search Criteria'!$B$18:$B$20,MATCH(E26,'Search Criteria'!$A$18:$A$20,0)),OR(NOT('Search Criteria'!$B$8),L26<>"FWD"),OR(NOT('Search Criteria'!$B$9),T26="Yes"),OR(NOT('Search Criteria'!$B$10),W26>0),OR(NOT('Search Criteria'!$B$11),X26="Yes"),OR(NOT('Search Criteria'!$B$12),O26="GREAT",O26="GOOD"),OR(NOT('Search Criteria'!$B$13),K26="Yes")),"YES","no") -> no | D26: 2025 | E26: Toyota | F26: RAV4 | G26: XLE | H26: 32997 | I26: 38459 | J26: =IFERROR(ROUND(I26/MAX(2026-D26,0.5),0),"") -> 38459 | K26: Yes | L26: AWD | M26: Gasoline | N26: 28 | O26: GOOD | P26: 34101 | Q26: 0.032 | R26: GREAT | S26: 280 | T26: Yes | U26: 1 | V26: No | W26: 2 | X26: No | Y26: Yes | Z26: No | AA26: No | AB26: Yes | AC26: No | AD26: No | AE26: No | AF26: No | AG26: No | AH26: No | AI26: Yes | AJ26: No | AK26: Black | AL26: Black | AM26: 2.5 L 4 Cyl | AN26: Sunshine Toyota | AO26: Springfield | AP26: MI | AQ26: 56.8 | AR26: 4.6 | AS26: 57 | AU26: 589.44 | AV26: 345 | AW26: 84.8 | AX26: 70.3 | AY26: 43.1 | AZ26: 16 | BA26: 100 | BB26: 24.2 | BC26: 2T3P1RFV7SC539038 | BD26: 2025 Toyota RAV4 | BE26: https://www.carfax.com/vehicle/2T3P1RFV7SC539038
A27: =RANK(B27,$B$5:$B$266) -> 22 | B27: =ROUND((AW27*'Scoring Weights'!$B$5+AX27*'Scoring Weights'!$B$6+AY27*'Scoring Weights'!$B$7+BA27*'Scoring Weights'!$B$8+AZ27*'Scoring Weights'!$B$9+BB27*'Scoring Weights'!$B$10)/MAX('Scoring Weights'!$B$11,1),1) -> 63.7 | C27: =IF(AND(H27<='Search Criteria'!$B$5,D27>='Search Criteria'!$B$6,AQ27<='Search Criteria'!$B$7,I27<=INDEX('Search Criteria'!$B$18:$B$20,MATCH(E27,'Search Criteria'!$A$18:$A$20,0)),OR(NOT('Search Criteria'!$B$8),L27<>"FWD"),OR(NOT('Search Criteria'!$B$9),T27="Yes"),OR(NOT('Search Criteria'!$B$10),W27>0),OR(NOT('Search Criteria'!$B$11),X27="Yes"),OR(NOT('Search Criteria'!$B$12),O27="GREAT",O27="GOOD"),OR(NOT('Search Criteria'!$B$13),K27="Yes")),"YES","no") -> YES | D27: 2024 | E27: Honda | F27: CR-V | G27: Sport Touring | H27: 35270 | I27: 34486 | J27: =IFERROR(ROUND(I27/MAX(2026-D27,0.5),0),"") -> 17243 | K27: No | L27: AWD | M27: Hybrid | N27: 37 | O27: GREAT | P27: 32524 | Q27: -0.084 | R27: n/a | T27: Yes | U27: 1 | V27: Yes | W27: 10 | X27: Yes | Y27: Yes | Z27: Yes | AA27: Yes | AB27: Yes | AC27: Yes | AD27: Yes | AE27: Yes | AF27: Yes | AG27: Yes | AH27: Yes | AI27: Yes | AJ27: Yes | AK27: Black | AL27: Gray | AM27: 2.0 L 4 Cyl | AN27: Signature Toyota Hyundai | AO27: Benton Harbor | AP27: MI | AQ27: 34.7 | AR27: 4.6 | AS27: 18 | AU27: 630.05 | AV27: 280 | AW27: 100 | AX27: 64.8 | AY27: 37.4 | AZ27: 100 | BA27: 0 | BB27: 53.7 | BC27: 7FARS6H92RE014122 | BD27: 2024 Honda CR-V | BE27: https://www.carfax.com/vehicle/7FARS6H92RE014122
A28: =RANK(B28,$B$5:$B$266) -> 24 | B28: =ROUND((AW28*'Scoring Weights'!$B$5+AX28*'Scoring Weights'!$B$6+AY28*'Scoring Weights'!$B$7+BA28*'Scoring Weights'!$B$8+AZ28*'Scoring Weights'!$B$9+BB28*'Scoring Weights'!$B$10)/MAX('Scoring Weights'!$B$11,1),1) -> 63.4 | C28: =IF(AND(H28<='Search Criteria'!$B$5,D28>='Search Criteria'!$B$6,AQ28<='Search Criteria'!$B$7,I28<=INDEX('Search Criteria'!$B$18:$B$20,MATCH(E28,'Search Criteria'!$A$18:$A$20,0)),OR(NOT('Search Criteria'!$B$8),L28<>"FWD"),OR(NOT('Search Criteria'!$B$9),T28="Yes"),OR(NOT('Search Criteria'!$B$10),W28>0),OR(NOT('Search Criteria'!$B$11),X28="Yes"),OR(NOT('Search Criteria'!$B$12),O28="GREAT",O28="GOOD"),OR(NOT('Search Criteria'!$B$13),K28="Yes")),"YES","no") -> no | D28: 2024 | E28: Honda | F28: HR-V | G28: EX-L | H28: 29950 | I28: 14796 | J28: =IFERROR(ROUND(I28/MAX(2026-D28,0.5),0),"") -> 7398 | K28: No | L28: AWD | M28: Gasoline | N28: 27 | O28: None | P28: 27395 | Q28: -0.093 | R28: GREAT | S28: 180 | T28: Yes | U28: 1 | V28: Yes | W28: 7 | X28: Yes | Y28: Yes | Z28: No | AA28: Yes | AB28: Yes | AC28: No | AD28: Yes | AE28: Yes | AF28: No | AG28: Yes | AH28: Yes | AI28: Yes | AJ28: No | AK28: White | AL28: Unspecified | AM28: 2.0 L 4 Cyl | AN28: Gurley Leep Honda | AO28: Elkhart | AP28: IN | AQ28: 0.4 | AR28: 4.6 | AS28: 8 | AT28: -57 | AU28: 535.01 | AV28: 261 | AW28: 96.4 | AX28: 42.6 | AY28: 81.7 | AZ28: 66 | BA28: 0 | BB28: 99.4 | BC28: 3CZRZ2H77RM723987 | BD28: 2024 Honda HR-V | BE28: https://www.carfax.com/vehicle/3CZRZ2H77RM723987
A29: =RANK(B29,$B$5:$B$266) -> 25 | B29: =ROUND((AW29*'Scoring Weights'!$B$5+AX29*'Scoring Weights'!$B$6+AY29*'Scoring Weights'!$B$7+BA29*'Scoring Weights'!$B$8+AZ29*'Scoring Weights'!$B$9+BB29*'Scoring Weights'!$B$10)/MAX('Scoring Weights'!$B$11,1),1) -> 63.2 | C29: =IF(AND(H29<='Search Criteria'!$B$5,D29>='Search Criteria'!$B$6,AQ29<='Search Criteria'!$B$7,I29<=INDEX('Search Criteria'!$B$18:$B$20,MATCH(E29,'Search Criteria'!$A$18:$A$20,0)),OR(NOT('Search Criteria'!$B$8),L29<>"FWD"),OR(NOT('Search Criteria'!$B$9),T29="Yes"),OR(NOT('Search Criteria'!$B$10),W29>0),OR(NOT('Search Criteria'!$B$11),X29="Yes"),OR(NOT('Search Criteria'!$B$12),O29="GREAT",O29="GOOD"),OR(NOT('Search Criteria'!$B$13),K29="Yes")),"YES","no") -> YES | D29: 2024 | E29: Honda | F29: CR-V | G29: Sport-L | H29: 34185 | I29: 34150 | J29: =IFERROR(ROUND(I29/MAX(2026-D29,0.5),0),"") -> 17075 | K29: No | L29: AWD | M29: Hybrid | N29: 37 | O29: GREAT | P29: 32547 | Q29: -0.05 | R29: n/a | T29: Yes | U29: 1 | V29: Yes | W29: 7 | X29: Yes | Y29: Yes | Z29: No | AA29: Yes | AB29: Yes | AC29: Yes | AD29: Yes | AE29: Yes | AF29: No | AG29: Yes | AH29: Yes | AI29: Yes | AJ29: No | AK29: Blue | AL29: Black | AM29: 2.0 L 4 Cyl | AN29: Gurley Leep Honda | AO29: Elkhart | AP29: IN | AQ29: 0.4 | AR29: 4.6 | AS29: 8 | AT29: 5601 | AU29: 610.67 | AV29: 261 | AW29: 96.4 | AX29: 70 | AY29: 38.2 | AZ29: 78 | BA29: 0 | BB29: 99.4 | BC29: 7FARS6H84RE043984 | BD29: 2024 Honda CR-V | BE29: https://www.carfax.com/vehicle/7FARS6H84RE043984
A30: =RANK(B30,$B$5:$B$266) -> 26 | B30: =ROUND((AW30*'Scoring Weights'!$B$5+AX30*'Scoring Weights'!$B$6+AY30*'Scoring Weights'!$B$7+BA30*'Scoring Weights'!$B$8+AZ30*'Scoring Weights'!$B$9+BB30*'Scoring Weights'!$B$10)/MAX('Scoring Weights'!$B$11,1),1) -> 63 | C30: =IF(AND(H30<='Search Criteria'!$B$5,D30>='Search Criteria'!$B$6,AQ30<='Search Criteria'!$B$7,I30<=INDEX('Search Criteria'!$B$18:$B$20,MATCH(E30,'Search Criteria'!$A$18:$A$20,0)),OR(NOT('Search Criteria'!$B$8),L30<>"FWD"),OR(NOT('Search Criteria'!$B$9),T30="Yes"),OR(NOT('Search Criteria'!$B$10),W30>0),OR(NOT('Search Criteria'!$B$11),X30="Yes"),OR(NOT('Search Criteria'!$B$12),O30="GREAT",O30="GOOD"),OR(NOT('Search Criteria'!$B$13),K30="Yes")),"YES","no") -> no | D30: 2022 | E30: Toyota | F30: RAV4 | G30: XLE | H30: 27864 | I30: 46688 | J30: =IFERROR(ROUND(I30/MAX(2026-D30,0.5),0),"") -> 11672 | K30: No | L30: AWD | M30: Gasoline | N30: 28 | O30: GREAT | P30: 29861 | Q30: 0.067 | R30: GREAT | S30: 260 | T30: No | U30: 1 | V30: Yes | W30: 12 | X30: Yes | Y30: Yes | Z30: Yes | AA30: Yes | AB30: Yes | AC30: Yes | AD30: No | AE30: No | AF30: No | AG30: No | AH30: No | AI30: Yes | AJ30: No | AK30: Black | AL30: Black | AM30: 2.5 L 4 Cyl | AN30: Gates Of Granger | AO30: Granger | AP30: IN | AQ30: 7.6 | AR30: 4.7 | AS30: 65 | AU30: 497.75 | AV30: 250 | AW30: 86.4 | AX30: 87.5 | AY30: 53.1 | AZ30: 52 | BA30: 0 | BB30: 89.9 | BC30: 2T3P1RFV3NC285087 | BD30: 2022 Toyota RAV4 | BE30: https://www.carfax.com/vehicle/2T3P1RFV3NC285087
A31: =RANK(B31,$B$5:$B$266) -> 26 | B31: =ROUND((AW31*'Scoring Weights'!$B$5+AX31*'Scoring Weights'!$B$6+AY31*'Scoring Weights'!$B$7+BA31*'Scoring Weights'!$B$8+AZ31*'Scoring Weights'!$B$9+BB31*'Scoring Weights'!$B$10)/MAX('Scoring Weights'!$B$11,1),1) -> 63 | C31: =IF(AND(H31<='Search Criteria'!$B$5,D31>='Search Criteria'!$B$6,AQ31<='Search Criteria'!$B$7,I31<=INDEX('Search Criteria'!$B$18:$B$20,MATCH(E31,'Search Criteria'!$A$18:$A$20,0)),OR(NOT('Search Criteria'!$B$8),L31<>"FWD"),OR(NOT('Search Criteria'!$B$9),T31="Yes"),OR(NOT('Search Criteria'!$B$10),W31>0),OR(NOT('Search Criteria'!$B$11),X31="Yes"),OR(NOT('Search Criteria'!$B$12),O31="GREAT",O31="GOOD"),OR(NOT('Search Criteria'!$B$13),K31="Yes")),"YES","no") -> no | D31: 2024 | E31: Honda | F31: CR-V | G31: Sport-L | H31: 37990 | I31: 23944 | J31: =IFERROR(ROUND(I31/MAX(2026-D31,0.5),0),"") -> 11972 | K31: Yes | L31: AWD | M31: Hybrid | N31: 37 | O31: FAIR | P31: 33253 | Q31: -0.142 | R31: GREAT | S31: 460 | T31: No | U31: 1 | V31: Yes | W31: 1 | X31: Yes | Y31: Yes | Z31: No | AA31: Yes | AB31: Yes | AC31: Yes | AD31: Yes | AE31: Yes | AF31: No | AG31: Yes | AH31: Yes | AI31: Yes | AJ31: No | AK31: Red | AL31: Black | AM31: 2.0 L 4 Cyl | AN31: Battle Creek Honda | AO31: Springfield | AP31: MI | AQ31: 56.8 | AR31: 4.5 | AS31: 65 | AU31: 678.64 | AV31: 314 | AW31: 68.9 | AX31: 31.4 | AY31: 61.1 | AZ31: 78 | BA31: 100 | BB31: 24.3 | BC31: 7FARS6H8XRE056819 | BD31: 2024 Honda CR-V | BE31: https://www.carfax.com/vehicle/7FARS6H8XRE056819
A32: =RANK(B32,$B$5:$B$266) -> 28 | B32: =ROUND((AW32*'Scoring Weights'!$B$5+AX32*'Scoring Weights'!$B$6+AY32*'Scoring Weights'!$B$7+BA32*'Scoring Weights'!$B$8+AZ32*'Scoring Weights'!$B$9+BB32*'Scoring Weights'!$B$10)/MAX('Scoring Weights'!$B$11,1),1) -> 62.9 | C32: =IF(AND(H32<='Search Criteria'!$B$5,D32>='Search Criteria'!$B$6,AQ32<='Search Criteria'!$B$7,I32<=INDEX('Search Criteria'!$B$18:$B$20,MATCH(E32,'Search Criteria'!$A$18:$A$20,0)),OR(NOT('Search Criteria'!$B$8),L32<>"FWD"),OR(NOT('Search Criteria'!$B$9),T32="Yes"),OR(NOT('Search Criteria'!$B$10),W32>0),OR(NOT('Search Criteria'!$B$11),X32="Yes"),OR(NOT('Search Criteria'!$B$12),O32="GREAT",O32="GOOD"),OR(NOT('Search Criteria'!$B$13),K32="Yes")),"YES","no") -> YES | D32: 2025 | E32: Toyota | F32: RAV4 | G32: XLE | H32: 36252 | I32: 14982 | J32: =IFERROR(ROUND(I32/MAX(2026-D32,0.5),0),"") -> 14982 | K32: No | L32: AWD | M32: Hybrid | N32: 39 | O32: GREAT | P32: 35975 | Q32: -0.008 | R32: GREAT | S32: 280 | T32: Yes | U32: 1 | V32: Yes | W32: 4 | X32: Yes | Y32: Yes | Z32: Yes | AA32: Yes | AB32: Yes | AC32: No | AD32: No | AE32: No | AF32: No | AG32: No | AH32: No | AI32: Yes | AJ32: No | AK32: Black | AL32: Black | AM32: 2.5 L 4 Cyl | AN32: Michiana Chrysler Dodge Jeep Ram Fiat | AO32: Mishawaka | AP32: IN | AQ32: 11 | AR32: 4.2 | AS32: 8 | AU32: 647.59 | AV32: 261 | AW32: 92.8 | AX32: 76.3 | AY32: 67.1 | AZ32: 40 | BA32: 0 | BB32: 85.3 | BC32: 4T3RWRFV4SU211732 | BD32: 2025 Toyota RAV4 | BE32: https://www.carfax.com/vehicle/4T3RWRFV4SU211732
A33: =RANK(B33,$B$5:$B$266) -> 29 | B33: =ROUND((AW33*'Scoring Weights'!$B$5+AX33*'Scoring Weights'!$B$6+AY33*'Scoring Weights'!$B$7+BA33*'Scoring Weights'!$B$8+AZ33*'Scoring Weights'!$B$9+BB33*'Scoring Weights'!$B$10)/MAX('Scoring Weights'!$B$11,1),1) -> 62.7 | C33: =IF(AND(H33<='Search Criteria'!$B$5,D33>='Search Criteria'!$B$6,AQ33<='Search Criteria'!$B$7,I33<=INDEX('Search Criteria'!$B$18:$B$20,MATCH(E33,'Search Criteria'!$A$18:$A$20,0)),OR(NOT('Search Criteria'!$B$8),L33<>"FWD"),OR(NOT('Search Criteria'!$B$9),T33="Yes"),OR(NOT('Search Criteria'!$B$10),W33>0),OR(NOT('Search Criteria'!$B$11),X33="Yes"),OR(NOT('Search Criteria'!$B$12),O33="GREAT",O33="GOOD"),OR(NOT('Search Criteria'!$B$13),K33="Yes")),"YES","no") -> YES | D33: 2025 | E33: Toyota | F33: RAV4 | G33: XLE | H33: 35719 | I33: 54139 | J33: =IFERROR(ROUND(I33/MAX(2026-D33,0.5),0),"") -> 54139 | K33: Yes | L33: AWD | M33: Hybrid | N33: 39 | O33: GOOD | P33: 32850 | Q33: -0.087 | R33: GREAT | S33: 400 | T33: Yes | U33: 1 | V33: Yes | W33: 6 | X33: Yes | Y33: Yes | Z33: Yes | AA33: Yes | AB33: Yes | AC33: No | AD33: No | AE33: No | AF33: No | AG33: No | AH33: No | AI33: Yes | AJ33: No | AK33: Unspecified | AL33: Black | AM33: 2.5 L 4 Cyl | AN33: Crown Toyota Volkswagen | AO33: Holland | AP33: MI | AQ33: 74.7 | AR33: 4.7 | AS33: 24 | AU33: 638.07 | AV33: 314 | AW33: 95.2 | AX33: 52.3 | AY33: 32.1 | AZ33: 40 | BA33: 100 | BB33: 0.4 | BC33: JTMRWRFV5SD591595 | BD33: 2025 Toyota RAV4 | BE33: https://www.carfax.com/vehicle/JTMRWRFV5SD591595
A34: =RANK(B34,$B$5:$B$266) -> 30 | B34: =ROUND((AW34*'Scoring Weights'!$B$5+AX34*'Scoring Weights'!$B$6+AY34*'Scoring Weights'!$B$7+BA34*'Scoring Weights'!$B$8+AZ34*'Scoring Weights'!$B$9+BB34*'Scoring Weights'!$B$10)/MAX('Scoring Weights'!$B$11,1),1) -> 62.2 | C34: =IF(AND(H34<='Search Criteria'!$B$5,D34>='Search Criteria'!$B$6,AQ34<='Search Criteria'!$B$7,I34<=INDEX('Search Criteria'!$B$18:$B$20,MATCH(E34,'Search Criteria'!$A$18:$A$20,0)),OR(NOT('Search Criteria'!$B$8),L34<>"FWD"),OR(NOT('Search Criteria'!$B$9),T34="Yes"),OR(NOT('Search Criteria'!$B$10),W34>0),OR(NOT('Search Criteria'!$B$11),X34="Yes"),OR(NOT('Search Criteria'!$B$12),O34="GREAT",O34="GOOD"),OR(NOT('Search Criteria'!$B$13),K34="Yes")),"YES","no") -> no | D34: 2024 | E34: Honda | F34: CR-V | G34: LX | H34: 29812 | I34: 18047 | J34: =IFERROR(ROUND(I34/MAX(2026-D34,0.5),0),"") -> 9024 | K34: No | L34: AWD | M34: Gasoline | N34: 29 | O34: GOOD | P34: 33660 | Q34: 0.114 | R34: GREAT | S34: 150 | T34: Yes | U34: 1 | V34: Yes | W34: 9 | X34: No | Y34: Yes | Z34: No | AA34: No | AB34: No | AC34: No | AD34: No | AE34: No | AF34: No | AG34: No | AH34: No | AI34: No | AJ34: No | AK34: Gray | AL34: Black | AM34: 1.5 L 4 Cyl | AN34: Gurley Leep Honda | AO34: Elkhart | AP34: IN | AQ34: 0.4 | AR34: 4.6 | AS34: 13 | AT34: -598 | AU34: 532.55 | AV34: 261 | AW34: 98.8 | AX34: 82.5 | AY34: 74.4 | AZ34: 0 | BA34: 0 | BB34: 99.4 | BC34: 5J6RS4H20RL003226 | BD34: 2024 Honda CR-V | BE34: https://www.carfax.com/vehicle/5J6RS4H20RL003226
A35: =RANK(B35,$B$5:$B$266) -> 31 | B35: =ROUND((AW35*'Scoring Weights'!$B$5+AX35*'Scoring Weights'!$B$6+AY35*'Scoring Weights'!$B$7+BA35*'Scoring Weights'!$B$8+AZ35*'Scoring Weights'!$B$9+BB35*'Scoring Weights'!$B$10)/MAX('Scoring Weights'!$B$11,1),1) -> 62.1 | C35: =IF(AND(H35<='Search Criteria'!$B$5,D35>='Search Criteria'!$B$6,AQ35<='Search Criteria'!$B$7,I35<=INDEX('Search Criteria'!$B$18:$B$20,MATCH(E35,'Search Criteria'!$A$18:$A$20,0)),OR(NOT('Search Criteria'!$B$8),L35<>"FWD"),OR(NOT('Search Criteria'!$B$9),T35="Yes"),OR(NOT('Search Criteria'!$B$10),W35>0),OR(NOT('Search Criteria'!$B$11),X35="Yes"),OR(NOT('Search Criteria'!$B$12),O35="GREAT",O35="GOOD"),OR(NOT('Search Criteria'!$B$13),K35="Yes")),"YES","no") -> YES | D35: 2025 | E35: Subaru | F35: Outback | G35: Onyx Edition | H35: 31233 | I35: 16159 | J35: =IFERROR(ROUND(I35/MAX(2026-D35,0.5),0),"") -> 16159 | K35: No | L35: AWD | M35: Gasoline | N35: 28 | O35: GREAT | P35: 32692 | Q35: 0.045 | R35: GOOD | S35: 280 | T35: Yes | U35: 1 | V35: Yes | W35: 6 | X35: Yes | Y35: Yes | Z35: Yes | AA35: Yes | AB35: Yes | AC35: Yes | AD35: Yes | AE35: No | AF35: No | AG35: No | AH35: Yes | AI35: Yes | AJ35: Yes | AK35: Black | AL35: Gray | AM35: 2.5 L 4 Cyl | AN35: Toyota of Warsaw | AO35: Warsaw | AP35: IN | AQ35: 31.9 | AR35: 4.6 | AS35: 37 | AT35: 2765 | AU35: 557.93 | AV35: 235 | AW35: 80.9 | AX35: 84.2 | AY35: 52 | AZ35: 74 | BA35: 0 | BB35: 57.4 | BC35: 4S4BTALC4S3182780 | BD35: 2025 Subaru Outback | BE35: https://www.carfax.com/vehicle/4S4BTALC4S3182780
A36: =RANK(B36,$B$5:$B$266) -> 31 | B36: =ROUND((AW36*'Scoring Weights'!$B$5+AX36*'Scoring Weights'!$B$6+AY36*'Scoring Weights'!$B$7+BA36*'Scoring Weights'!$B$8+AZ36*'Scoring Weights'!$B$9+BB36*'Scoring Weights'!$B$10)/MAX('Scoring Weights'!$B$11,1),1) -> 62.1 | C36: =IF(AND(H36<='Search Criteria'!$B$5,D36>='Search Criteria'!$B$6,AQ36<='Search Criteria'!$B$7,I36<=INDEX('Search Criteria'!$B$18:$B$20,MATCH(E36,'Search Criteria'!$A$18:$A$20,0)),OR(NOT('Search Criteria'!$B$8),L36<>"FWD"),OR(NOT('Search Criteria'!$B$9),T36="Yes"),OR(NOT('Search Criteria'!$B$10),W36>0),OR(NOT('Search Criteria'!$B$11),X36="Yes"),OR(NOT('Search Criteria'!$B$12),O36="GREAT",O36="GOOD"),OR(NOT('Search Criteria'!$B$13),K36="Yes")),"YES","no") -> no | D36: 2024 | E36: Honda | F36: CR-V | G36: EXL | H36: 34861 | I36: 11224 | J36: =IFERROR(ROUND(I36/MAX(2026-D36,0.5),0),"") -> 5612 | K36: No | L36: AWD | M36: Gasoline | N36: 29 | O36: FAIR | P36: 34131 | Q36: -0.021 | R36: GREAT | S36: 150 | T36: Yes | U36: 1 | V36: Yes | W36: 3 | X36: Yes | Y36: Yes | Z36: No | AA36: Yes | AB36: Yes | AC36: Yes | AD36: Yes | AE36: No | AF36: No | AG36: Yes | AH36: Yes | AI36: Yes | AJ36: No | AK36: Black | AL36: Black | AM36: 1.5 L 4 Cyl | AN36: Victory Honda Michigan City | AO36: MICHIGAN CITY | AP36: IN | AQ36: 46.9 | AR36: 4.7 | AS36: 2 | AU36: 622.74 | AV36: 261 | AW36: 91.6 | AX36: 49.5 | AY36: 88.8 | AZ36: 68 | BA36: 0 | BB36: 37.5 | BC36: 5J6RS4H77RL015465 | BD36: 2024 Honda CR-V | BE36: https://www.carfax.com/vehicle/5J6RS4H77RL015465
A37: =RANK(B37,$B$5:$B$266) -> 33 | B37: =ROUND((AW37*'Scoring Weights'!$B$5+AX37*'Scoring Weights'!$B$6+AY37*'Scoring Weights'!$B$7+BA37*'Scoring Weights'!$B$8+AZ37*'Scoring Weights'!$B$9+BB37*'Scoring Weights'!$B$10)/MAX('Scoring Weights'!$B$11,1),1) -> 61.7 | C37: =IF(AND(H37<='Search Criteria'!$B$5,D37>='Search Criteria'!$B$6,AQ37<='Search Criteria'!$B$7,I37<=INDEX('Search Criteria'!$B$18:$B$20,MATCH(E37,'Search Criteria'!$A$18:$A$20,0)),OR(NOT('Search Criteria'!$B$8),L37<>"FWD"),OR(NOT('Search Criteria'!$B$9),T37="Yes"),OR(NOT('Search Criteria'!$B$10),W37>0),OR(NOT('Search Criteria'!$B$11),X37="Yes"),OR(NOT('Search Criteria'!$B$12),O37="GREAT",O37="GOOD"),OR(NOT('Search Criteria'!$B$13),K37="Yes")),"YES","no") -> no | D37: 2025 | E37: Subaru | F37: Outback | G37: Onyx Edition XT | H37: 35268 | I37: 26625 | J37: =IFERROR(ROUND(I37/MAX(2026-D37,0.5),0),"") -> 26625 | K37: Yes | L37: AWD | M37: Gasoline | N37: 25 | O37: None | P37: 31580 | Q37: -0.117 | R37: GOOD | S37: 260 | T37: Yes | U37: 1 | V37: No | W37: 10 | X37: Yes | Y37: Yes | Z37: Yes | AA37: Yes | AB37: Yes | AC37: Yes | AD37: Yes | AE37: No | AF37: No | AG37: No | AH37: Yes | AI37: Yes | AJ37: Yes | AK37: Silver | AL37: Gray | AM37: 2.4 L 4 Cyl | AN37: Zeigler Subaru of Fort Wayne | AO37: Fort Wayne | AP37: IN | AQ37: 59.8 | AR37: 4.8 | AS37: 12 | AU37: 630.01 | AV37: 268 | AW37: 80.1 | AX37: 39.1 | AY37: 32.7 | AZ37: 74 | BA37: 100 | BB37: 20.3 | BC37: 4S4BTGLD8S3187895 | BD37: 2025 Subaru Outback | BE37: https://www.carfax.com/vehicle/4S4BTGLD8S3187895
A38: =RANK(B38,$B$5:$B$266) -> 34 | B38: =ROUND((AW38*'Scoring Weights'!$B$5+AX38*'Scoring Weights'!$B$6+AY38*'Scoring Weights'!$B$7+BA38*'Scoring Weights'!$B$8+AZ38*'Scoring Weights'!$B$9+BB38*'Scoring Weights'!$B$10)/MAX('Scoring Weights'!$B$11,1),1) -> 61.4 | C38: =IF(AND(H38<='Search Criteria'!$B$5,D38>='Search Criteria'!$B$6,AQ38<='Search Criteria'!$B$7,I38<=INDEX('Search Criteria'!$B$18:$B$20,MATCH(E38,'Search Criteria'!$A$18:$A$20,0)),OR(NOT('Search Criteria'!$B$8),L38<>"FWD"),OR(NOT('Search Criteria'!$B$9),T38="Yes"),OR(NOT('Search Criteria'!$B$10),W38>0),OR(NOT('Search Criteria'!$B$11),X38="Yes"),OR(NOT('Search Criteria'!$B$12),O38="GREAT",O38="GOOD"),OR(NOT('Search Criteria'!$B$13),K38="Yes")),"YES","no") -> no | D38: 2025 | E38: Toyota | F38: RAV4 | G38: XLE | H38: 35270 | I38: 36603 | J38: =IFERROR(ROUND(I38/MAX(2026-D38,0.5),0),"") -> 36603 | K38: Yes | L38: AWD | M38: Gasoline | N38: 28 | O38: None | P38: 34249 | Q38: -0.03 | R38: GREAT | S38: 230 | T38: Yes | U38: 1 | V38: No | W38: 2 | X38: No | Y38: Yes | Z38: No | AA38: No | AB38: Yes | AC38: No | AD38: No | AE38: No | AF38: No | AG38: No | AH38: No | AI38: Yes | AJ38: No | AK38: Silver | AL38: Black | AM38: 2.5 L 4 Cyl | AN38: Signature Toyota Hyundai | AO38: Benton Harbor | AP38: MI | AQ38: 34.7 | AR38: 4.6 | AS38: 16 | AU38: 630.05 | AV38: 280 | AW38: 84.8 | AX38: 52.1 | AY38: 44.4 | AZ38: 16 | BA38: 100 | BB38: 53.7 | BC38: 2T3P1RFV5SW532586 | BD38: 2025 Toyota RAV4 | BE38: https://www.carfax.com/vehicle/2T3P1RFV5SW532586
A39: =RANK(B39,$B$5:$B$266) -> 35 | B39: =ROUND((AW39*'Scoring Weights'!$B$5+AX39*'Scoring Weights'!$B$6+AY39*'Scoring Weights'!$B$7+BA39*'Scoring Weights'!$B$8+AZ39*'Scoring Weights'!$B$9+BB39*'Scoring Weights'!$B$10)/MAX('Scoring Weights'!$B$11,1),1) -> 61.1 | C39: =IF(AND(H39<='Search Criteria'!$B$5,D39>='Search Criteria'!$B$6,AQ39<='Search Criteria'!$B$7,I39<=INDEX('Search Criteria'!$B$18:$B$20,MATCH(E39,'Search Criteria'!$A$18:$A$20,0)),OR(NOT('Search Criteria'!$B$8),L39<>"FWD"),OR(NOT('Search Criteria'!$B$9),T39="Yes"),OR(NOT('Search Criteria'!$B$10),W39>0),OR(NOT('Search Criteria'!$B$11),X39="Yes"),OR(NOT('Search Criteria'!$B$12),O39="GREAT",O39="GOOD"),OR(NOT('Search Criteria'!$B$13),K39="Yes")),"YES","no") -> no | D39: 2025 | E39: Honda | F39: HR-V | G39: Sport | H39: 26563 | I39: 22698 | J39: =IFERROR(ROUND(I39/MAX(2026-D39,0.5),0),"") -> 22698 | K39: Yes | L39: AWD | M39: Gasoline | N39: 27 | O39: GREAT | P39: 27028 | Q39: 0.017 | R39: GREAT | S39: 510 | T39: No | U39: 2 | V39: No | W39: 6 | X39: Yes | Y39: Yes | Z39: No | AA39: No | AB39: Yes | AC39: No | AD39: Yes | AE39: No | AF39: No | AG39: No | AH39: No | AI39: No | AJ39: No | AK39: White | AL39: Black | AM39: 2.0 L 4 Cyl | AN39: Crown Motors Cadillac Buick Honda Mazda | AO39: Holland | AP39: MI | AQ39: 71 | AR39: 4.7 | AS39: 78 | AU39: 474.51 | AV39: 314 | AW39: 63 | AX39: 80.1 | AY39: 47.3 | AZ39: 24 | BA39: 100 | BB39: 5.4 | BC39: 3CZRZ2H54SM764677 | BD39: 2025 Honda HR-V | BE39: https://www.carfax.com/vehicle/3CZRZ2H54SM764677
A40: =RANK(B40,$B$5:$B$266) -> 35 | B40: =ROUND((AW40*'Scoring Weights'!$B$5+AX40*'Scoring Weights'!$B$6+AY40*'Scoring Weights'!$B$7+BA40*'Scoring Weights'!$B$8+AZ40*'Scoring Weights'!$B$9+BB40*'Scoring Weights'!$B$10)/MAX('Scoring Weights'!$B$11,1),1) -> 61.1 | C40: =IF(AND(H40<='Search Criteria'!$B$5,D40>='Search Criteria'!$B$6,AQ40<='Search Criteria'!$B$7,I40<=INDEX('Search Criteria'!$B$18:$B$20,MATCH(E40,'Search Criteria'!$A$18:$A$20,0)),OR(NOT('Search Criteria'!$B$8),L40<>"FWD"),OR(NOT('Search Criteria'!$B$9),T40="Yes"),OR(NOT('Search Criteria'!$B$10),W40>0),OR(NOT('Search Criteria'!$B$11),X40="Yes"),OR(NOT('Search Criteria'!$B$12),O40="GREAT",O40="GOOD"),OR(NOT('Search Criteria'!$B$13),K40="Yes")),"YES","no") -> no | D40: 2025 | E40: Toyota | F40: RAV4 | G40: XLE | H40: 32997 | I40: 39877 | J40: =IFERROR(ROUND(I40/MAX(2026-D40,0.5),0),"") -> 39877 | K40: Yes | L40: AWD | M40: Gasoline | N40: 28 | O40: GOOD | P40: 33988 | Q40: 0.029 | R40: GREAT | S40: 260 | T40: Yes | U40: 2 | V40: No | W40: 2 | X40: No | Y40: Yes | Z40: No | AA40: No | AB40: Yes | AC40: No | AD40: No | AE40: No | AF40: No | AG40: No | AH40: No | AI40: Yes | AJ40: No | AK40: Silver | AL40: Black | AM40: 2.5 L 4 Cyl | AN40: Sunshine Toyota | AO40: Springfield | AP40: MI | AQ40: 56.8 | AR40: 4.6 | AS40: 50 | AU40: 589.44 | AV40: 345 | AW40: 76 | AX40: 69.8 | AY40: 42.1 | AZ40: 16 | BA40: 100 | BB40: 24.2 | BC40: 2T3P1RFV5SW513973 | BD40: 2025 Toyota RAV4 | BE40: https://www.carfax.com/vehicle/2T3P1RFV5SW513973
A41: =RANK(B41,$B$5:$B$266) -> 35 | B41: =ROUND((AW41*'Scoring Weights'!$B$5+AX41*'Scoring Weights'!$B$6+AY41*'Scoring Weights'!$B$7+BA41*'Scoring Weights'!$B$8+AZ41*'Scoring Weights'!$B$9+BB41*'Scoring Weights'!$B$10)/MAX('Scoring Weights'!$B$11,1),1) -> 61.1 | C41: =IF(AND(H41<='Search Criteria'!$B$5,D41>='Search Criteria'!$B$6,AQ41<='Search Criteria'!$B$7,I41<=INDEX('Search Criteria'!$B$18:$B$20,MATCH(E41,'Search Criteria'!$A$18:$A$20,0)),OR(NOT('Search Criteria'!$B$8),L41<>"FWD"),OR(NOT('Search Criteria'!$B$9),T41="Yes"),OR(NOT('Search Criteria'!$B$10),W41>0),OR(NOT('Search Criteria'!$B$11),X41="Yes"),OR(NOT('Search Criteria'!$B$12),O41="GREAT",O41="GOOD"),OR(NOT('Search Criteria'!$B$13),K41="Yes")),"YES","no") -> YES | D41: 2025 | E41: Honda | F41: CR-V | G41: Sport-L | H41: 35094 | I41: 29734 | J41: =IFERROR(ROUND(I41/MAX(2026-D41,0.5),0),"") -> 29734 | K41: No | L41: AWD | M41: Hybrid | N41: 37 | O41: GREAT | P41: 33990 | Q41: -0.032 | R41: n/a | T41: Yes | U41: 2 | V41: No | W41: 9 | X41: Yes | Y41: Yes | Z41: No | AA41: Yes | AB41: Yes | AC41: Yes | AD41: Yes | AE41: Yes | AF41: No | AG41: Yes | AH41: Yes | AI41: Yes | AJ41: No | AK41: Gray | AL41: Unspecified | AM41: 2.0 L 4 Cyl | AN41: Gurley Leep Honda | AO41: Elkhart | AP41: IN | AQ41: 0.4 | AR41: 4.6 | AS41: 13 | AT41: 5666 | AU41: 626.9 | AV41: 261 | AW41: 84.4 | AX41: 72.6 | AY41: 40.3 | AZ41: 78 | BA41: 0 | BB41: 99.4 | BC41: 7FARS6H88SE008967 | BD41: 2025 Honda CR-V | BE41: https://www.carfax.com/vehicle/7FARS6H88SE008967
A42: =RANK(B42,$B$5:$B$266) -> 38 | B42: =ROUND((AW42*'Scoring Weights'!$B$5+AX42*'Scoring Weights'!$B$6+AY42*'Scoring Weights'!$B$7+BA42*'Scoring Weights'!$B$8+AZ42*'Scoring Weights'!$B$9+BB42*'Scoring Weights'!$B$10)/MAX('Scoring Weights'!$B$11,1),1) -> 60.2 | C42: =IF(AND(H42<='Search Criteria'!$B$5,D42>='Search Criteria'!$B$6,AQ42<='Search Criteria'!$B$7,I42<=INDEX('Search Criteria'!$B$18:$B$20,MATCH(E42,'Search Criteria'!$A$18:$A$20,0)),OR(NOT('Search Criteria'!$B$8),L42<>"FWD"),OR(NOT('Search Criteria'!$B$9),T42="Yes"),OR(NOT('Search Criteria'!$B$10),W42>0),OR(NOT('Search Criteria'!$B$11),X42="Yes"),OR(NOT('Search Criteria'!$B$12),O42="GREAT",O42="GOOD"),OR(NOT('Search Criteria'!$B$13),K42="Yes")),"YES","no") -> no | D42: 2025 | E42: Toyota | F42: RAV4 | G42: XLE | H42: 35250 | I42: 33433 | J42: =IFERROR(ROUND(I42/MAX(2026-D42,0.5),0),"") -> 33433 | K42: Yes | L42: AWD | M42: Gasoline | N42: 28 | O42: FAIR | P42: 34503 | Q42: -0.022 | R42: GREAT | S42: 260 | T42: Yes | U42: 1 | V42: No | W42: 4 | X42: No | Y42: Yes | Z42: No | AA42: No | AB42: Yes | AC42: No | AD42: No | AE42: No | AF42: No | AG42: No | AH42: No | AI42: Yes | AJ42: No | AK42: Silver | AL42: Black | AM42: 2.5 L 4 Cyl | AN42: Evans Toyota | AO42: Fort Wayne | AP42: IN | AQ42: 59.9 | AR42: 4.5 | AS42: 96 | AU42: 629.69 | AV42: 262 | AW42: 87.2 | AX42: 49.5 | AY42: 46.6 | AZ42: 16 | BA42: 100 | BB42: 20.2 | BC42: 2T3P1RFV5SW533172 | BD42: 2025 Toyota RAV4 | BE42: https://www.carfax.com/vehicle/2T3P1RFV5SW533172
A43: =RANK(B43,$B$5:$B$266) -> 39 | B43: =ROUND((AW43*'Scoring Weights'!$B$5+AX43*'Scoring Weights'!$B$6+AY43*'Scoring Weights'!$B$7+BA43*'Scoring Weights'!$B$8+AZ43*'Scoring Weights'!$B$9+BB43*'Scoring Weights'!$B$10)/MAX('Scoring Weights'!$B$11,1),1) -> 59.5 | C43: =IF(AND(H43<='Search Criteria'!$B$5,D43>='Search Criteria'!$B$6,AQ43<='Search Criteria'!$B$7,I43<=INDEX('Search Criteria'!$B$18:$B$20,MATCH(E43,'Search Criteria'!$A$18:$A$20,0)),OR(NOT('Search Criteria'!$B$8),L43<>"FWD"),OR(NOT('Search Criteria'!$B$9),T43="Yes"),OR(NOT('Search Criteria'!$B$10),W43>0),OR(NOT('Search Criteria'!$B$11),X43="Yes"),OR(NOT('Search Criteria'!$B$12),O43="GREAT",O43="GOOD"),OR(NOT('Search Criteria'!$B$13),K43="Yes")),"YES","no") -> no | D43: 2022 | E43: Toyota | F43: RAV4 | G43: XLE | H43: 29661 | I43: 28369 | J43: =IFERROR(ROUND(I43/MAX(2026-D43,0.5),0),"") -> 7092 | K43: No | L43: AWD | M43: Gasoline | N43: 28 | O43: GREAT | P43: 31324 | Q43: 0.053 | R43: GREAT | S43: 230 | T43: No | U43: 2 | V43: No | W43: 11 | X43: Yes | Y43: Yes | Z43: Yes | AA43: Yes | AB43: Yes | AC43: Yes | AD43: No | AE43: No | AF43: No | AG43: No | AH43: No | AI43: Yes | AJ43: No | AK43: Silver | AL43: Black | AM43: 2.5 L 4 Cyl | AN43: Team Chevrolet | AO43: Valparaiso | AP43: IN | AQ43: 63.7 | AR43: 4.5 | AS43: 53 | AU43: 529.85 | AV43: 261 | AW43: 72 | AX43: 85.5 | AY43: 77.4 | AZ43: 52 | BA43: 0 | BB43: 15.1 | BC43: 2T3P1RFV2NW279456 | BD43: 2022 Toyota RAV4 | BE43: https://www.carfax.com/vehicle/2T3P1RFV2NW279456
A44: =RANK(B44,$B$5:$B$266) -> 40 | B44: =ROUND((AW44*'Scoring Weights'!$B$5+AX44*'Scoring Weights'!$B$6+AY44*'Scoring Weights'!$B$7+BA44*'Scoring Weights'!$B$8+AZ44*'Scoring Weights'!$B$9+BB44*'Scoring Weights'!$B$10)/MAX('Scoring Weights'!$B$11,1),1) -> 59.4 | C44: =IF(AND(H44<='Search Criteria'!$B$5,D44>='Search Criteria'!$B$6,AQ44<='Search Criteria'!$B$7,I44<=INDEX('Search Criteria'!$B$18:$B$20,MATCH(E44,'Search Criteria'!$A$18:$A$20,0)),OR(NOT('Search Criteria'!$B$8),L44<>"FWD"),OR(NOT('Search Criteria'!$B$9),T44="Yes"),OR(NOT('Search Criteria'!$B$10),W44>0),OR(NOT('Search Criteria'!$B$11),X44="Yes"),OR(NOT('Search Criteria'!$B$12),O44="GREAT",O44="GOOD"),OR(NOT('Search Criteria'!$B$13),K44="Yes")),"YES","no") -> no | D44: 2024 | E44: Honda | F44: CR-V | G44: Sport | H44: 31961 | I44: 35174 | J44: =IFERROR(ROUND(I44/MAX(2026-D44,0.5),0),"") -> 17587 | K44: No | L44: AWD | M44: Hybrid | N44: 37 | O44: GREAT | P44: 32477 | Q44: 0.016 | R44: n/a | T44: No | U44: 1 | V44: Yes | W44: 9 | X44: Yes | Y44: Yes | Z44: No | AA44: Yes | AB44: Yes | AC44: Yes | AD44: Yes | AE44: Yes | AF44: No | AG44: No | AH44: No | AI44: Yes | AJ44: No | AK44: Gray | AL44: Black | AM44: 2.0 L 4 Cyl | AN44: Gurley Leep Nissan | AO44: Mishawaka | AP44: IN | AQ44: 10.9 | AR44: 4.4 | AS44: 32 | AT44: 1200 | AU44: 570.94 | AV44: 261 | AW44: 85.2 | AX44: 79.9 | AY44: 35.9 | AZ44: 64 | BA44: 0 | BB44: 85.5 | BC44: 7FARS6H57RE009544 | BD44: 2024 Honda CR-V | BE44: https://www.carfax.com/vehicle/7FARS6H57RE009544
A45: =RANK(B45,$B$5:$B$266) -> 40 | B45: =ROUND((AW45*'Scoring Weights'!$B$5+AX45*'Scoring Weights'!$B$6+AY45*'Scoring Weights'!$B$7+BA45*'Scoring Weights'!$B$8+AZ45*'Scoring Weights'!$B$9+BB45*'Scoring Weights'!$B$10)/MAX('Scoring Weights'!$B$11,1),1) -> 59.4 | C45: =IF(AND(H45<='Search Criteria'!$B$5,D45>='Search Criteria'!$B$6,AQ45<='Search Criteria'!$B$7,I45<=INDEX('Search Criteria'!$B$18:$B$20,MATCH(E45,'Search Criteria'!$A$18:$A$20,0)),OR(NOT('Search Criteria'!$B$8),L45<>"FWD"),OR(NOT('Search Criteria'!$B$9),T45="Yes"),OR(NOT('Search Criteria'!$B$10),W45>0),OR(NOT('Search Criteria'!$B$11),X45="Yes"),OR(NOT('Search Criteria'!$B$12),O45="GREAT",O45="GOOD"),OR(NOT('Search Criteria'!$B$13),K45="Yes")),"YES","no") -> YES | D45: 2025 | E45: Subaru | F45: Outback | G45: Onyx Edition | H45: 28149 | I45: 33731 | J45: =IFERROR(ROUND(I45/MAX(2026-D45,0.5),0),"") -> 33731 | K45: No | L45: AWD | M45: Gasoline | N45: 28 | O45: GOOD | P45: 30826 | Q45: 0.087 | R45: GREAT | S45: 340 | T45: Yes | U45: 1 | V45: No | W45: 4 | X45: Yes | Y45: Yes | Z45: Yes | AA45: Yes | AB45: Yes | AC45: Yes | AD45: Yes | AE45: No | AF45: No | AG45: No | AH45: Yes | AI45: Yes | AJ45: Yes | AK45: Silver | AL45: Gray | AM45: 2.5 L 4 Cyl | AN45: Gurley Leep Honda | AO45: Elkhart | AP45: IN | AQ45: 0.4 | AR45: 4.6 | AS45: 46 | AT45: 4107 | AU45: 502.84 | AV45: 261 | AW45: 87.2 | AX45: 78.4 | AY45: 22.8 | AZ45: 74 | BA45: 0 | BB45: 99.4 | BC45: 4S4BTALC3S3187209 | BD45: 2025 Subaru Outback | BE45: https://www.carfax.com/vehicle/4S4BTALC3S3187209
A46: =RANK(B46,$B$5:$B$266) -> 42 | B46: =ROUND((AW46*'Scoring Weights'!$B$5+AX46*'Scoring Weights'!$B$6+AY46*'Scoring Weights'!$B$7+BA46*'Scoring Weights'!$B$8+AZ46*'Scoring Weights'!$B$9+BB46*'Scoring Weights'!$B$10)/MAX('Scoring Weights'!$B$11,1),1) -> 59.2 | C46: =IF(AND(H46<='Search Criteria'!$B$5,D46>='Search Criteria'!$B$6,AQ46<='Search Criteria'!$B$7,I46<=INDEX('Search Criteria'!$B$18:$B$20,MATCH(E46,'Search Criteria'!$A$18:$A$20,0)),OR(NOT('Search Criteria'!$B$8),L46<>"FWD"),OR(NOT('Search Criteria'!$B$9),T46="Yes"),OR(NOT('Search Criteria'!$B$10),W46>0),OR(NOT('Search Criteria'!$B$11),X46="Yes"),OR(NOT('Search Criteria'!$B$12),O46="GREAT",O46="GOOD"),OR(NOT('Search Criteria'!$B$13),K46="Yes")),"YES","no") -> YES | D46: 2025 | E46: Toyota | F46: RAV4 | G46: XLE Premium | H46: 39185 | I46: 15206 | J46: =IFERROR(ROUND(I46/MAX(2026-D46,0.5),0),"") -> 15206 | K46: No | L46: AWD | M46: Gasoline | N46: 28 | O46: GOOD | P46: 35958 | Q46: -0.09 | R46: GREAT | S46: 320 | T46: Yes | U46: 1 | V46: Yes | W46: 5 | X46: Yes | Y46: Yes | Z46: Yes | AA46: Yes | AB46: Yes | AC46: Yes | AD46: Yes | AE46: Yes | AF46: No | AG46: No | AH46: No | AI46: Yes | AJ46: No | AK46: Unspecified | AL46: Gray | AM46: 2.5 L 4 Cyl | AN46: Bob Thomas Ford West | AO46: Fort Wayne | AP46: IN | AQ46: 59.9 | AR46: 4.7 | AS46: 47 | AU46: 699.98 | AV46: 549 | AW46: 94 | AX46: 51.9 | AY46: 66.3 | AZ46: 74 | BA46: 0 | BB46: 20.2 | BC46: 2T3A1RFV1SW502278 | BD46: 2025 Toyota RAV4 | BE46: https://www.carfax.com/vehicle/2T3A1RFV1SW502278
A47: =RANK(B47,$B$5:$B$266) -> 43 | B47: =ROUND((AW47*'Scoring Weights'!$B$5+AX47*'Scoring Weights'!$B$6+AY47*'Scoring Weights'!$B$7+BA47*'Scoring Weights'!$B$8+AZ47*'Scoring Weights'!$B$9+BB47*'Scoring Weights'!$B$10)/MAX('Scoring Weights'!$B$11,1),1) -> 59.1 | C47: =IF(AND(H47<='Search Criteria'!$B$5,D47>='Search Criteria'!$B$6,AQ47<='Search Criteria'!$B$7,I47<=INDEX('Search Criteria'!$B$18:$B$20,MATCH(E47,'Search Criteria'!$A$18:$A$20,0)),OR(NOT('Search Criteria'!$B$8),L47<>"FWD"),OR(NOT('Search Criteria'!$B$9),T47="Yes"),OR(NOT('Search Criteria'!$B$10),W47>0),OR(NOT('Search Criteria'!$B$11),X47="Yes"),OR(NOT('Search Criteria'!$B$12),O47="GREAT",O47="GOOD"),OR(NOT('Search Criteria'!$B$13),K47="Yes")),"YES","no") -> no | D47: 2026 | E47: Subaru | F47: Outback | G47: Premium | H47: 35268 | I47: 2629 | J47: =IFERROR(ROUND(I47/MAX(2026-D47,0.5),0),"") -> 5258 | K47: No | L47: AWD | M47: Gasoline | N47: 27 | O47: None | P47: 35793 | Q47: 0.015 | R47: n/a | T47: Yes | V47: No | W47: 1 | X47: Yes | Y47: Yes | Z47: Yes | AA47: Yes | AB47: Yes | AC47: Yes | AD47: Yes | AE47: No | AF47: Yes | AG47: Yes | AH47: Yes | AI47: Yes | AJ47: No | AK47: Gray | AL47: Black | AM47: 2.5 L 4 Cyl | AN47: Zeigler Subaru of Fort Wayne | AO47: Fort Wayne | AP47: IN | AQ47: 59.8 | AR47: 4.8 | AS47: 3 | AU47: 630.01 | AV47: 268 | AW47: 60.5 | AX47: 58.8 | AY47: 96.3 | AZ47: 86 | BA47: 0 | BB47: 20.3 | BC47: JF2BUPBD6TY477397 | BD47: 2026 Subaru Outback | BE47: https://www.carfax.com/vehicle/JF2BUPBD6TY477397
A48: =RANK(B48,$B$5:$B$266) -> 44 | B48: =ROUND((AW48*'Scoring Weights'!$B$5+AX48*'Scoring Weights'!$B$6+AY48*'Scoring Weights'!$B$7+BA48*'Scoring Weights'!$B$8+AZ48*'Scoring Weights'!$B$9+BB48*'Scoring Weights'!$B$10)/MAX('Scoring Weights'!$B$11,1),1) -> 59 | C48: =IF(AND(H48<='Search Criteria'!$B$5,D48>='Search Criteria'!$B$6,AQ48<='Search Criteria'!$B$7,I48<=INDEX('Search Criteria'!$B$18:$B$20,MATCH(E48,'Search Criteria'!$A$18:$A$20,0)),OR(NOT('Search Criteria'!$B$8),L48<>"FWD"),OR(NOT('Search Criteria'!$B$9),T48="Yes"),OR(NOT('Search Criteria'!$B$10),W48>0),OR(NOT('Search Criteria'!$B$11),X48="Yes"),OR(NOT('Search Criteria'!$B$12),O48="GREAT",O48="GOOD"),OR(NOT('Search Criteria'!$B$13),K48="Yes")),"YES","no") -> YES | D48: 2024 | E48: Honda | F48: CR-V | G48: Sport | H48: 33249 | I48: 31775 | J48: =IFERROR(ROUND(I48/MAX(2026-D48,0.5),0),"") -> 15888 | K48: No | L48: AWD | M48: Hybrid | N48: 37 | O48: GREAT | P48: 32711 | Q48: -0.016 | R48: n/a | T48: Yes | U48: 2 | V48: Yes | W48: 8 | X48: Yes | Y48: Yes | Z48: No | AA48: Yes | AB48: Yes | AC48: No | AD48: Yes | AE48: Yes | AF48: No | AG48: No | AH48: No | AI48: Yes | AJ48: No | AK48: White | AL48: Black | AM48: 2.0 L 4 Cyl | AN48: Jordan Ford | AO48: Mishawaka | AP48: IN | AQ48: 10.7 | AR48: 4.6 | AS48: 13 | AT48: -1250 | AU48: 593.95 | AV48: 250 | AW48: 88.8 | AX48: 75 | AY48: 43.5 | AZ48: 52 | BA48: 0 | BB48: 85.7 | BC48: 7FARS6H56RE044785 | BD48: 2024 Honda CR-V | BE48: https://www.carfax.com/vehicle/7FARS6H56RE044785
A49: =RANK(B49,$B$5:$B$266) -> 45 | B49: =ROUND((AW49*'Scoring Weights'!$B$5+AX49*'Scoring Weights'!$B$6+AY49*'Scoring Weights'!$B$7+BA49*'Scoring Weights'!$B$8+AZ49*'Scoring Weights'!$B$9+BB49*'Scoring Weights'!$B$10)/MAX('Scoring Weights'!$B$11,1),1) -> 58.9 | C49: =IF(AND(H49<='Search Criteria'!$B$5,D49>='Search Criteria'!$B$6,AQ49<='Search Criteria'!$B$7,I49<=INDEX('Search Criteria'!$B$18:$B$20,MATCH(E49,'Search Criteria'!$A$18:$A$20,0)),OR(NOT('Search Criteria'!$B$8),L49<>"FWD"),OR(NOT('Search Criteria'!$B$9),T49="Yes"),OR(NOT('Search Criteria'!$B$10),W49>0),OR(NOT('Search Criteria'!$B$11),X49="Yes"),OR(NOT('Search Criteria'!$B$12),O49="GREAT",O49="GOOD"),OR(NOT('Search Criteria'!$B$13),K49="Yes")),"YES","no") -> no | D49: 2025 | E49: Toyota | F49: RAV4 | G49: LE | H49: 32175 | I49: 44009 | J49: =IFERROR(ROUND(I49/MAX(2026-D49,0.5),0),"") -> 44009 | K49: Yes | L49: AWD | M49: Hybrid | N49: 39 | O49: GREAT | P49: 33658 | Q49: 0.044 | R49: GOOD | S49: 510 | T49: Yes | U49: 1 | V49: No | W49: 2 | X49: No | Y49: Yes | Z49: No | AA49: No | AB49: No | AC49: No | AD49: No | AE49: No | AF49: No | AG49: No | AH49: No | AI49: No | AJ49: No | AK49: White | AL49: Black | AM49: 2.5 L 4 Cyl | AN49: Sunshine Toyota | AO49: Springfield | AP49: MI | AQ49: 56.8 | AR49: 4.6 | AS49: 100 | AT49: 2278 | AU49: 574.76 | AV49: 345 | AW49: 65.7 | AX49: 84.1 | AY49: 39.2 | AZ49: 0 | BA49: 100 | BB49: 24.2 | BC49: 2T3LWRFV9SW261077 | BD49: 2025 Toyota RAV4 | BE49: https://www.carfax.com/vehicle/2T3LWRFV9SW261077
A50: =RANK(B50,$B$5:$B$266) -> 46 | B50: =ROUND((AW50*'Scoring Weights'!$B$5+AX50*'Scoring Weights'!$B$6+AY50*'Scoring Weights'!$B$7+BA50*'Scoring Weights'!$B$8+AZ50*'Scoring Weights'!$B$9+BB50*'Scoring Weights'!$B$10)/MAX('Scoring Weights'!$B$11,1),1) -> 58.6 | C50: =IF(AND(H50<='Search Criteria'!$B$5,D50>='Search Criteria'!$B$6,AQ50<='Search Criteria'!$B$7,I50<=INDEX('Search Criteria'!$B$18:$B$20,MATCH(E50,'Search Criteria'!$A$18:$A$20,0)),OR(NOT('Search Criteria'!$B$8),L50<>"FWD"),OR(NOT('Search Criteria'!$B$9),T50="Yes"),OR(NOT('Search Criteria'!$B$10),W50>0),OR(NOT('Search Criteria'!$B$11),X50="Yes"),OR(NOT('Search Criteria'!$B$12),O50="GREAT",O50="GOOD"),OR(NOT('Search Criteria'!$B$13),K50="Yes")),"YES","no") -> YES | D50: 2025 | E50: Honda | F50: CR-V | G50: Sport-L | H50: 36597 | I50: 16535 | J50: =IFERROR(ROUND(I50/MAX(2026-D50,0.5),0),"") -> 16535 | K50: No | L50: AWD | M50: Hybrid | N50: 37 | O50: GOOD | P50: 34902 | Q50: -0.049 | R50: GREAT | S50: 610 | T50: Yes | U50: 2 | V50: No | W50: 5 | X50: Yes | Y50: Yes | Z50: No | AA50: Yes | AB50: Yes | AC50: Yes | AD50: Yes | AE50: Yes | AF50: No | AG50: Yes | AH50: Yes | AI50: Yes | AJ50: No | AK50: White | AL50: Black | AM50: 2.0 L 4 Cyl | AN50: Gurley Leep Honda | AO50: Elkhart | AP50: IN | AQ50: 0.4 | AR50: 4.6 | AS50: 19 | AT50: -63 | AU50: 653.75 | AV50: 261 | AW50: 75.4 | AX50: 58.1 | AY50: 57.1 | AZ50: 78 | BA50: 0 | BB50: 99.4 | BC50: 7FARS6H89SE024319 | BD50: 2025 Honda CR-V | BE50: https://www.carfax.com/vehicle/7FARS6H89SE024319
A51: =RANK(B51,$B$5:$B$266) -> 47 | B51: =ROUND((AW51*'Scoring Weights'!$B$5+AX51*'Scoring Weights'!$B$6+AY51*'Scoring Weights'!$B$7+BA51*'Scoring Weights'!$B$8+AZ51*'Scoring Weights'!$B$9+BB51*'Scoring Weights'!$B$10)/MAX('Scoring Weights'!$B$11,1),1) -> 58.3 | C51: =IF(AND(H51<='Search Criteria'!$B$5,D51>='Search Criteria'!$B$6,AQ51<='Search Criteria'!$B$7,I51<=INDEX('Search Criteria'!$B$18:$B$20,MATCH(E51,'Search Criteria'!$A$18:$A$20,0)),OR(NOT('Search Criteria'!$B$8),L51<>"FWD"),OR(NOT('Search Criteria'!$B$9),T51="Yes"),OR(NOT('Search Criteria'!$B$10),W51>0),OR(NOT('Search Criteria'!$B$11),X51="Yes"),OR(NOT('Search Criteria'!$B$12),O51="GREAT",O51="GOOD"),OR(NOT('Search Criteria'!$B$13),K51="Yes")),"YES","no") -> no | D51: 2025 | E51: Toyota | F51: RAV4 | G51: XLE | H51: 36958 | I51: 13677 | J51: =IFERROR(ROUND(I51/MAX(2026-D51,0.5),0),"") -> 13677 | K51: No | L51: AWD | M51: Hybrid | N51: 39 | O51: GREAT | P51: 36080 | Q51: -0.024 | R51: GREAT | S51: 440 | T51: Yes | U51: 1 | V51: No | W51: 3 | X51: No | Y51: Yes | Z51: No | AA51: Yes | AB51: Yes | AC51: Yes | AD51: No | AE51: No | AF51: No | AG51: No | AH51: No | AI51: Yes | AJ51: No | AK51: Gray | AL51: Black | AM51: 2.5 L 4 Cyl | AN51: David Rice Auto Sales LLC | AO51: Schoolcraft | AP51: MI | AQ51: 33.3 | AR51: 4.1 | AS51: 51 | AU51: 660.2 | AV51: 230 | AW51: 79.3 | AX51: 73.8 | AY51: 71.2 | AZ51: 42 | BA51: 0 | BB51: 55.7 | BC51: JTMRWRFV1SJ072125 | BD51: 2025 Toyota RAV4 | BE51: https://www.carfax.com/vehicle/JTMRWRFV1SJ072125
A52: =RANK(B52,$B$5:$B$266) -> 48 | B52: =ROUND((AW52*'Scoring Weights'!$B$5+AX52*'Scoring Weights'!$B$6+AY52*'Scoring Weights'!$B$7+BA52*'Scoring Weights'!$B$8+AZ52*'Scoring Weights'!$B$9+BB52*'Scoring Weights'!$B$10)/MAX('Scoring Weights'!$B$11,1),1) -> 58 | C52: =IF(AND(H52<='Search Criteria'!$B$5,D52>='Search Criteria'!$B$6,AQ52<='Search Criteria'!$B$7,I52<=INDEX('Search Criteria'!$B$18:$B$20,MATCH(E52,'Search Criteria'!$A$18:$A$20,0)),OR(NOT('Search Criteria'!$B$8),L52<>"FWD"),OR(NOT('Search Criteria'!$B$9),T52="Yes"),OR(NOT('Search Criteria'!$B$10),W52>0),OR(NOT('Search Criteria'!$B$11),X52="Yes"),OR(NOT('Search Criteria'!$B$12),O52="GREAT",O52="GOOD"),OR(NOT('Search Criteria'!$B$13),K52="Yes")),"YES","no") -> no | D52: 2024 | E52: Honda | F52: CR-V | G52: Sport | H52: 30809 | I52: 29108 | J52: =IFERROR(ROUND(I52/MAX(2026-D52,0.5),0),"") -> 14554 | K52: No | L52: FWD | M52: Hybrid | N52: 40 | O52: GREAT | P52: 32896 | Q52: 0.063 | R52: n/a | T52: Yes | U52: 1 | V52: Yes | W52: 3 | X52: Yes | Y52: Yes | Z52: No | AA52: Yes | AB52: Yes | AC52: No | AD52: Yes | AE52: No | AF52: No | AG52: No | AH52: No | AI52: Yes | AJ52: No | AK52: White | AL52: Black | AM52: 2.0 L 4 Cyl | AN52: Crown Motors Cadillac Buick Honda Mazda | AO52: Holland | AP52: MI | AQ52: 71 | AR52: 4.7 | AS52: 86 | AU52: 550.36 | AV52: 314 | AW52: 91.6 | AX52: 87 | AY52: 49.5 | AZ52: 42 | BA52: 0 | BB52: 5.4 | BC52: 7FARS5H51RE030142 | BD52: 2024 Honda CR-V | BE52: https://www.carfax.com/vehicle/7FARS5H51RE030142
A53: =RANK(B53,$B$5:$B$266) -> 49 | B53: =ROUND((AW53*'Scoring Weights'!$B$5+AX53*'Scoring Weights'!$B$6+AY53*'Scoring Weights'!$B$7+BA53*'Scoring Weights'!$B$8+AZ53*'Scoring Weights'!$B$9+BB53*'Scoring Weights'!$B$10)/MAX('Scoring Weights'!$B$11,1),1) -> 57.9 | C53: =IF(AND(H53<='Search Criteria'!$B$5,D53>='Search Criteria'!$B$6,AQ53<='Search Criteria'!$B$7,I53<=INDEX('Search Criteria'!$B$18:$B$20,MATCH(E53,'Search Criteria'!$A$18:$A$20,0)),OR(NOT('Search Criteria'!$B$8),L53<>"FWD"),OR(NOT('Search Criteria'!$B$9),T53="Yes"),OR(NOT('Search Criteria'!$B$10),W53>0),OR(NOT('Search Criteria'!$B$11),X53="Yes"),OR(NOT('Search Criteria'!$B$12),O53="GREAT",O53="GOOD"),OR(NOT('Search Criteria'!$B$13),K53="Yes")),"YES","no") -> YES | D53: 2024 | E53: Subaru | F53: Outback | G53: Limited XT | H53: 30238 | I53: 25726 | J53: =IFERROR(ROUND(I53/MAX(2026-D53,0.5),0),"") -> 12863 | K53: No | L53: AWD | M53: Gasoline | N53: 25 | O53: GOOD | P53: 30011 | Q53: -0.008 | R53: GOOD | S53: 260 | T53: Yes | U53: 1 | V53: Yes | W53: 9 | X53: Yes | Y53: Yes | Z53: Yes | AA53: Yes | AB53: Yes | AC53: Yes | AD53: Yes | AE53: No | AF53: Yes | AG53: No | AH53: Yes | AI53: Yes | AJ53: Yes | AK53: Gray | AL53: Gray | AM53: 2.4 L 4 Cyl | AN53: Victory Honda Michigan City | AO53: MICHIGAN CITY | AP53: IN | AQ53: 46.9 | AR53: 4.7 | AS53: 75 | AT53: 2739 | AU53: 540.16 | AV53: 261 | AW53: 84.5 | AX53: 64.3 | AY53: 46.8 | AZ53: 82 | BA53: 0 | BB53: 37.5 | BC53: 4S4BTGND3R3143827 | BD53: 2024 Subaru Outback | BE53: https://www.carfax.com/vehicle/4S4BTGND3R3143827
A54: =RANK(B54,$B$5:$B$266) -> 49 | B54: =ROUND((AW54*'Scoring Weights'!$B$5+AX54*'Scoring Weights'!$B$6+AY54*'Scoring Weights'!$B$7+BA54*'Scoring Weights'!$B$8+AZ54*'Scoring Weights'!$B$9+BB54*'Scoring Weights'!$B$10)/MAX('Scoring Weights'!$B$11,1),1) -> 57.9 | C54: =IF(AND(H54<='Search Criteria'!$B$5,D54>='Search Criteria'!$B$6,AQ54<='Search Criteria'!$B$7,I54<=INDEX('Search Criteria'!$B$18:$B$20,MATCH(E54,'Search Criteria'!$A$18:$A$20,0)),OR(NOT('Search Criteria'!$B$8),L54<>"FWD"),OR(NOT('Search Criteria'!$B$9),T54="Yes"),OR(NOT('Search Criteria'!$B$10),W54>0),OR(NOT('Search Criteria'!$B$11),X54="Yes"),OR(NOT('Search Criteria'!$B$12),O54="GREAT",O54="GOOD"),OR(NOT('Search Criteria'!$B$13),K54="Yes")),"YES","no") -> no | D54: 2024 | E54: Subaru | F54: Outback | G54: Limited XT | H54: 28261 | I54: 31604 | J54: =IFERROR(ROUND(I54/MAX(2026-D54,0.5),0),"") -> 15802 | K54: No | L54: AWD | M54: Gasoline | N54: 25 | O54: GREAT | P54: 29387 | Q54: 0.038 | R54: GREAT | S54: 200 | T54: No | U54: 1 | V54: Yes | W54: 6 | X54: Yes | Y54: Yes | Z54: Yes | AA54: Yes | AB54: Yes | AC54: Yes | AD54: Yes | AE54: No | AF54: Yes | AG54: Yes | AH54: Yes | AI54: Yes | AJ54: Yes | AK54: Blue | AL54: Gray | AM54: 2.4 L 4 Cyl | AN54: Art Hill Ford Lincoln | AO54: Merrillville | AP54: IN | AQ54: 72.9 | AR54: 4.2 | AS54: 77 | AU54: 504.84 | AV54: 261 | AW54: 81.6 | AX54: 83.2 | AY54: 31.2 | AZ54: 90 | BA54: 0 | BB54: 2.7 | BC54: 4S4BTGND7R3248466 | BD54: 2024 Subaru Outback | BE54: https://www.carfax.com/vehicle/4S4BTGND7R3248466
A55: =RANK(B55,$B$5:$B$266) -> 51 | B55: =ROUND((AW55*'Scoring Weights'!$B$5+AX55*'Scoring Weights'!$B$6+AY55*'Scoring Weights'!$B$7+BA55*'Scoring Weights'!$B$8+AZ55*'Scoring Weights'!$B$9+BB55*'Scoring Weights'!$B$10)/MAX('Scoring Weights'!$B$11,1),1) -> 57.7 | C55: =IF(AND(H55<='Search Criteria'!$B$5,D55>='Search Criteria'!$B$6,AQ55<='Search Criteria'!$B$7,I55<=INDEX('Search Criteria'!$B$18:$B$20,MATCH(E55,'Search Criteria'!$A$18:$A$20,0)),OR(NOT('Search Criteria'!$B$8),L55<>"FWD"),OR(NOT('Search Criteria'!$B$9),T55="Yes"),OR(NOT('Search Criteria'!$B$10),W55>0),OR(NOT('Search Criteria'!$B$11),X55="Yes"),OR(NOT('Search Criteria'!$B$12),O55="GREAT",O55="GOOD"),OR(NOT('Search Criteria'!$B$13),K55="Yes")),"YES","no") -> YES | D55: 2022 | E55: Honda | F55: CR-V | G55: EXL | H55: 27793 | I55: 49644 | J55: =IFERROR(ROUND(I55/MAX(2026-D55,0.5),0),"") -> 12411 | K55: No | L55: AWD | M55: Gasoline | N55: 29 | O55: GREAT | P55: 29201 | Q55: 0.048 | R55: GREAT | S55: 340 | T55: Yes | U55: 3 | V55: Yes | W55: 12 | X55: Yes | Y55: Yes | Z55: No | AA55: Yes | AB55: Yes | AC55: Yes | AD55: Yes | AE55: No | AF55: No | AG55: No | AH55: No | AI55: Yes | AJ55: No | AK55: Silver | AL55: White | AM55: 1.5 L 4 Cyl | AN55: Jim Stykemain Ford | AO55: Garrett | AP55: IN | AQ55: 50.6 | AR55: 4.7 | AS55: 41 | AU55: 496.48 | AV55: 200 | AW55: 91.2 | AX55: 84.7 | AY55: 34.3 | AZ55: 54 | BA55: 0 | BB55: 32.6 | BC55: 5J6RW2H87NA000701 | BD55: 2022 Honda CR-V | BE55: https://www.carfax.com/vehicle/5J6RW2H87NA000701
A56: =RANK(B56,$B$5:$B$266) -> 52 | B56: =ROUND((AW56*'Scoring Weights'!$B$5+AX56*'Scoring Weights'!$B$6+AY56*'Scoring Weights'!$B$7+BA56*'Scoring Weights'!$B$8+AZ56*'Scoring Weights'!$B$9+BB56*'Scoring Weights'!$B$10)/MAX('Scoring Weights'!$B$11,1),1) -> 57.4 | C56: =IF(AND(H56<='Search Criteria'!$B$5,D56>='Search Criteria'!$B$6,AQ56<='Search Criteria'!$B$7,I56<=INDEX('Search Criteria'!$B$18:$B$20,MATCH(E56,'Search Criteria'!$A$18:$A$20,0)),OR(NOT('Search Criteria'!$B$8),L56<>"FWD"),OR(NOT('Search Criteria'!$B$9),T56="Yes"),OR(NOT('Search Criteria'!$B$10),W56>0),OR(NOT('Search Criteria'!$B$11),X56="Yes"),OR(NOT('Search Criteria'!$B$12),O56="GREAT",O56="GOOD"),OR(NOT('Search Criteria'!$B$13),K56="Yes")),"YES","no") -> no | D56: 2023 | E56: Honda | F56: CR-V | G56: Sport Touring | H56: 33741 | I56: 40529 | J56: =IFERROR(ROUND(I56/MAX(2026-D56,0.5),0),"") -> 13510 | K56: No | L56: AWD | M56: Hybrid | N56: 37 | O56: FAIR | P56: 30969 | Q56: -0.09 | R56: n/a | T56: No | U56: 1 | V56: Yes | W56: 12 | X56: Yes | Y56: Yes | Z56: Yes | AA56: Yes | AB56: Yes | AC56: Yes | AD56: Yes | AE56: Yes | AF56: Yes | AG56: Yes | AH56: Yes | AI56: Yes | AJ56: Yes | AK56: Blue | AL56: Black | AM56: 2.0 L 4 Cyl | AN56: Gurley Leep Honda | AO56: Elkhart | AP56: IN | AQ56: 0.4 | AR56: 4.6 | AS56: 1 | AU56: 602.73 | AV56: 261 | AW56: 86.4 | AX56: 39.3 | AY56: 40.7 | AZ56: 100 | BA56: 0 | BB56: 99.4 | BC56: 7FARS6H96PE001614 | BD56: 2023 Honda CR-V | BE56: https://www.carfax.com/vehicle/7FARS6H96PE001614
A57: =RANK(B57,$B$5:$B$266) -> 52 | B57: =ROUND((AW57*'Scoring Weights'!$B$5+AX57*'Scoring Weights'!$B$6+AY57*'Scoring Weights'!$B$7+BA57*'Scoring Weights'!$B$8+AZ57*'Scoring Weights'!$B$9+BB57*'Scoring Weights'!$B$10)/MAX('Scoring Weights'!$B$11,1),1) -> 57.4 | C57: =IF(AND(H57<='Search Criteria'!$B$5,D57>='Search Criteria'!$B$6,AQ57<='Search Criteria'!$B$7,I57<=INDEX('Search Criteria'!$B$18:$B$20,MATCH(E57,'Search Criteria'!$A$18:$A$20,0)),OR(NOT('Search Criteria'!$B$8),L57<>"FWD"),OR(NOT('Search Criteria'!$B$9),T57="Yes"),OR(NOT('Search Criteria'!$B$10),W57>0),OR(NOT('Search Criteria'!$B$11),X57="Yes"),OR(NOT('Search Criteria'!$B$12),O57="GREAT",O57="GOOD"),OR(NOT('Search Criteria'!$B$13),K57="Yes")),"YES","no") -> YES | D57: 2025 | E57: Honda | F57: CR-V | G57: Sport-L | H57: 35897 | I57: 27590 | J57: =IFERROR(ROUND(I57/MAX(2026-D57,0.5),0),"") -> 27590 | K57: No | L57: AWD | M57: Hybrid | N57: 37 | O57: GOOD | P57: 34139 | Q57: -0.052 | R57: GREAT | S57: 610 | T57: Yes | U57: 2 | V57: No | W57: 12 | X57: Yes | Y57: Yes | Z57: No | AA57: Yes | AB57: Yes | AC57: Yes | AD57: Yes | AE57: Yes | AF57: No | AG57: Yes | AH57: Yes | AI57: Yes | AJ57: No | AK57: Gray | AL57: Unspecified | AM57: 2.0 L 4 Cyl | AN57: Gurley Leep Honda | AO57: Elkhart | AP57: IN | AQ57: 0.4 | AR57: 4.6 | AS57: 16 | AT57: -43 | AU57: 641.25 | AV57: 261 | AW57: 81.4 | AX57: 57.7 | AY57: 42.4 | AZ57: 78 | BA57: 0 | BB57: 99.4 | BC57: 7FARS6H86SE022138 | BD57: 2025 Honda CR-V | BE57: https://www.carfax.com/vehicle/7FARS6H86SE022138
A58: =RANK(B58,$B$5:$B$266) -> 54 | B58: =ROUND((AW58*'Scoring Weights'!$B$5+AX58*'Scoring Weights'!$B$6+AY58*'Scoring Weights'!$B$7+BA58*'Scoring Weights'!$B$8+AZ58*'Scoring Weights'!$B$9+BB58*'Scoring Weights'!$B$10)/MAX('Scoring Weights'!$B$11,1),1) -> 57.3 | C58: =IF(AND(H58<='Search Criteria'!$B$5,D58>='Search Criteria'!$B$6,AQ58<='Search Criteria'!$B$7,I58<=INDEX('Search Criteria'!$B$18:$B$20,MATCH(E58,'Search Criteria'!$A$18:$A$20,0)),OR(NOT('Search Criteria'!$B$8),L58<>"FWD"),OR(NOT('Search Criteria'!$B$9),T58="Yes"),OR(NOT('Search Criteria'!$B$10),W58>0),OR(NOT('Search Criteria'!$B$11),X58="Yes"),OR(NOT('Search Criteria'!$B$12),O58="GREAT",O58="GOOD"),OR(NOT('Search Criteria'!$B$13),K58="Yes")),"YES","no") -> YES | D58: 2025 | E58: Honda | F58: HR-V | G58: Sport | H58: 27095 | I58: 21310 | J58: =IFERROR(ROUND(I58/MAX(2026-D58,0.5),0),"") -> 21310 | K58: No | L58: AWD | M58: Gasoline | N58: 27 | O58: GOOD | P58: 27112 | Q58: 0.001 | R58: GREAT | S58: 220 | T58: Yes | U58: 1 | V58: Yes | W58: 5 | X58: Yes | Y58: Yes | Z58: No | AA58: No | AB58: Yes | AC58: No | AD58: Yes | AE58: Yes | AF58: No | AG58: No | AH58: No | AI58: No | AJ58: No | AK58: Green | AL58: Black | AM58: 2.0 L 4 Cyl | AN58: Gurley Leep Honda | AO58: Elkhart | AP58: IN | AQ58: 0.4 | AR58: 4.6 | AS58: 2 | AU58: 484.01 | AV58: 261 | AW58: 94 | AX58: 65.5 | AY58: 48.7 | AZ58: 34 | BA58: 0 | BB58: 99.4 | BC58: 3CZRZ2H51SM757265 | BD58: 2025 Honda HR-V | BE58: https://www.carfax.com/vehicle/3CZRZ2H51SM757265
A59: =RANK(B59,$B$5:$B$266) -> 54 | B59: =ROUND((AW59*'Scoring Weights'!$B$5+AX59*'Scoring Weights'!$B$6+AY59*'Scoring Weights'!$B$7+BA59*'Scoring Weights'!$B$8+AZ59*'Scoring Weights'!$B$9+BB59*'Scoring Weights'!$B$10)/MAX('Scoring Weights'!$B$11,1),1) -> 57.3 | C59: =IF(AND(H59<='Search Criteria'!$B$5,D59>='Search Criteria'!$B$6,AQ59<='Search Criteria'!$B$7,I59<=INDEX('Search Criteria'!$B$18:$B$20,MATCH(E59,'Search Criteria'!$A$18:$A$20,0)),OR(NOT('Search Criteria'!$B$8),L59<>"FWD"),OR(NOT('Search Criteria'!$B$9),T59="Yes"),OR(NOT('Search Criteria'!$B$10),W59>0),OR(NOT('Search Criteria'!$B$11),X59="Yes"),OR(NOT('Search Criteria'!$B$12),O59="GREAT",O59="GOOD"),OR(NOT('Search Criteria'!$B$13),K59="Yes")),"YES","no") -> no | D59: 2024 | E59: Honda | F59: CR-V | G59: EXL | H59: 32499 | I59: 36807 | J59: =IFERROR(ROUND(I59/MAX(2026-D59,0.5),0),"") -> 18404 | K59: No | L59: AWD | M59: Gasoline | N59: 29 | O59: GOOD | P59: 32364 | Q59: -0.004 | R59: GREAT | S59: 320 | T59: No | U59: 1 | V59: Yes | W59: 8 | X59: Yes | Y59: Yes | Z59: No | AA59: Yes | AB59: Yes | AC59: Yes | AD59: Yes | AE59: Yes | AF59: No | AG59: Yes | AH59: Yes | AI59: Yes | AJ59: No | AK59: Gray | AL59: Gray | AM59: 1.5 L 4 Cyl | AN59: Jordan Toyota | AO59: Mishawaka | AP59: IN | AQ59: 10.6 | AR59: 4.7 | AS59: 4 | AU59: 580.55 | AV59: 250 | AW59: 84 | AX59: 64.8 | AY59: 33.2 | AZ59: 78 | BA59: 0 | BB59: 85.9 | BC59: 5J6RS4H71RL002887 | BD59: 2024 Honda CR-V | BE59: https://www.carfax.com/vehicle/5J6RS4H71RL002887
A60: =RANK(B60,$B$5:$B$266) -> 54 | B60: =ROUND((AW60*'Scoring Weights'!$B$5+AX60*'Scoring Weights'!$B$6+AY60*'Scoring Weights'!$B$7+BA60*'Scoring Weights'!$B$8+AZ60*'Scoring Weights'!$B$9+BB60*'Scoring Weights'!$B$10)/MAX('Scoring Weights'!$B$11,1),1) -> 57.3 | C60: =IF(AND(H60<='Search Criteria'!$B$5,D60>='Search Criteria'!$B$6,AQ60<='Search Criteria'!$B$7,I60<=INDEX('Search Criteria'!$B$18:$B$20,MATCH(E60,'Search Criteria'!$A$18:$A$20,0)),OR(NOT('Search Criteria'!$B$8),L60<>"FWD"),OR(NOT('Search Criteria'!$B$9),T60="Yes"),OR(NOT('Search Criteria'!$B$10),W60>0),OR(NOT('Search Criteria'!$B$11),X60="Yes"),OR(NOT('Search Criteria'!$B$12),O60="GREAT",O60="GOOD"),OR(NOT('Search Criteria'!$B$13),K60="Yes")),"YES","no") -> no | D60: 2025 | E60: Honda | F60: CR-V | G60: EXL | H60: 37257 | I60: 25961 | J60: =IFERROR(ROUND(I60/MAX(2026-D60,0.5),0),"") -> 25961 | K60: No | L60: AWD | M60: Gasoline | N60: 28 | O60: None | P60: 34251 | Q60: -0.088 | R60: GREAT | S60: 150 | T60: Yes | U60: 1 | V60: Yes | W60: 10 | X60: Yes | Y60: Yes | Z60: No | AA60: Yes | AB60: Yes | AC60: Yes | AD60: Yes | AE60: No | AF60: No | AG60: Yes | AH60: Yes | AI60: Yes | AJ60: No | AK60: Blue | AL60: Black | AM60: 1.5 L 4 Cyl | AN60: Michiana Chrysler Dodge Jeep Ram Fiat | AO60: Mishawaka | AP60: IN | AQ60: 11 | AR60: 4.2 | AS60: 47 | AU60: 665.54 | AV60: 261 | AW60: 100 | AX60: 43.4 | AY60: 44 | AZ60: 68 | BA60: 0 | BB60: 85.3 | BC60: 7FARS4H70SE014290 | BD60: 2025 Honda CR-V | BE60: https://www.carfax.com/vehicle/7FARS4H70SE014290
A61: =RANK(B61,$B$5:$B$266) -> 57 | B61: =ROUND((AW61*'Scoring Weights'!$B$5+AX61*'Scoring Weights'!$B$6+AY61*'Scoring Weights'!$B$7+BA61*'Scoring Weights'!$B$8+AZ61*'Scoring Weights'!$B$9+BB61*'Scoring Weights'!$B$10)/MAX('Scoring Weights'!$B$11,1),1) -> 57.1 | C61: =IF(AND(H61<='Search Criteria'!$B$5,D61>='Search Criteria'!$B$6,AQ61<='Search Criteria'!$B$7,I61<=INDEX('Search Criteria'!$B$18:$B$20,MATCH(E61,'Search Criteria'!$A$18:$A$20,0)),OR(NOT('Search Criteria'!$B$8),L61<>"FWD"),OR(NOT('Search Criteria'!$B$9),T61="Yes"),OR(NOT('Search Criteria'!$B$10),W61>0),OR(NOT('Search Criteria'!$B$11),X61="Yes"),OR(NOT('Search Criteria'!$B$12),O61="GREAT",O61="GOOD"),OR(NOT('Search Criteria'!$B$13),K61="Yes")),"YES","no") -> no | D61: 2025 | E61: Honda | F61: CR-V | G61: EX | H61: 34261 | I61: 10604 | J61: =IFERROR(ROUND(I61/MAX(2026-D61,0.5),0),"") -> 10604 | K61: No | L61: AWD | M61: Gasoline | N61: 28 | O61: FAIR | P61: 35312 | Q61: 0.03 | R61: GREAT | S61: 150 | T61: Yes | U61: 1 | V61: Yes | W61: 5 | X61: Yes | Y61: Yes | Z61: No | AA61: Yes | AB61: Yes | AC61: No | AD61: No | AE61: No | AF61: No | AG61: No | AH61: No | AI61: Yes | AJ61: No | AK61: White | AL61: Black | AM61: 1.5 L 4 Cyl | AN61: Victory Honda Michigan City | AO61: MICHIGAN CITY | AP61: IN | AQ61: 46.9 | AR61: 4.7 | AS61: 10 | AU61: 612.02 | AV61: 261 | AW61: 94 | AX61: 57.2 | AY61: 77.9 | AZ61: 30 | BA61: 0 | BB61: 37.5 | BC61: 7FARS4H49SE019591 | BD61: 2025 Honda CR-V | BE61: https://www.carfax.com/vehicle/7FARS4H49SE019591
A62: =RANK(B62,$B$5:$B$266) -> 58 | B62: =ROUND((AW62*'Scoring Weights'!$B$5+AX62*'Scoring Weights'!$B$6+AY62*'Scoring Weights'!$B$7+BA62*'Scoring Weights'!$B$8+AZ62*'Scoring Weights'!$B$9+BB62*'Scoring Weights'!$B$10)/MAX('Scoring Weights'!$B$11,1),1) -> 56.8 | C62: =IF(AND(H62<='Search Criteria'!$B$5,D62>='Search Criteria'!$B$6,AQ62<='Search Criteria'!$B$7,I62<=INDEX('Search Criteria'!$B$18:$B$20,MATCH(E62,'Search Criteria'!$A$18:$A$20,0)),OR(NOT('Search Criteria'!$B$8),L62<>"FWD"),OR(NOT('Search Criteria'!$B$9),T62="Yes"),OR(NOT('Search Criteria'!$B$10),W62>0),OR(NOT('Search Criteria'!$B$11),X62="Yes"),OR(NOT('Search Criteria'!$B$12),O62="GREAT",O62="GOOD"),OR(NOT('Search Criteria'!$B$13),K62="Yes")),"YES","no") -> YES | D62: 2025 | E62: Toyota | F62: RAV4 | G62: XLE | H62: 36395 | I62: 11639 | J62: =IFERROR(ROUND(I62/MAX(2026-D62,0.5),0),"") -> 11639 | K62: No | L62: AWD | M62: Gasoline | N62: 28 | O62: GOOD | P62: 36242 | Q62: -0.004 | R62: GREAT | S62: 280 | T62: Yes | U62: 2 | V62: No | W62: 3 | X62: Yes | Y62: Yes | Z62: Yes | AA62: Yes | AB62: Yes | AC62: Yes | AD62: No | AE62: No | AF62: No | AG62: No | AH62: No | AI62: Yes | AJ62: No | AK62: Unspecified | AL62: Gray | AM62: 2.5 L 4 Cyl | AN62: Sunshine Toyota | AO62: Springfield | AP62: MI | AQ62: 56.8 | AR62: 4.6 | AS62: 2 | AU62: 650.14 | AV62: 345 | AW62: 77.2 | AX62: 64.8 | AY62: 77.8 | AZ62: 52 | BA62: 0 | BB62: 24.2 | BC62: 2T3P1RFV7SC536558 | BD62: 2025 Toyota RAV4 | BE62: https://www.carfax.com/vehicle/2T3P1RFV7SC536558
A63: =RANK(B63,$B$5:$B$266) -> 58 | B63: =ROUND((AW63*'Scoring Weights'!$B$5+AX63*'Scoring Weights'!$B$6+AY63*'Scoring Weights'!$B$7+BA63*'Scoring Weights'!$B$8+AZ63*'Scoring Weights'!$B$9+BB63*'Scoring Weights'!$B$10)/MAX('Scoring Weights'!$B$11,1),1) -> 56.8 | C63: =IF(AND(H63<='Search Criteria'!$B$5,D63>='Search Criteria'!$B$6,AQ63<='Search Criteria'!$B$7,I63<=INDEX('Search Criteria'!$B$18:$B$20,MATCH(E63,'Search Criteria'!$A$18:$A$20,0)),OR(NOT('Search Criteria'!$B$8),L63<>"FWD"),OR(NOT('Search Criteria'!$B$9),T63="Yes"),OR(NOT('Search Criteria'!$B$10),W63>0),OR(NOT('Search Criteria'!$B$11),X63="Yes"),OR(NOT('Search Criteria'!$B$12),O63="GREAT",O63="GOOD"),OR(NOT('Search Criteria'!$B$13),K63="Yes")),"YES","no") -> no | D63: 2025 | E63: Honda | F63: CR-V | G63: LX | H63: 29024 | I63: 19038 | J63: =IFERROR(ROUND(I63/MAX(2026-D63,0.5),0),"") -> 19038 | K63: No | L63: AWD | M63: Gasoline | N63: 28 | O63: GREAT | P63: 34730 | Q63: 0.164 | R63: GREAT | S63: 400 | T63: Yes | U63: 2 | V63: No | W63: 7 | X63: No | Y63: Yes | Z63: No | AA63: No | AB63: No | AC63: No | AD63: No | AE63: No | AF63: No | AG63: No | AH63: No | AI63: No | AJ63: No | AK63: Black | AL63: Black | AM63: 1.5 L 4 Cyl | AN63: Gurley Leep Hyundai Subaru | AO63: Mishawaka | AP63: IN | AQ63: 10.8 | AR63: 4.5 | AS63: 21 | AU63: 518.47 | AV63: 261 | AW63: 82 | AX63: 100 | AY63: 51 | AZ63: 0 | BA63: 0 | BB63: 85.6 | BC63: 2HKRS4H26SH450028 | BD63: 2025 Honda CR-V | BE63: https://www.carfax.com/vehicle/2HKRS4H26SH450028
A64: =RANK(B64,$B$5:$B$266) -> 60 | B64: =ROUND((AW64*'Scoring Weights'!$B$5+AX64*'Scoring Weights'!$B$6+AY64*'Scoring Weights'!$B$7+BA64*'Scoring Weights'!$B$8+AZ64*'Scoring Weights'!$B$9+BB64*'Scoring Weights'!$B$10)/MAX('Scoring Weights'!$B$11,1),1) -> 56.6 | C64: =IF(AND(H64<='Search Criteria'!$B$5,D64>='Search Criteria'!$B$6,AQ64<='Search Criteria'!$B$7,I64<=INDEX('Search Criteria'!$B$18:$B$20,MATCH(E64,'Search Criteria'!$A$18:$A$20,0)),OR(NOT('Search Criteria'!$B$8),L64<>"FWD"),OR(NOT('Search Criteria'!$B$9),T64="Yes"),OR(NOT('Search Criteria'!$B$10),W64>0),OR(NOT('Search Criteria'!$B$11),X64="Yes"),OR(NOT('Search Criteria'!$B$12),O64="GREAT",O64="GOOD"),OR(NOT('Search Criteria'!$B$13),K64="Yes")),"YES","no") -> YES | D64: 2023 | E64: Honda | F64: CR-V | G64: EX | H64: 29982 | I64: 34721 | J64: =IFERROR(ROUND(I64/MAX(2026-D64,0.5),0),"") -> 11574 | K64: No | L64: AWD | M64: Gasoline | N64: 29 | O64: GOOD | P64: 31370 | Q64: 0.044 | R64: GREAT | S64: 320 | T64: Yes | U64: 2 | V64: Yes | W64: 9 | X64: Yes | Y64: Yes | Z64: No | AA64: Yes | AB64: Yes | AC64: No | AD64: No | AE64: No | AF64: No | AG64: No | AH64: No | AI64: Yes | AJ64: No | AK64: Silver | AL64: Black | AM64: 1.5 L 4 Cyl | AN64: Gates Chevrolet South Bend | AO64: South Bend | AP64: IN | AQ64: 15.4 | AR64: 4.1 | AS64: 46 | AU64: 535.59 | AV64: 250 | AW64: 90 | AX64: 72 | AY64: 51.3 | AZ64: 30 | BA64: 0 | BB64: 79.5 | BC64: 7FARS4H46PE011892 | BD64: 2023 Honda CR-V | BE64: https://www.carfax.com/vehicle/7FARS4H46PE011892
A65: =RANK(B65,$B$5:$B$266) -> 60 | B65: =ROUND((AW65*'Scoring Weights'!$B$5+AX65*'Scoring Weights'!$B$6+AY65*'Scoring Weights'!$B$7+BA65*'Scoring Weights'!$B$8+AZ65*'Scoring Weights'!$B$9+BB65*'Scoring Weights'!$B$10)/MAX('Scoring Weights'!$B$11,1),1) -> 56.6 | C65: =IF(AND(H65<='Search Criteria'!$B$5,D65>='Search Criteria'!$B$6,AQ65<='Search Criteria'!$B$7,I65<=INDEX('Search Criteria'!$B$18:$B$20,MATCH(E65,'Search Criteria'!$A$18:$A$20,0)),OR(NOT('Search Criteria'!$B$8),L65<>"FWD"),OR(NOT('Search Criteria'!$B$9),T65="Yes"),OR(NOT('Search Criteria'!$B$10),W65>0),OR(NOT('Search Criteria'!$B$11),X65="Yes"),OR(NOT('Search Criteria'!$B$12),O65="GREAT",O65="GOOD"),OR(NOT('Search Criteria'!$B$13),K65="Yes")),"YES","no") -> no | D65: 2023 | E65: Toyota | F65: RAV4 | G65: LE | H65: 28997 | I65: 37013 | J65: =IFERROR(ROUND(I65/MAX(2026-D65,0.5),0),"") -> 12338 | K65: No | L65: AWD | M65: Gasoline | N65: 30 | O65: GOOD | P65: 31828 | Q65: 0.089 | R65: GREAT | S65: 440 | T65: Yes | U65: 1 | V65: Yes | W65: 9 | X65: No | Y65: Yes | Z65: No | AA65: No | AB65: No | AC65: No | AD65: No | AE65: No | AF65: No | AG65: No | AH65: No | AI65: No | AJ65: No | AK65: Gray | AL65: Gray | AM65: 2.5 L 4 Cyl | AN65: Jordan Lexus of Mishawaka | AO65: Mishawaka | AP65: IN | AQ65: 11.1 | AR65: 4.7 | AS65: 31 | AT65: 252 | AU65: 517.99 | AV65: 250 | AW65: 94.6 | AX65: 78.7 | AY65: 58.2 | AZ65: 0 | BA65: 0 | BB65: 85.2 | BC65: 2T3F1RFV7PC371775 | BD65: 2023 Toyota RAV4 | BE65: https://www.carfax.com/vehicle/2T3F1RFV7PC371775
A66: =RANK(B66,$B$5:$B$266) -> 62 | B66: =ROUND((AW66*'Scoring Weights'!$B$5+AX66*'Scoring Weights'!$B$6+AY66*'Scoring Weights'!$B$7+BA66*'Scoring Weights'!$B$8+AZ66*'Scoring Weights'!$B$9+BB66*'Scoring Weights'!$B$10)/MAX('Scoring Weights'!$B$11,1),1) -> 56.4 | C66: =IF(AND(H66<='Search Criteria'!$B$5,D66>='Search Criteria'!$B$6,AQ66<='Search Criteria'!$B$7,I66<=INDEX('Search Criteria'!$B$18:$B$20,MATCH(E66,'Search Criteria'!$A$18:$A$20,0)),OR(NOT('Search Criteria'!$B$8),L66<>"FWD"),OR(NOT('Search Criteria'!$B$9),T66="Yes"),OR(NOT('Search Criteria'!$B$10),W66>0),OR(NOT('Search Criteria'!$B$11),X66="Yes"),OR(NOT('Search Criteria'!$B$12),O66="GREAT",O66="GOOD"),OR(NOT('Search Criteria'!$B$13),K66="Yes")),"YES","no") -> no | D66: 2024 | E66: Toyota | F66: RAV4 | G66: XSE | H66: 36999 | I66: 34190 | J66: =IFERROR(ROUND(I66/MAX(2026-D66,0.5),0),"") -> 17095 | K66: No | L66: AWD | M66: Hybrid | N66: 39 | O66: None | P66: 33248 | Q66: -0.113 | R66: n/a | T66: Yes | U66: 1 | V66: Yes | W66: 8 | X66: Yes | Y66: Yes | Z66: Yes | AA66: Yes | AB66: Yes | AC66: Yes | AD66: Yes | AE66: No | AF66: Yes | AG66: Yes | AH66: Yes | AI66: Yes | AJ66: Yes | AK66: White | AL66: Black | AM66: 2.5 L 4 Cyl | AN66: Graff Toyota of Chesterton | AO66: Chesterton | AP66: IN | AQ66: 59.4 | AR66: 4.4 | AS66: 13 | AT66: 1800 | AU66: 660.93 | AW66: 97.6 | AX66: 39.7 | AY66: 48.3 | AZ66: 90 | BA66: 0 | BB66: 20.8 | BC66: JTME6RFV2RD564850 | BD66: 2024 Toyota RAV4 | BE66: https://www.carfax.com/vehicle/JTME6RFV2RD564850
A67: =RANK(B67,$B$5:$B$266) -> 63 | B67: =ROUND((AW67*'Scoring Weights'!$B$5+AX67*'Scoring Weights'!$B$6+AY67*'Scoring Weights'!$B$7+BA67*'Scoring Weights'!$B$8+AZ67*'Scoring Weights'!$B$9+BB67*'Scoring Weights'!$B$10)/MAX('Scoring Weights'!$B$11,1),1) -> 56.3 | C67: =IF(AND(H67<='Search Criteria'!$B$5,D67>='Search Criteria'!$B$6,AQ67<='Search Criteria'!$B$7,I67<=INDEX('Search Criteria'!$B$18:$B$20,MATCH(E67,'Search Criteria'!$A$18:$A$20,0)),OR(NOT('Search Criteria'!$B$8),L67<>"FWD"),OR(NOT('Search Criteria'!$B$9),T67="Yes"),OR(NOT('Search Criteria'!$B$10),W67>0),OR(NOT('Search Criteria'!$B$11),X67="Yes"),OR(NOT('Search Criteria'!$B$12),O67="GREAT",O67="GOOD"),OR(NOT('Search Criteria'!$B$13),K67="Yes")),"YES","no") -> no | D67: 2023 | E67: Honda | F67: CR-V | G67: EXL | H67: 32156 | I67: 36006 | J67: =IFERROR(ROUND(I67/MAX(2026-D67,0.5),0),"") -> 12002 | K67: No | L67: AWD | M67: Gasoline | N67: 29 | O67: GOOD | P67: 31281 | Q67: -0.028 | R67: GREAT | S67: 490 | T67: No | U67: 2 | V67: Yes | W67: 7 | X67: Yes | Y67: Yes | Z67: No | AA67: Yes | AB67: Yes | AC67: Yes | AD67: Yes | AE67: Yes | AF67: No | AG67: Yes | AH67: Yes | AI67: Yes | AJ67: No | AK67: White | AL67: Gray | AM67: 1.5 L 4 Cyl | AN67: Gurley Leep Honda | AO67: Elkhart | AP67: IN | AQ67: 0.4 | AR67: 4.6 | AS67: 2 | AU67: 574.42 | AV67: 261 | AW67: 69.8 | AX67: 61.2 | AY67: 49 | AZ67: 78 | BA67: 0 | BB67: 99.4 | BC67: 2HKRS4H74PH418360 | BD67: 2023 Honda CR-V | BE67: https://www.carfax.com/vehicle/2HKRS4H74PH418360
A68: =RANK(B68,$B$5:$B$266) -> 64 | B68: =ROUND((AW68*'Scoring Weights'!$B$5+AX68*'Scoring Weights'!$B$6+AY68*'Scoring Weights'!$B$7+BA68*'Scoring Weights'!$B$8+AZ68*'Scoring Weights'!$B$9+BB68*'Scoring Weights'!$B$10)/MAX('Scoring Weights'!$B$11,1),1) -> 56 | C68: =IF(AND(H68<='Search Criteria'!$B$5,D68>='Search Criteria'!$B$6,AQ68<='Search Criteria'!$B$7,I68<=INDEX('Search Criteria'!$B$18:$B$20,MATCH(E68,'Search Criteria'!$A$18:$A$20,0)),OR(NOT('Search Criteria'!$B$8),L68<>"FWD"),OR(NOT('Search Criteria'!$B$9),T68="Yes"),OR(NOT('Search Criteria'!$B$10),W68>0),OR(NOT('Search Criteria'!$B$11),X68="Yes"),OR(NOT('Search Criteria'!$B$12),O68="GREAT",O68="GOOD"),OR(NOT('Search Criteria'!$B$13),K68="Yes")),"YES","no") -> no | D68: 2024 | E68: Toyota | F68: RAV4 | G68: LE | H68: 33250 | I68: 21761 | J68: =IFERROR(ROUND(I68/MAX(2026-D68,0.5),0),"") -> 10881 | K68: No | L68: AWD | M68: Hybrid | N68: 39 | O68: GREAT | P68: 34240 | Q68: 0.029 | R68: GREAT | S68: 700 | T68: Yes | U68: 1 | V68: No | W68: 6 | X68: No | Y68: Yes | Z68: No | AA68: No | AB68: Yes | AC68: No | AD68: No | AE68: No | AF68: No | AG68: No | AH68: No | AI68: No | AJ68: No | AK68: Unspecified | AL68: Black | AM68: 2.5 L 4 Cyl | AN68: Evans Toyota | AO68: Fort Wayne | AP68: IN | AQ68: 59.9 | AR68: 4.5 | AS68: 121 | AU68: 593.96 | AV68: 262 | AW68: 85.4 | AX68: 81.8 | AY68: 72.6 | AZ68: 12 | BA68: 0 | BB68: 20.2 | BC68: 4T3MWRFV2RU158968 | BD68: 2024 Toyota RAV4 | BE68: https://www.carfax.com/vehicle/4T3MWRFV2RU158968
A69: =RANK(B69,$B$5:$B$266) -> 65 | B69: =ROUND((AW69*'Scoring Weights'!$B$5+AX69*'Scoring Weights'!$B$6+AY69*'Scoring Weights'!$B$7+BA69*'Scoring Weights'!$B$8+AZ69*'Scoring Weights'!$B$9+BB69*'Scoring Weights'!$B$10)/MAX('Scoring Weights'!$B$11,1),1) -> 55.8 | C69: =IF(AND(H69<='Search Criteria'!$B$5,D69>='Search Criteria'!$B$6,AQ69<='Search Criteria'!$B$7,I69<=INDEX('Search Criteria'!$B$18:$B$20,MATCH(E69,'Search Criteria'!$A$18:$A$20,0)),OR(NOT('Search Criteria'!$B$8),L69<>"FWD"),OR(NOT('Search Criteria'!$B$9),T69="Yes"),OR(NOT('Search Criteria'!$B$10),W69>0),OR(NOT('Search Criteria'!$B$11),X69="Yes"),OR(NOT('Search Criteria'!$B$12),O69="GREAT",O69="GOOD"),OR(NOT('Search Criteria'!$B$13),K69="Yes")),"YES","no") -> YES | D69: 2025 | E69: Honda | F69: CR-V | G69: EX | H69: 30472 | I69: 41083 | J69: =IFERROR(ROUND(I69/MAX(2026-D69,0.5),0),"") -> 41083 | K69: No | L69: AWD | M69: Gasoline | N69: 28 | O69: GREAT | P69: 33206 | Q69: 0.082 | R69: GREAT | S69: 400 | T69: Yes | U69: 1 | V69: Yes | W69: 5 | X69: Yes | Y69: Yes | Z69: No | AA69: Yes | AB69: Yes | AC69: No | AD69: No | AE69: No | AF69: No | AG69: No | AH69: No | AI69: Yes | AJ69: No | AK69: Gray | AL69: Black | AM69: 1.5 L 4 Cyl | AN69: Zeigler Chrysler Jeep Dodge Ram of Kalamazoo | AO69: Kalamazoo | AP69: MI | AQ69: 41.6 | AR69: 4.6 | AS69: 65 | AU69: 544.34 | AV69: 314 | AW69: 94 | AX69: 89.9 | AY69: 28.9 | AZ69: 30 | BA69: 0 | BB69: 44.5 | BC69: 2HKRS4H49SH430180 | BD69: 2025 Honda CR-V | BE69: https://www.carfax.com/vehicle/2HKRS4H49SH430180
A70: =RANK(B70,$B$5:$B$266) -> 65 | B70: =ROUND((AW70*'Scoring Weights'!$B$5+AX70*'Scoring Weights'!$B$6+AY70*'Scoring Weights'!$B$7+BA70*'Scoring Weights'!$B$8+AZ70*'Scoring Weights'!$B$9+BB70*'Scoring Weights'!$B$10)/MAX('Scoring Weights'!$B$11,1),1) -> 55.8 | C70: =IF(AND(H70<='Search Criteria'!$B$5,D70>='Search Criteria'!$B$6,AQ70<='Search Criteria'!$B$7,I70<=INDEX('Search Criteria'!$B$18:$B$20,MATCH(E70,'Search Criteria'!$A$18:$A$20,0)),OR(NOT('Search Criteria'!$B$8),L70<>"FWD"),OR(NOT('Search Criteria'!$B$9),T70="Yes"),OR(NOT('Search Criteria'!$B$10),W70>0),OR(NOT('Search Criteria'!$B$11),X70="Yes"),OR(NOT('Search Criteria'!$B$12),O70="GREAT",O70="GOOD"),OR(NOT('Search Criteria'!$B$13),K70="Yes")),"YES","no") -> no | D70: 2024 | E70: Toyota | F70: RAV4 | G70: XLE | H70: 28895 | I70: 71448 | J70: =IFERROR(ROUND(I70/MAX(2026-D70,0.5),0),"") -> 35724 | K70: No | L70: AWD | M70: Hybrid | N70: 39 | O70: GREAT | P70: 30273 | Q70: 0.046 | R70: GREAT | S70: 390 | T70: Yes | U70: 1 | V70: No | W70: 7 | X70: No | Y70: Yes | Z70: Yes | AA70: Yes | AB70: Yes | AC70: Yes | AD70: No | AE70: No | AF70: No | AG70: No | AH70: No | AI70: Yes | AJ70: No | AK70: Black | AL70: Gray | AM70: 2.5 L 4 Cyl | AN70: David Rice Auto Sales LLC | AO70: Schoolcraft | AP70: MI | AQ70: 33.3 | AR70: 4.1 | AS70: 51 | AU70: 516.17 | AV70: 230 | AW70: 90.8 | AX70: 84.3 | AY70: 20 | AZ70: 52 | BA70: 0 | BB70: 55.7 | BC70: 2T3RWRFV7RW217549 | BD70: 2024 Toyota RAV4 | BE70: https://www.carfax.com/vehicle/2T3RWRFV7RW217549
A71: =RANK(B71,$B$5:$B$266) -> 67 | B71: =ROUND((AW71*'Scoring Weights'!$B$5+AX71*'Scoring Weights'!$B$6+AY71*'Scoring Weights'!$B$7+BA71*'Scoring Weights'!$B$8+AZ71*'Scoring Weights'!$B$9+BB71*'Scoring Weights'!$B$10)/MAX('Scoring Weights'!$B$11,1),1) -> 55.7 | C71: =IF(AND(H71<='Search Criteria'!$B$5,D71>='Search Criteria'!$B$6,AQ71<='Search Criteria'!$B$7,I71<=INDEX('Search Criteria'!$B$18:$B$20,MATCH(E71,'Search Criteria'!$A$18:$A$20,0)),OR(NOT('Search Criteria'!$B$8),L71<>"FWD"),OR(NOT('Search Criteria'!$B$9),T71="Yes"),OR(NOT('Search Criteria'!$B$10),W71>0),OR(NOT('Search Criteria'!$B$11),X71="Yes"),OR(NOT('Search Criteria'!$B$12),O71="GREAT",O71="GOOD"),OR(NOT('Search Criteria'!$B$13),K71="Yes")),"YES","no") -> no | D71: 2025 | E71: Toyota | F71: RAV4 | G71: LE | H71: 35426 | I71: 35980 | J71: =IFERROR(ROUND(I71/MAX(2026-D71,0.5),0),"") -> 35980 | K71: Yes | L71: AWD | M71: Hybrid | N71: 39 | O71: FAIR | P71: 34299 | Q71: -0.033 | R71: n/a | T71: No | U71: 1 | V71: Yes | W71: 6 | X71: No | Y71: Yes | Z71: No | AA71: No | AB71: No | AC71: No | AD71: No | AE71: No | AF71: No | AG71: No | AH71: Yes | AI71: No | AJ71: No | AK71: Silver | AL71: Black | AM71: 2.5 L 4 Cyl | AN71: Crown Toyota Volkswagen | AO71: Holland | AP71: MI | AQ71: 74.7 | AR71: 4.7 | AS71: 32 | AT71: -36 | AU71: 632.83 | AV71: 314 | AW71: 81.6 | AX71: 47.8 | AY71: 44.8 | AZ71: 6 | BA71: 100 | BB71: 0.4 | BC71: JTMLWRFV1SD337243 | BD71: 2025 Toyota RAV4 | BE71: https://www.carfax.com/vehicle/JTMLWRFV1SD337243
A72: =RANK(B72,$B$5:$B$266) -> 68 | B72: =ROUND((AW72*'Scoring Weights'!$B$5+AX72*'Scoring Weights'!$B$6+AY72*'Scoring Weights'!$B$7+BA72*'Scoring Weights'!$B$8+AZ72*'Scoring Weights'!$B$9+BB72*'Scoring Weights'!$B$10)/MAX('Scoring Weights'!$B$11,1),1) -> 55.5 | C72: =IF(AND(H72<='Search Criteria'!$B$5,D72>='Search Criteria'!$B$6,AQ72<='Search Criteria'!$B$7,I72<=INDEX('Search Criteria'!$B$18:$B$20,MATCH(E72,'Search Criteria'!$A$18:$A$20,0)),OR(NOT('Search Criteria'!$B$8),L72<>"FWD"),OR(NOT('Search Criteria'!$B$9),T72="Yes"),OR(NOT('Search Criteria'!$B$10),W72>0),OR(NOT('Search Criteria'!$B$11),X72="Yes"),OR(NOT('Search Criteria'!$B$12),O72="GREAT",O72="GOOD"),OR(NOT('Search Criteria'!$B$13),K72="Yes")),"YES","no") -> no | D72: 2024 | E72: Honda | F72: CR-V | G72: EXL | H72: 32083 | I72: 37527 | J72: =IFERROR(ROUND(I72/MAX(2026-D72,0.5),0),"") -> 18764 | K72: No | L72: AWD | M72: Gasoline | N72: 29 | O72: GOOD | P72: 32314 | Q72: 0.007 | R72: GREAT | S72: 320 | T72: No | U72: 1 | V72: Yes | W72: 8 | X72: Yes | Y72: Yes | Z72: No | AA72: Yes | AB72: Yes | AC72: Yes | AD72: Yes | AE72: Yes | AF72: No | AG72: Yes | AH72: Yes | AI72: Yes | AJ72: No | AK72: Gray | AL72: Black | AM72: 1.5 L 4 Cyl | AN72: Zeigler Chrysler Jeep Dodge Ram of Kalamazoo | AO72: Kalamazoo | AP72: MI | AQ72: 41.6 | AR72: 4.6 | AS72: 54 | AT72: 1576 | AU72: 573.12 | AV72: 314 | AW72: 84 | AX72: 66.5 | AY72: 32.5 | AZ72: 78 | BA72: 0 | BB72: 44.5 | BC72: 7FARS4H79RE001869 | BD72: 2024 Honda CR-V | BE72: https://www.carfax.com/vehicle/7FARS4H79RE001869
A73: =RANK(B73,$B$5:$B$266) -> 69 | B73: =ROUND((AW73*'Scoring Weights'!$B$5+AX73*'Scoring Weights'!$B$6+AY73*'Scoring Weights'!$B$7+BA73*'Scoring Weights'!$B$8+AZ73*'Scoring Weights'!$B$9+BB73*'Scoring Weights'!$B$10)/MAX('Scoring Weights'!$B$11,1),1) -> 55.2 | C73: =IF(AND(H73<='Search Criteria'!$B$5,D73>='Search Criteria'!$B$6,AQ73<='Search Criteria'!$B$7,I73<=INDEX('Search Criteria'!$B$18:$B$20,MATCH(E73,'Search Criteria'!$A$18:$A$20,0)),OR(NOT('Search Criteria'!$B$8),L73<>"FWD"),OR(NOT('Search Criteria'!$B$9),T73="Yes"),OR(NOT('Search Criteria'!$B$10),W73>0),OR(NOT('Search Criteria'!$B$11),X73="Yes"),OR(NOT('Search Criteria'!$B$12),O73="GREAT",O73="GOOD"),OR(NOT('Search Criteria'!$B$13),K73="Yes")),"YES","no") -> no | D73: 2023 | E73: Honda | F73: CR-V | G73: EXL | H73: 33514 | I73: 30206 | J73: =IFERROR(ROUND(I73/MAX(2026-D73,0.5),0),"") -> 10069 | K73: No | L73: AWD | M73: Gasoline | N73: 29 | O73: FAIR | P73: 31682 | Q73: -0.058 | R73: GREAT | S73: 570 | T73: Yes | U73: 1 | V73: Yes | W73: 4 | X73: Yes | Y73: Yes | Z73: No | AA73: Yes | AB73: Yes | AC73: Yes | AD73: Yes | AE73: No | AF73: No | AG73: Yes | AH73: Yes | AI73: Yes | AJ73: No | AK73: Gray | AL73: Black | AM73: 1.5 L 4 Cyl | AN73: Zeigler Chrysler Jeep Dodge Ram of Kalamazoo | AO73: Kalamazoo | AP73: MI | AQ73: 41.6 | AR73: 4.6 | AS73: 23 | AU73: 598.68 | AV73: 314 | AW73: 88.6 | AX73: 44.1 | AY73: 59.6 | AZ73: 68 | BA73: 0 | BB73: 44.5 | BC73: 2HKRS4H76PH436567 | BD73: 2023 Honda CR-V | BE73: https://www.carfax.com/vehicle/2HKRS4H76PH436567
A74: =RANK(B74,$B$5:$B$266) -> 69 | B74: =ROUND((AW74*'Scoring Weights'!$B$5+AX74*'Scoring Weights'!$B$6+AY74*'Scoring Weights'!$B$7+BA74*'Scoring Weights'!$B$8+AZ74*'Scoring Weights'!$B$9+BB74*'Scoring Weights'!$B$10)/MAX('Scoring Weights'!$B$11,1),1) -> 55.2 | C74: =IF(AND(H74<='Search Criteria'!$B$5,D74>='Search Criteria'!$B$6,AQ74<='Search Criteria'!$B$7,I74<=INDEX('Search Criteria'!$B$18:$B$20,MATCH(E74,'Search Criteria'!$A$18:$A$20,0)),OR(NOT('Search Criteria'!$B$8),L74<>"FWD"),OR(NOT('Search Criteria'!$B$9),T74="Yes"),OR(NOT('Search Criteria'!$B$10),W74>0),OR(NOT('Search Criteria'!$B$11),X74="Yes"),OR(NOT('Search Criteria'!$B$12),O74="GREAT",O74="GOOD"),OR(NOT('Search Criteria'!$B$13),K74="Yes")),"YES","no") -> no | D74: 2024 | E74: Honda | F74: CR-V | G74: EXL | H74: 28446 | I74: 73012 | J74: =IFERROR(ROUND(I74/MAX(2026-D74,0.5),0),"") -> 36506 | K74: No | L74: AWD | M74: Gasoline | N74: 29 | O74: GREAT | P74: 29862 | Q74: 0.047 | R74: GREAT | S74: 600 | T74: No | U74: 1 | V74: Yes | W74: 20 | X74: Yes | Y74: Yes | Z74: No | AA74: Yes | AB74: Yes | AC74: Yes | AD74: Yes | AE74: Yes | AF74: No | AG74: Yes | AH74: Yes | AI74: Yes | AJ74: No | AK74: Red | AL74: Black | AM74: 1.5 L 4 Cyl | AN74: Jordan Ford | AO74: Mishawaka | AP74: IN | AQ74: 10.7 | AR74: 4.6 | AS74: 44 | AT74: 553 | AU74: 508.15 | AV74: 250 | AW74: 82.2 | AX74: 84.6 | AY74: 0 | AZ74: 78 | BA74: 0 | BB74: 85.7 | BC74: 2HKRS4H72RH461761 | BD74: 2024 Honda CR-V | BE74: https://www.carfax.com/vehicle/2HKRS4H72RH461761
A75: =RANK(B75,$B$5:$B$266) -> 71 | B75: =ROUND((AW75*'Scoring Weights'!$B$5+AX75*'Scoring Weights'!$B$6+AY75*'Scoring Weights'!$B$7+BA75*'Scoring Weights'!$B$8+AZ75*'Scoring Weights'!$B$9+BB75*'Scoring Weights'!$B$10)/MAX('Scoring Weights'!$B$11,1),1) -> 55.1 | C75: =IF(AND(H75<='Search Criteria'!$B$5,D75>='Search Criteria'!$B$6,AQ75<='Search Criteria'!$B$7,I75<=INDEX('Search Criteria'!$B$18:$B$20,MATCH(E75,'Search Criteria'!$A$18:$A$20,0)),OR(NOT('Search Criteria'!$B$8),L75<>"FWD"),OR(NOT('Search Criteria'!$B$9),T75="Yes"),OR(NOT('Search Criteria'!$B$10),W75>0),OR(NOT('Search Criteria'!$B$11),X75="Yes"),OR(NOT('Search Criteria'!$B$12),O75="GREAT",O75="GOOD"),OR(NOT('Search Criteria'!$B$13),K75="Yes")),"YES","no") -> no | D75: 2026 | E75: Honda | F75: CR-V | G75: EX | H75: 34661 | I75: 11169 | J75: =IFERROR(ROUND(I75/MAX(2026-D75,0.5),0),"") -> 22338 | K75: No | L75: AWD | M75: Gasoline | N75: 29 | O75: FAIR | P75: 36411 | Q75: 0.048 | R75: GREAT | S75: 150 | T75: Yes | U75: 1 | V75: Yes | W75: 4 | X75: Yes | Y75: Yes | Z75: No | AA75: Yes | AB75: Yes | AC75: No | AD75: No | AE75: No | AF75: No | AG75: Yes | AH75: No | AI75: Yes | AJ75: No | AK75: White | AL75: Black | AM75: 1.5 L 4 Cyl | AN75: Victory Honda Michigan City | AO75: MICHIGAN CITY | AP75: IN | AQ75: 46.9 | AR75: 4.7 | AS75: 2 | AU75: 619.17 | AV75: 261 | AW75: 92.8 | AX75: 60 | AY75: 58.8 | AZ75: 38 | BA75: 0 | BB75: 37.5 | BC75: 5J6RS4H45TL000833 | BD75: 2026 Honda CR-V | BE75: https://www.carfax.com/vehicle/5J6RS4H45TL000833
A76: =RANK(B76,$B$5:$B$266) -> 71 | B76: =ROUND((AW76*'Scoring Weights'!$B$5+AX76*'Scoring Weights'!$B$6+AY76*'Scoring Weights'!$B$7+BA76*'Scoring Weights'!$B$8+AZ76*'Scoring Weights'!$B$9+BB76*'Scoring Weights'!$B$10)/MAX('Scoring Weights'!$B$11,1),1) -> 55.1 | C76: =IF(AND(H76<='Search Criteria'!$B$5,D76>='Search Criteria'!$B$6,AQ76<='Search Criteria'!$B$7,I76<=INDEX('Search Criteria'!$B$18:$B$20,MATCH(E76,'Search Criteria'!$A$18:$A$20,0)),OR(NOT('Search Criteria'!$B$8),L76<>"FWD"),OR(NOT('Search Criteria'!$B$9),T76="Yes"),OR(NOT('Search Criteria'!$B$10),W76>0),OR(NOT('Search Criteria'!$B$11),X76="Yes"),OR(NOT('Search Criteria'!$B$12),O76="GREAT",O76="GOOD"),OR(NOT('Search Criteria'!$B$13),K76="Yes")),"YES","no") -> no | D76: 2024 | E76: Honda | F76: CR-V | G76: EX | H76: 33044 | I76: 26705 | J76: =IFERROR(ROUND(I76/MAX(2026-D76,0.5),0),"") -> 13353 | K76: No | L76: AWD | M76: Gasoline | N76: 29 | O76: None | P76: 33062 | Q76: 0.001 | R76: GREAT | S76: 560 | T76: Yes | U76: 1 | V76: Yes | W76: 10 | X76: Yes | Y76: Yes | Z76: No | AA76: Yes | AB76: Yes | AC76: No | AD76: No | AE76: Yes | AF76: No | AG76: No | AH76: No | AI76: Yes | AJ76: No | AK76: Black | AL76: Black | AM76: 1.5 L 4 Cyl | AN76: Zeigler Chrysler Jeep Dodge Ram of Kalamazoo | AO76: Kalamazoo | AP76: MI | AQ76: 41.6 | AR76: 4.6 | AS76: 26 | AT76: -1044 | AU76: 590.28 | AV76: 314 | AW76: 95.8 | AX76: 56.7 | AY76: 54.9 | AZ76: 40 | BA76: 0 | BB76: 44.5 | BC76: 2HKRS4H43RH412414 | BD76: 2024 Honda CR-V | BE76: https://www.carfax.com/vehicle/2HKRS4H43RH412414
A77: =RANK(B77,$B$5:$B$266) -> 71 | B77: =ROUND((AW77*'Scoring Weights'!$B$5+AX77*'Scoring Weights'!$B$6+AY77*'Scoring Weights'!$B$7+BA77*'Scoring Weights'!$B$8+AZ77*'Scoring Weights'!$B$9+BB77*'Scoring Weights'!$B$10)/MAX('Scoring Weights'!$B$11,1),1) -> 55.1 | C77: =IF(AND(H77<='Search Criteria'!$B$5,D77>='Search Criteria'!$B$6,AQ77<='Search Criteria'!$B$7,I77<=INDEX('Search Criteria'!$B$18:$B$20,MATCH(E77,'Search Criteria'!$A$18:$A$20,0)),OR(NOT('Search Criteria'!$B$8),L77<>"FWD"),OR(NOT('Search Criteria'!$B$9),T77="Yes"),OR(NOT('Search Criteria'!$B$10),W77>0),OR(NOT('Search Criteria'!$B$11),X77="Yes"),OR(NOT('Search Criteria'!$B$12),O77="GREAT",O77="GOOD"),OR(NOT('Search Criteria'!$B$13),K77="Yes")),"YES","no") -> YES | D77: 2022 | E77: Toyota | F77: 4Runner | G77: TRD Off Road Premium | H77: 38104 | I77: 78455 | J77: =IFERROR(ROUND(I77/MAX(2026-D77,0.5),0),"") -> 19614 | K77: No | L77: 4WD | M77: Gasoline | N77: 17 | O77: GREAT | R77: GREAT | S77: 220 | T77: Yes | U77: 1 | V77: No | W77: 17 | X77: Yes | Y77: Yes | Z77: No | AA77: Yes | AB77: Yes | AC77: No | AD77: No | AE77: No | AF77: Yes | AG77: No | AH77: No | AI77: Yes | AJ77: No | AK77: White | AL77: Black | AM77: 4.0 L 6 Cyl | AN77: Gurley Leep Kia | AO77: Mishawaka | AP77: IN | AQ77: 11 | AR77: 4.2 | AS77: 20 | AU77: 680.67 | AV77: 261 | AW77: 94.4 | AX77: 82.9 | AY77: 15.1 | AZ77: 38 | BA77: 0 | BB77: 85.3 | BC77: JTERU5JR4N6047375 | BD77: 2022 Toyota 4Runner | BE77: https://www.carfax.com/vehicle/JTERU5JR4N6047375
A78: =RANK(B78,$B$5:$B$266) -> 74 | B78: =ROUND((AW78*'Scoring Weights'!$B$5+AX78*'Scoring Weights'!$B$6+AY78*'Scoring Weights'!$B$7+BA78*'Scoring Weights'!$B$8+AZ78*'Scoring Weights'!$B$9+BB78*'Scoring Weights'!$B$10)/MAX('Scoring Weights'!$B$11,1),1) -> 54.5 | C78: =IF(AND(H78<='Search Criteria'!$B$5,D78>='Search Criteria'!$B$6,AQ78<='Search Criteria'!$B$7,I78<=INDEX('Search Criteria'!$B$18:$B$20,MATCH(E78,'Search Criteria'!$A$18:$A$20,0)),OR(NOT('Search Criteria'!$B$8),L78<>"FWD"),OR(NOT('Search Criteria'!$B$9),T78="Yes"),OR(NOT('Search Criteria'!$B$10),W78>0),OR(NOT('Search Criteria'!$B$11),X78="Yes"),OR(NOT('Search Criteria'!$B$12),O78="GREAT",O78="GOOD"),OR(NOT('Search Criteria'!$B$13),K78="Yes")),"YES","no") -> YES | D78: 2025 | E78: Honda | F78: CR-V | G78: EX | H78: 30814 | I78: 38801 | J78: =IFERROR(ROUND(I78/MAX(2026-D78,0.5),0),"") -> 38801 | K78: No | L78: AWD | M78: Gasoline | N78: 28 | O78: GREAT | P78: 33364 | Q78: 0.076 | R78: GREAT | S78: 370 | T78: Yes | U78: 1 | V78: Yes | W78: 7 | X78: Yes | Y78: Yes | Z78: No | AA78: Yes | AB78: Yes | AC78: No | AD78: No | AE78: No | AF78: No | AG78: No | AH78: No | AI78: Yes | AJ78: No | AK78: White | AL78: Black | AM78: 1.5 L 4 Cyl | AN78: Zeigler GMC of Holland | AO78: Holland | AP78: MI | AQ78: 74.5 | AR78: 4.6 | AS78: 58 | AU78: 550.45 | AV78: 314 | AW78: 96.4 | AX78: 89 | AY78: 31.2 | AZ78: 30 | BA78: 0 | BB78: 0.7 | BC78: 2HKRS4H44SH448795 | BD78: 2025 Honda CR-V | BE78: https://www.carfax.com/vehicle/2HKRS4H44SH448795
A79: =RANK(B79,$B$5:$B$266) -> 75 | B79: =ROUND((AW79*'Scoring Weights'!$B$5+AX79*'Scoring Weights'!$B$6+AY79*'Scoring Weights'!$B$7+BA79*'Scoring Weights'!$B$8+AZ79*'Scoring Weights'!$B$9+BB79*'Scoring Weights'!$B$10)/MAX('Scoring Weights'!$B$11,1),1) -> 54.4 | C79: =IF(AND(H79<='Search Criteria'!$B$5,D79>='Search Criteria'!$B$6,AQ79<='Search Criteria'!$B$7,I79<=INDEX('Search Criteria'!$B$18:$B$20,MATCH(E79,'Search Criteria'!$A$18:$A$20,0)),OR(NOT('Search Criteria'!$B$8),L79<>"FWD"),OR(NOT('Search Criteria'!$B$9),T79="Yes"),OR(NOT('Search Criteria'!$B$10),W79>0),OR(NOT('Search Criteria'!$B$11),X79="Yes"),OR(NOT('Search Criteria'!$B$12),O79="GREAT",O79="GOOD"),OR(NOT('Search Criteria'!$B$13),K79="Yes")),"YES","no") -> no | D79: 2024 | E79: Toyota | F79: RAV4 | G79: LE | H79: 26946 | I79: 53822 | J79: =IFERROR(ROUND(I79/MAX(2026-D79,0.5),0),"") -> 26911 | K79: No | L79: AWD | M79: Gasoline | N79: 30 | O79: GREAT | P79: 31680 | Q79: 0.149 | R79: GREAT | S79: 340 | T79: Yes | U79: 1 | V79: No | W79: 3 | X79: No | Y79: Yes | Z79: No | AA79: No | AB79: No | AC79: No | AD79: No | AE79: No | AF79: No | AG79: No | AH79: No | AI79: No | AJ79: No | AK79: White | AL79: Black | AM79: 2.5 L 4 Cyl | AN79: Jordan Ford | AO79: Mishawaka | AP79: IN | AQ79: 10.7 | AR79: 4.6 | AS79: 50 | AT79: 2053 | AU79: 481.35 | AV79: 250 | AW79: 86 | AX79: 99.9 | AY79: 32.3 | AZ79: 0 | BA79: 0 | BB79: 85.7 | BC79: 2T3F1RFV3RC436690 | BD79: 2024 Toyota RAV4 | BE79: https://www.carfax.com/vehicle/2T3F1RFV3RC436690
A80: =RANK(B80,$B$5:$B$266) -> 75 | B80: =ROUND((AW80*'Scoring Weights'!$B$5+AX80*'Scoring Weights'!$B$6+AY80*'Scoring Weights'!$B$7+BA80*'Scoring Weights'!$B$8+AZ80*'Scoring Weights'!$B$9+BB80*'Scoring Weights'!$B$10)/MAX('Scoring Weights'!$B$11,1),1) -> 54.4 | C80: =IF(AND(H80<='Search Criteria'!$B$5,D80>='Search Criteria'!$B$6,AQ80<='Search Criteria'!$B$7,I80<=INDEX('Search Criteria'!$B$18:$B$20,MATCH(E80,'Search Criteria'!$A$18:$A$20,0)),OR(NOT('Search Criteria'!$B$8),L80<>"FWD"),OR(NOT('Search Criteria'!$B$9),T80="Yes"),OR(NOT('Search Criteria'!$B$10),W80>0),OR(NOT('Search Criteria'!$B$11),X80="Yes"),OR(NOT('Search Criteria'!$B$12),O80="GREAT",O80="GOOD"),OR(NOT('Search Criteria'!$B$13),K80="Yes")),"YES","no") -> no | D80: 2024 | E80: Honda | F80: HR-V | G80: LX | H80: 26738 | I80: 7365 | J80: =IFERROR(ROUND(I80/MAX(2026-D80,0.5),0),"") -> 3683 | K80: No | L80: AWD | M80: Gasoline | N80: 27 | O80: FAIR | P80: 27847 | Q80: 0.04 | R80: GREAT | S80: 560 | T80: Yes | U80: 1 | V80: Yes | W80: 5 | X80: No | Y80: Yes | Z80: No | AA80: No | AB80: No | AC80: No | AD80: No | AE80: No | AF80: No | AG80: No | AH80: No | AI80: No | AJ80: No | AK80: White | AL80: Gray | AM80: 2.0 L 4 Cyl | AN80: Ben Davis Chevrolet | AO80: Auburn | AP80: IN | AQ80: 53 | AR80: 4.4 | AS80: 47 | AT80: 5 | AU80: 477.64 | AV80: 261 | AW80: 89.8 | AX80: 58.7 | AY80: 92.6 | AZ80: 0 | BA80: 0 | BB80: 29.3 | BC80: 3CZRZ2H36RM771834 | BD80: 2024 Honda HR-V | BE80: https://www.carfax.com/vehicle/3CZRZ2H36RM771834
A81: =RANK(B81,$B$5:$B$266) -> 77 | B81: =ROUND((AW81*'Scoring Weights'!$B$5+AX81*'Scoring Weights'!$B$6+AY81*'Scoring Weights'!$B$7+BA81*'Scoring Weights'!$B$8+AZ81*'Scoring Weights'!$B$9+BB81*'Scoring Weights'!$B$10)/MAX('Scoring Weights'!$B$11,1),1) -> 54.3 | C81: =IF(AND(H81<='Search Criteria'!$B$5,D81>='Search Criteria'!$B$6,AQ81<='Search Criteria'!$B$7,I81<=INDEX('Search Criteria'!$B$18:$B$20,MATCH(E81,'Search Criteria'!$A$18:$A$20,0)),OR(NOT('Search Criteria'!$B$8),L81<>"FWD"),OR(NOT('Search Criteria'!$B$9),T81="Yes"),OR(NOT('Search Criteria'!$B$10),W81>0),OR(NOT('Search Criteria'!$B$11),X81="Yes"),OR(NOT('Search Criteria'!$B$12),O81="GREAT",O81="GOOD"),OR(NOT('Search Criteria'!$B$13),K81="Yes")),"YES","no") -> no | D81: 2026 | E81: Honda | F81: CR-V | G81: TrailSport | H81: 37990 | I81: 25209 | J81: =IFERROR(ROUND(I81/MAX(2026-D81,0.5),0),"") -> 50418 | K81: No | L81: AWD | M81: Hybrid | N81: 35 | O81: None | P81: 35441 | Q81: -0.072 | R81: n/a | T81: Yes | U81: 1 | V81: Yes | W81: 2 | X81: Yes | Y81: Yes | Z81: Yes | AA81: Yes | AB81: Yes | AC81: Yes | AD81: Yes | AE81: Yes | AF81: No | AG81: Yes | AH81: No | AI81: Yes | AJ81: No | AK81: White | AL81: Black | AM81: 2.0 L 4 Cyl | AN81: Battle Creek Honda | AO81: Springfield | AP81: MI | AQ81: 56.8 | AR81: 4.5 | AS81: 2 | AU81: 678.64 | AV81: 314 | AW81: 90.4 | AX81: 45.8 | AY81: 44.8 | AZ81: 82 | BA81: 0 | BB81: 24.3 | BC81: 7FARS6H63TE025272 | BD81: 2026 Honda CR-V | BE81: https://www.carfax.com/vehicle/7FARS6H63TE025272
A82: =RANK(B82,$B$5:$B$266) -> 77 | B82: =ROUND((AW82*'Scoring Weights'!$B$5+AX82*'Scoring Weights'!$B$6+AY82*'Scoring Weights'!$B$7+BA82*'Scoring Weights'!$B$8+AZ82*'Scoring Weights'!$B$9+BB82*'Scoring Weights'!$B$10)/MAX('Scoring Weights'!$B$11,1),1) -> 54.3 | C82: =IF(AND(H82<='Search Criteria'!$B$5,D82>='Search Criteria'!$B$6,AQ82<='Search Criteria'!$B$7,I82<=INDEX('Search Criteria'!$B$18:$B$20,MATCH(E82,'Search Criteria'!$A$18:$A$20,0)),OR(NOT('Search Criteria'!$B$8),L82<>"FWD"),OR(NOT('Search Criteria'!$B$9),T82="Yes"),OR(NOT('Search Criteria'!$B$10),W82>0),OR(NOT('Search Criteria'!$B$11),X82="Yes"),OR(NOT('Search Criteria'!$B$12),O82="GREAT",O82="GOOD"),OR(NOT('Search Criteria'!$B$13),K82="Yes")),"YES","no") -> no | D82: 2025 | E82: Toyota | F82: RAV4 | G82: XLE | H82: 30268 | I82: 35816 | J82: =IFERROR(ROUND(I82/MAX(2026-D82,0.5),0),"") -> 35816 | K82: No | L82: FWD | M82: Gasoline | N82: 30 | O82: GREAT | P82: 34312 | Q82: 0.118 | R82: GREAT | S82: 360 | T82: Yes | U82: 1 | V82: No | W82: 2 | X82: No | Y82: Yes | Z82: No | AA82: No | AB82: Yes | AC82: No | AD82: No | AE82: No | AF82: No | AG82: No | AH82: No | AI82: Yes | AJ82: No | AK82: Blue | AL82: Black | AM82: 2.5 L 4 Cyl | AN82: Zeigler Subaru of Fort Wayne | AO82: Fort Wayne | AP82: IN | AQ82: 59.8 | AR82: 4.8 | AS82: 80 | AT82: 2932 | AU82: 540.69 | AV82: 268 | AW82: 84.8 | AX82: 95.2 | AY82: 44.9 | AZ82: 16 | BA82: 0 | BB82: 20.3 | BC82: 2T3W1RFV3SW388998 | BD82: 2025 Toyota RAV4 | BE82: https://www.carfax.com/vehicle/2T3W1RFV3SW388998
A83: =RANK(B83,$B$5:$B$266) -> 77 | B83: =ROUND((AW83*'Scoring Weights'!$B$5+AX83*'Scoring Weights'!$B$6+AY83*'Scoring Weights'!$B$7+BA83*'Scoring Weights'!$B$8+AZ83*'Scoring Weights'!$B$9+BB83*'Scoring Weights'!$B$10)/MAX('Scoring Weights'!$B$11,1),1) -> 54.3 | C83: =IF(AND(H83<='Search Criteria'!$B$5,D83>='Search Criteria'!$B$6,AQ83<='Search Criteria'!$B$7,I83<=INDEX('Search Criteria'!$B$18:$B$20,MATCH(E83,'Search Criteria'!$A$18:$A$20,0)),OR(NOT('Search Criteria'!$B$8),L83<>"FWD"),OR(NOT('Search Criteria'!$B$9),T83="Yes"),OR(NOT('Search Criteria'!$B$10),W83>0),OR(NOT('Search Criteria'!$B$11),X83="Yes"),OR(NOT('Search Criteria'!$B$12),O83="GREAT",O83="GOOD"),OR(NOT('Search Criteria'!$B$13),K83="Yes")),"YES","no") -> YES | D83: 2022 | E83: Honda | F83: CR-V | G83: EXL | H83: 28212 | I83: 54671 | J83: =IFERROR(ROUND(I83/MAX(2026-D83,0.5),0),"") -> 13668 | K83: No | L83: AWD | M83: Hybrid | N83: 38 | O83: GOOD | P83: 28853 | Q83: 0.022 | R83: GOOD | S83: 100 | T83: Yes | U83: 2 | V83: Yes | W83: 17 | X83: Yes | Y83: Yes | Z83: Yes | AA83: Yes | AB83: Yes | AC83: Yes | AD83: Yes | AE83: Yes | AF83: No | AG83: No | AH83: No | AI83: Yes | AJ83: No | AK83: White | AL83: White | AM83: 2.0 L 4 Cyl | AN83: Gurley Leep Kia | AO83: Mishawaka | AP83: IN | AQ83: 11 | AR83: 4.2 | AS83: 32 | AT83: 944 | AU83: 503.97 | AV83: 261 | AW83: 76.3 | AX83: 68.7 | AY83: 26.2 | AZ83: 74 | BA83: 0 | BB83: 85.3 | BC83: 5J6RT6H88NL023795 | BD83: 2022 Honda CR-V | BE83: https://www.carfax.com/vehicle/5J6RT6H88NL023795
A84: =RANK(B84,$B$5:$B$266) -> 80 | B84: =ROUND((AW84*'Scoring Weights'!$B$5+AX84*'Scoring Weights'!$B$6+AY84*'Scoring Weights'!$B$7+BA84*'Scoring Weights'!$B$8+AZ84*'Scoring Weights'!$B$9+BB84*'Scoring Weights'!$B$10)/MAX('Scoring Weights'!$B$11,1),1) -> 54.2 | C84: =IF(AND(H84<='Search Criteria'!$B$5,D84>='Search Criteria'!$B$6,AQ84<='Search Criteria'!$B$7,I84<=INDEX('Search Criteria'!$B$18:$B$20,MATCH(E84,'Search Criteria'!$A$18:$A$20,0)),OR(NOT('Search Criteria'!$B$8),L84<>"FWD"),OR(NOT('Search Criteria'!$B$9),T84="Yes"),OR(NOT('Search Criteria'!$B$10),W84>0),OR(NOT('Search Criteria'!$B$11),X84="Yes"),OR(NOT('Search Criteria'!$B$12),O84="GREAT",O84="GOOD"),OR(NOT('Search Criteria'!$B$13),K84="Yes")),"YES","no") -> no | D84: 2024 | E84: Toyota | F84: RAV4 | G84: LE | H84: 31981 | I84: 22730 | J84: =IFERROR(ROUND(I84/MAX(2026-D84,0.5),0),"") -> 11365 | K84: No | L84: AWD | M84: Gasoline | N84: 30 | O84: None | P84: 34163 | Q84: 0.064 | R84: GREAT | S84: 220 | T84: Yes | U84: 1 | V84: Yes | W84: 7 | X84: No | Y84: Yes | Z84: No | AA84: No | AB84: No | AC84: No | AD84: No | AE84: No | AF84: No | AG84: No | AH84: No | AI84: No | AJ84: No | AK84: Gray | AL84: Black | AM84: 2.5 L 4 Cyl | AN84: Graff Chevrolet GMC of Michigan City | AO84: Michigan City | AP84: IN | AQ84: 47.5 | AR84: 4.6 | AS84: 25 | AU84: 571.29 | AW84: 96.4 | AX84: 66.2 | AY84: 70.7 | AZ84: 0 | BA84: 0 | BB84: 36.7 | BC84: 2T3F1RFV5RW434888 | BD84: 2024 Toyota RAV4 | BE84: https://www.carfax.com/vehicle/2T3F1RFV5RW434888
A85: =RANK(B85,$B$5:$B$266) -> 81 | B85: =ROUND((AW85*'Scoring Weights'!$B$5+AX85*'Scoring Weights'!$B$6+AY85*'Scoring Weights'!$B$7+BA85*'Scoring Weights'!$B$8+AZ85*'Scoring Weights'!$B$9+BB85*'Scoring Weights'!$B$10)/MAX('Scoring Weights'!$B$11,1),1) -> 54 | C85: =IF(AND(H85<='Search Criteria'!$B$5,D85>='Search Criteria'!$B$6,AQ85<='Search Criteria'!$B$7,I85<=INDEX('Search Criteria'!$B$18:$B$20,MATCH(E85,'Search Criteria'!$A$18:$A$20,0)),OR(NOT('Search Criteria'!$B$8),L85<>"FWD"),OR(NOT('Search Criteria'!$B$9),T85="Yes"),OR(NOT('Search Criteria'!$B$10),W85>0),OR(NOT('Search Criteria'!$B$11),X85="Yes"),OR(NOT('Search Criteria'!$B$12),O85="GREAT",O85="GOOD"),OR(NOT('Search Criteria'!$B$13),K85="Yes")),"YES","no") -> no | D85: 2023 | E85: Honda | F85: CR-V | G85: Sport | H85: 30990 | I85: 26754 | J85: =IFERROR(ROUND(I85/MAX(2026-D85,0.5),0),"") -> 8918 | K85: No | L85: AWD | M85: Hybrid | N85: 37 | O85: GOOD | P85: 31920 | Q85: 0.029 | R85: n/a | T85: No | U85: 1 | V85: Yes | W85: 2 | X85: Yes | Y85: Yes | Z85: No | AA85: Yes | AB85: Yes | AC85: No | AD85: No | AE85: Yes | AF85: No | AG85: No | AH85: No | AI85: Yes | AJ85: No | AK85: Silver | AL85: Black | AM85: 2.0 L 4 Cyl | AN85: Battle Creek Honda | AO85: Springfield | AP85: MI | AQ85: 56.8 | AR85: 4.5 | AS85: 16 | AU85: 553.59 | AV85: 314 | AW85: 76.8 | AX85: 69.8 | AY85: 66 | AZ85: 40 | BA85: 0 | BB85: 24.3 | BC85: 7FARS6H59PE019523 | BD85: 2023 Honda CR-V | BE85: https://www.carfax.com/vehicle/7FARS6H59PE019523
A86: =RANK(B86,$B$5:$B$266) -> 81 | B86: =ROUND((AW86*'Scoring Weights'!$B$5+AX86*'Scoring Weights'!$B$6+AY86*'Scoring Weights'!$B$7+BA86*'Scoring Weights'!$B$8+AZ86*'Scoring Weights'!$B$9+BB86*'Scoring Weights'!$B$10)/MAX('Scoring Weights'!$B$11,1),1) -> 54 | C86: =IF(AND(H86<='Search Criteria'!$B$5,D86>='Search Criteria'!$B$6,AQ86<='Search Criteria'!$B$7,I86<=INDEX('Search Criteria'!$B$18:$B$20,MATCH(E86,'Search Criteria'!$A$18:$A$20,0)),OR(NOT('Search Criteria'!$B$8),L86<>"FWD"),OR(NOT('Search Criteria'!$B$9),T86="Yes"),OR(NOT('Search Criteria'!$B$10),W86>0),OR(NOT('Search Criteria'!$B$11),X86="Yes"),OR(NOT('Search Criteria'!$B$12),O86="GREAT",O86="GOOD"),OR(NOT('Search Criteria'!$B$13),K86="Yes")),"YES","no") -> no | D86: 2023 | E86: Toyota | F86: RAV4 | G86: XLE Premium | H86: 36406 | I86: 24665 | J86: =IFERROR(ROUND(I86/MAX(2026-D86,0.5),0),"") -> 8222 | K86: No | L86: AWD | M86: Gasoline | N86: 28 | O86: FAIR | P86: 32814 | Q86: -0.109 | R86: GREAT | S86: 380 | T86: No | U86: 1 | V86: Yes | W86: 9 | X86: Yes | Y86: Yes | Z86: Yes | AA86: Yes | AB86: Yes | AC86: Yes | AD86: Yes | AE86: No | AF86: No | AG86: No | AH86: No | AI86: Yes | AJ86: No | AK86: Silver | AL86: Black | AM86: 2.5 L 4 Cyl | AN86: Evans Toyota | AO86: Fort Wayne | AP86: IN | AQ86: 59.9 | AR86: 4.5 | AS86: 44 | AU86: 650.34 | AV86: 262 | AW86: 85.2 | AX86: 36.3 | AY86: 77.2 | AZ86: 64 | BA86: 0 | BB86: 20.2 | BC86: 2T3A1RFV1PC393250 | BD86: 2023 Toyota RAV4 | BE86: https://www.carfax.com/vehicle/2T3A1RFV1PC393250
A87: =RANK(B87,$B$5:$B$266) -> 83 | B87: =ROUND((AW87*'Scoring Weights'!$B$5+AX87*'Scoring Weights'!$B$6+AY87*'Scoring Weights'!$B$7+BA87*'Scoring Weights'!$B$8+AZ87*'Scoring Weights'!$B$9+BB87*'Scoring Weights'!$B$10)/MAX('Scoring Weights'!$B$11,1),1) -> 53.9 | C87: =IF(AND(H87<='Search Criteria'!$B$5,D87>='Search Criteria'!$B$6,AQ87<='Search Criteria'!$B$7,I87<=INDEX('Search Criteria'!$B$18:$B$20,MATCH(E87,'Search Criteria'!$A$18:$A$20,0)),OR(NOT('Search Criteria'!$B$8),L87<>"FWD"),OR(NOT('Search Criteria'!$B$9),T87="Yes"),OR(NOT('Search Criteria'!$B$10),W87>0),OR(NOT('Search Criteria'!$B$11),X87="Yes"),OR(NOT('Search Criteria'!$B$12),O87="GREAT",O87="GOOD"),OR(NOT('Search Criteria'!$B$13),K87="Yes")),"YES","no") -> YES | D87: 2024 | E87: Subaru | F87: Outback | G87: Premium | H87: 25059 | I87: 33775 | J87: =IFERROR(ROUND(I87/MAX(2026-D87,0.5),0),"") -> 16888 | K87: No | L87: AWD | M87: Gasoline | N87: 28 | O87: GREAT | P87: 29156 | Q87: 0.141 | R87: GOOD | S87: 260 | T87: Yes | U87: 1 | V87: Yes | W87: 4 | X87: Yes | Y87: Yes | Z87: No | AA87: Yes | AB87: Yes | AC87: No | AD87: Yes | AE87: No | AF87: Yes | AG87: No | AH87: No | AI87: Yes | AJ87: No | AK87: Blue | AL87: Black | AM87: 2.5 L 4 Cyl | AN87: Chevrolet of Merrillville | AO87: Merrillville | AP87: IN | AQ87: 71.2 | AR87: 4 | AS87: 20 | AT87: 915 | AU87: 447.64 | AV87: 261 | AW87: 78.5 | AX87: 98.6 | AY87: 25.5 | AZ87: 50 | BA87: 0 | BB87: 5.1 | BC87: 4S4BTAFC6R3136342 | BD87: 2024 Subaru Outback | BE87: https://www.carfax.com/vehicle/4S4BTAFC6R3136342
A88: =RANK(B88,$B$5:$B$266) -> 83 | B88: =ROUND((AW88*'Scoring Weights'!$B$5+AX88*'Scoring Weights'!$B$6+AY88*'Scoring Weights'!$B$7+BA88*'Scoring Weights'!$B$8+AZ88*'Scoring Weights'!$B$9+BB88*'Scoring Weights'!$B$10)/MAX('Scoring Weights'!$B$11,1),1) -> 53.9 | C88: =IF(AND(H88<='Search Criteria'!$B$5,D88>='Search Criteria'!$B$6,AQ88<='Search Criteria'!$B$7,I88<=INDEX('Search Criteria'!$B$18:$B$20,MATCH(E88,'Search Criteria'!$A$18:$A$20,0)),OR(NOT('Search Criteria'!$B$8),L88<>"FWD"),OR(NOT('Search Criteria'!$B$9),T88="Yes"),OR(NOT('Search Criteria'!$B$10),W88>0),OR(NOT('Search Criteria'!$B$11),X88="Yes"),OR(NOT('Search Criteria'!$B$12),O88="GREAT",O88="GOOD"),OR(NOT('Search Criteria'!$B$13),K88="Yes")),"YES","no") -> no | D88: 2022 | E88: Toyota | F88: RAV4 | G88: XLE Premium | H88: 28699 | I88: 46086 | J88: =IFERROR(ROUND(I88/MAX(2026-D88,0.5),0),"") -> 11522 | K88: No | L88: FWD | M88: Gasoline | N88: 30 | O88: None | P88: 29909 | Q88: 0.04 | R88: GREAT | S88: 350 | T88: No | U88: 1 | V88: Yes | W88: 8 | X88: No | Y88: Yes | Z88: No | AA88: Yes | AB88: Yes | AC88: Yes | AD88: Yes | AE88: No | AF88: No | AG88: No | AH88: No | AI88: Yes | AJ88: No | AK88: Black | AL88: Black | AM88: 2.5 L 4 Cyl | AN88: Graff Toyota of Chesterton | AO88: Chesterton | AP88: IN | AQ88: 59.4 | AR88: 4.4 | AS88: 13 | AT88: 2606 | AU88: 512.67 | AW88: 84 | AX88: 62.7 | AY88: 53.9 | AZ88: 54 | BA88: 0 | BB88: 20.8 | BC88: 2T3C1RFV7NW232034 | BD88: 2022 Toyota RAV4 | BE88: https://www.carfax.com/vehicle/2T3C1RFV7NW232034
